Workbook
Name Tableau: Tableau1[]

Sheet Tableau recherche
A1: Région | B1: Département | C1: N° Département | D1: Rue | E1: Code Postal | F1: Ville | G1: Adresse | H1: Lien Google Maps | I1: Emplacement | J1: Typologie | K1: Nature | L1: Durée du bail | M1: Cession / Droit au bail | N1: Numéro de lot | O1: Surface GLA | P1: Répartition surface GLA | Q1: Surface maximale | R1: Surface utile | S1: Répartition surface utile | T1: Loyer annuel | U1: Loyer Mensuel | V1: Loyer €/m² | W1: Loyer variable | X1: Charges annuelles | Y1: Charges Mensuelles | Z1: Charges €/m² | AA1: Taxe foncière | AB1: Taxe foncière €/m² | AC1: Marketing | AD1: Marketing €/m² | AE1: Total (L+C+M) | AF1: Dépôt de garantie | AG1: GAPD | AH1: Gestion | AI1: Etat de livraison | AJ1: Extraction | AK1: Restauration | AL1: Environnement Commercial | AM1: Commentaires | AN1: Honoraires de rédaction | AO1: Honoraires commerciaux | AP1: Latitude | AQ1: Longitude | AR1: Référence annonce | AS1: Photos annonce | AT1: Actif | AU1: Valeur BP | AV1: Contact | AW1: Page Web | AX1: Date d'ajout
A2: =VLOOKUP(Tableau1[[#This Row],[N° Département]],Feuil1!$C$6:$E$106,3) -> Nouvelle-Aquitaine | B2: =VLOOKUP(Tableau1[[#This Row],[N° Département]],Feuil1!$C$6:$E$106,2) -> Charente | C2: =LEFT(Tableau1[[#This Row],[Code Postal]],2)*1 -> 16 | D2: 53 Rue Hergé | E2: 16000 | F2: Angoulême | G2: =Tableau1[[#This Row],[Rue]]&CHAR(10)&Tableau1[[#This Row],[Code Postal]]&" - "&Tableau1[[#This Row],[Ville]] -> 53 Rue Hergé 16000 - Angoulême | H2: https://www.google.com/maps/place/53+Rue+Herg%C3%A9,+16000+Angoul%C3%Aame | I2: Centre Ville | J2: Pied d'immeuble | K2: / | M2: / | N2: / | O2: 451 | P2: 357 + 40 + 21 + 31 | Q2: / | R2: 423 | S2: 342 + 34 + 17 + 28 | T2: =Tableau1[[#This Row],[Loyer €/m²]]*Tableau1[[#This Row],[Surface GLA]] -> 67650 | U2: =IFERROR(Tableau1[[#This Row],[Loyer annuel]]/12,"") -> 5637.5 | V2: 150 | W2: / | X2: =Tableau1[[#This Row],[Charges €/m²]]*Tableau1[[#This Row],[Surface GLA]] -> 12177 | Y2: =IFERROR(Tableau1[[#This Row],[Charges annuelles]]/12,"") -> 1014.75 | Z2: 27 | AA2: =IFERROR(Tableau1[[#This Row],[Taxe foncière €/m²]]*Tableau1[[#This Row],[Surface GLA]],) -> 0 | AB2: / | AC2: =IFERROR(Tableau1[[#This Row],[Marketing €/m²]]*Tableau1[[#This Row],[Surface GLA]],) -> 0 | AD2: / | AE2: =IFERROR(Tableau1[[#This Row],[Loyer annuel]]+Tableau1[[#This Row],[Charges annuelles]]+Tableau1[[#This Row],[Taxe foncière]]+Tableau1[[#This Row],[Marketing]],"") -> 79827 | AF2: / | AG2: / | AH2: / | AI2: En l'état du précédent locataire | AJ2: A étudier | AK2: Chaude et froide | AL2: Foot Locker, Free, SFR, Avril Cosmétique, Tamaris, Devred, Damart, American Vintage, Restauration | AM2: En plein centre-ville. Ancien Sephora. RDC + 3 niveaux. Taxes comprises | AO2: 30% du loyer facial avec un minimum de 15 000 € HT | AP2: 45.648526 | AQ2: 0.158468 | AR2: 1 | AS2: https://pub-843c46afc4cb41489909bce00c9b143d.r2.dev/1%20-%20Angoul%C3%AAme/1.jpg; https://pub-843c46afc4cb41489909bce00c9b143d.r2.dev/1%20-%20Angoul%C3%AAme/2.jpg; https://pub-843c46afc4cb41489909bce00c9b143d.r2.dev/1%20-%20Angoul%C3%AAme/3.jpg; https://pub-843c46afc4cb41489909bce00c9b143d.r2.dev/1%20-%20Angoul%C3%AAme/4%20ANGOULEME%207%20-%20RC%20SEPHORA.jpg; https://pub-843c46afc4cb41489909bce00c9b143d.r2.dev/1%20-%20Angoul%C3%AAme/5%20ANGOULEME%207%20-%201er%20Etage%2053-55%20rue%20herg%C3%A9.jpg; https://pub-843c46afc4cb41489909bce00c9b143d.r2.dev/1%20-%20Angoul%C3%AAme/6%20ANGOULEME%207%20-%202e%20Etage%2053-55%20rue%20herg%C3%A9.jpg; https://pub-843c46afc4cb41489909bce00c9b143d.r2.dev/1%20-%20Angoul%C3%AAme/7%20ANGOULEME%207%20-%203e%20Etage%2053-55%20rue%20herg%C3%A9.jpg | AT2: Oui | AU2: 120 €/m² = 50 760 € | AV2: Praemia
A3: =VLOOKUP(Tableau1[[#This Row],[N° Département]],Feuil1!$C$6:$E$106,3) -> Bourgogne-Franche-Comté | B3: =VLOOKUP(Tableau1[[#This Row],[N° Département]],Feuil1!$C$6:$E$106,2) -> Doubs | C3: =LEFT(Tableau1[[#This Row],[Code Postal]],2)*1 -> 25 | D3: 44 Grande Rue | E3: 25000 | F3: Besançon | G3: =Tableau1[[#This Row],[Rue]]&CHAR(10)&Tableau1[[#This Row],[Code Postal]]&" - "&Tableau1[[#This Row],[Ville]] -> 44 Grande Rue 25000 - Besançon | H3: https://www.google.com/maps/place/44+Grande+Rue,+25000+Besan%C3%A7on | I3: Centre Ville | J3: Pied d'immeuble | K3: / | M3: / | N3: / | O3: 325 | P3: 214 (SS) + 110 | Q3: / | R3: / | S3: / | T3: =Tableau1[[#This Row],[Loyer €/m²]]*Tableau1[[#This Row],[Surface GLA]] -> 42250 | U3: =IFERROR(Tableau1[[#This Row],[Loyer annuel]]/12,"") -> 3520.8333 | V3: 130 | W3: / | X3: =Tableau1[[#This Row],[Charges €/m²]]*Tableau1[[#This Row],[Surface GLA]] -> 8450 | Y3: =IFERROR(Tableau1[[#This Row],[Charges annuelles]]/12,"") -> 704.16667 | Z3: 26 | AA3: =IFERROR(Tableau1[[#This Row],[Taxe foncière €/m²]]*Tableau1[[#This Row],[Surface GLA]],) -> 0 | AB3: / | AC3: =IFERROR(Tableau1[[#This Row],[Marketing €/m²]]*Tableau1[[#This Row],[Surface GLA]],) -> 0 | AD3: / | AE3: =IFERROR(Tableau1[[#This Row],[Loyer annuel]]+Tableau1[[#This Row],[Charges annuelles]]+Tableau1[[#This Row],[Taxe foncière]]+Tableau1[[#This Row],[Marketing]],"") -> 50700 | AF3: / | AG3: / | AH3: / | AI3: En l'état du précédent locataire | AJ3: Non | AK3: Froide | AL3: Avril Cosmétique, Générale d'Optique, Darjeeling, Pimkie, Promod, Calzedonia, Eram, SFR, Le Comptoir de Mathilde, Restauration | AM3: Ancien cabinet médical. Local voisin de Bagelstein. Taxes comprises | AO3: 30% du loyer facial avec un minimum de 15 000 € HT | AP3: 47.238162 | AQ3: 6.0234543 | AR3: 2 | AS3: https://pub-843c46afc4cb41489909bce00c9b143d.r2.dev/2%20-%20Besan%C3%A7on/1.jpg; https://pub-843c46afc4cb41489909bce00c9b143d.r2.dev/2%20-%20Besan%C3%A7on/2.jpg; https://pub-843c46afc4cb41489909bce00c9b143d.r2.dev/2%20-%20Besan%C3%A7on/3.jpg; https://pub-843c46afc4cb41489909bce00c9b143d.r2.dev/2%20-%20Besan%C3%A7on/4%20Plan%20RDC.jpg; https://pub-843c46afc4cb41489909bce00c9b143d.r2.dev/2%20-%20Besan%C3%A7on/5%20Plan%20R-1.jpg | AT3: Oui | AU3: 100 €/m² = 32 500 € | AV3: Praemia
A4: =VLOOKUP(Tableau1[[#This Row],[N° Département]],Feuil1!$C$6:$E$106,3) -> Centre-Val de Loire | B4: =VLOOKUP(Tableau1[[#This Row],[N° Département]],Feuil1!$C$6:$E$106,2) -> Loir-et-Cher | C4: =LEFT(Tableau1[[#This Row],[Code Postal]],2)*1 -> 41 | D4: 90 Rue du Commerce | E4: 41000 | F4: Blois | G4: =Tableau1[[#This Row],[Rue]]&CHAR(10)&Tableau1[[#This Row],[Code Postal]]&" - "&Tableau1[[#This Row],[Ville]] -> 90 Rue du Commerce 41000 - Blois | H4: https://www.google.com/maps/place/90+Rue+du+Commerce,+41000+Blois | I4: Centre Ville | J4: Pied d'immeuble | K4: / | M4: / | N4: / | O4: 264 | P4: 205 + 59 | Q4: / | R4: 244 | S4: 190 + 54 | T4: =Tableau1[[#This Row],[Loyer €/m²]]*Tableau1[[#This Row],[Surface GLA]] -> 92400 | U4: =IFERROR(Tableau1[[#This Row],[Loyer annuel]]/12,"") -> 7700 | V4: 350 | W4: / | X4: =Tableau1[[#This Row],[Charges €/m²]]*Tableau1[[#This Row],[Surface GLA]] -> 12408 | Y4: =IFERROR(Tableau1[[#This Row],[Charges annuelles]]/12,"") -> 1034 | Z4: 47 | AA4: =IFERROR(Tableau1[[#This Row],[Taxe foncière €/m²]]*Tableau1[[#This Row],[Surface GLA]],) -> 0 | AB4: / | AC4: =IFERROR(Tableau1[[#This Row],[Marketing €/m²]]*Tableau1[[#This Row],[Surface GLA]],) -> 0 | AD4: / | AE4: =IFERROR(Tableau1[[#This Row],[Loyer annuel]]+Tableau1[[#This Row],[Charges annuelles]]+Tableau1[[#This Row],[Taxe foncière]]+Tableau1[[#This Row],[Marketing]],"") -> 104808 | AF4: / | AG4: / | AH4: / | AI4: En l'état du précédent locataire | AJ4: Non | AK4: Froide | AL4: My Candle Shop, Naf Naf, Petit Bateau, Armand Thierry, Maison 123, Jott, Calzedonia, Caroll, Pimkie, Restauration | AM4: Ancien Etam. Local en parfait état, utilisé en BDD. Verrière intérieur. Taxes comprises | AO4: 30% du loyer facial avec un minimum de 15 000 € HT | AP4: 47.586994 | AQ4: 1.331958 | AR4: 3 | AS4: https://pub-843c46afc4cb41489909bce00c9b143d.r2.dev/3%20-%20Blois/1.jpg; https://pub-843c46afc4cb41489909bce00c9b143d.r2.dev/3%20-%20Blois/2.jpg; https://pub-843c46afc4cb41489909bce00c9b143d.r2.dev/3%20-%20Blois/3.jpg; https://pub-843c46afc4cb41489909bce00c9b143d.r2.dev/3%20-%20Blois/4.jpg; https://pub-843c46afc4cb41489909bce00c9b143d.r2.dev/3%20-%20Blois/5%20Plan%20RDC.jpg; https://pub-843c46afc4cb41489909bce00c9b143d.r2.dev/3%20-%20Blois/6%20Plan%20R%2B1.jpg | AT4: Oui | AU4: 300 €/m² = 73 500 € | AV4: Praemia
A5: =VLOOKUP(Tableau1[[#This Row],[N° Département]],Feuil1!$C$6:$E$106,3) -> Bourgogne-Franche-Comté | B5: =VLOOKUP(Tableau1[[#This Row],[N° Département]],Feuil1!$C$6:$E$106,2) -> Doubs | C5: =LEFT(Tableau1[[#This Row],[Code Postal]],2)*1 -> 25 | D5: 7 Rue de Sochaux | E5: 25400 | F5: Exincourt | G5: =Tableau1[[#This Row],[Rue]]&CHAR(10)&Tableau1[[#This Row],[Code Postal]]&" - "&Tableau1[[#This Row],[Ville]] -> 7 Rue de Sochaux 25400 - Exincourt | H5: https://maps.app.goo.gl/YuAJQRM2HM3gYVyJ6 | I5: Périphérie | J5: Boîte | K5: / | M5: / | N5: / | O5: 9030 | P5: 2 999 (SS) + 2 978 + 2981 + 72 (mezz) | Q5: / | R5: 8628 | S5: 2 843 (SS) + 2 870 + 2 871 (R+1) + 44 (mezz) | T5: =Tableau1[[#This Row],[Loyer €/m²]]*Tableau1[[#This Row],[Surface GLA]] -> 451500 | U5: =IFERROR(Tableau1[[#This Row],[Loyer annuel]]/12,"") -> 37625 | V5: 50 | W5: / | X5: =Tableau1[[#This Row],[Charges €/m²]]*Tableau1[[#This Row],[Surface GLA]] -> 90300 | Y5: =IFERROR(Tableau1[[#This Row],[Charges annuelles]]/12,"") -> 7525 | Z5: 10 | AA5: =IFERROR(Tableau1[[#This Row],[Taxe foncière €/m²]]*Tableau1[[#This Row],[Surface GLA]],) -> 0 | AB5: / | AC5: =IFERROR(Tableau1[[#This Row],[Marketing €/m²]]*Tableau1[[#This Row],[Surface GLA]],) -> 0 | AD5: / | AE5: =IFERROR(Tableau1[[#This Row],[Loyer annuel]]+Tableau1[[#This Row],[Charges annuelles]]+Tableau1[[#This Row],[Taxe foncière]]+Tableau1[[#This Row],[Marketing]],"") -> 541800 | AF5: / | AG5: / | AH5: / | AI5: En l'état du précédent locataire | AJ5: A étudier | AK5: Chaude et froide | AL5: Ma Jardinerie, Electro Dépôt, Centrakor, La Boucherie, Kya | AM5: Ancien Maison Depôt. Quai de livraison et monte-charge. Taxes comprises | AO5: 30% du loyer facial avec un minimum de 15 000 € HT | AP5: 47.505019 | AQ5: 6.844836 | AR5: 4 | AS5: https://pub-843c46afc4cb41489909bce00c9b143d.r2.dev/4%20-%20Exincourt/1.jpg; https://pub-843c46afc4cb41489909bce00c9b143d.r2.dev/4%20-%20Exincourt/2.jpg; https://pub-843c46afc4cb41489909bce00c9b143d.r2.dev/4%20-%20Exincourt/3%20Plan%20R-1.jpg; https://pub-843c46afc4cb41489909bce00c9b143d.r2.dev/4%20-%20Exincourt/4%20Plan%20RDC.jpg; https://pub-843c46afc4cb41489909bce00c9b143d.r2.dev/4%20-%20Exincourt/5%20Plan%20R%2B1.jpg | AT5: Oui | AU5: 50 €/m² = 431 400 € | AV5: Praemia
A6: =VLOOKUP(Tableau1[[#This Row],[N° Département]],Feuil1!$C$6:$E$106,3) -> Normandie | B6: =VLOOKUP(Tableau1[[#This Row],[N° Département]],Feuil1!$C$6:$E$106,2) -> Calvados | C6: =LEFT(Tableau1[[#This Row],[Code Postal]],2)*1 -> 14 | D6: 103 Le Val | E6: 14200 | F6: Hérouville-Saint-Clair | G6: =Tableau1[[#This Row],[Rue]]&CHAR(10)&Tableau1[[#This Row],[Code Postal]]&" - "&Tableau1[[#This Row],[Ville]] -> 103 Le Val 14200 - Hérouville-Saint-Clair | H6: https://maps.app.goo.gl/yRNFdK1p6sWPThzm7 | I6: Périphérie | J6: Centre Commercial | K6: / | M6: / | N6: B2 | O6: 179 | P6: / | Q6: / | R6: / | S6: / | T6: =Tableau1[[#This Row],[Loyer €/m²]]*Tableau1[[#This Row],[Surface GLA]] -> 71600 | U6: =IFERROR(Tableau1[[#This Row],[Loyer annuel]]/12,"") -> 5966.6667 | V6: 400 | W6: / | X6: =Tableau1[[#This Row],[Charges €/m²]]*Tableau1[[#This Row],[Surface GLA]] -> 13067 | Y6: =IFERROR(Tableau1[[#This Row],[Charges annuelles]]/12,"") -> 1088.9167 | Z6: 73 | AA6: =IFERROR(Tableau1[[#This Row],[Taxe foncière €/m²]]*Tableau1[[#This Row],[Surface GLA]],) -> 4296 | AB6: 24 | AC6: =IFERROR(Tableau1[[#This Row],[Marketing €/m²]]*Tableau1[[#This Row],[Surface GLA]],) -> 3759 | AD6: 21 | AE6: =IFERROR(Tableau1[[#This Row],[Loyer annuel]]+Tableau1[[#This Row],[Charges annuelles]]+Tableau1[[#This Row],[Taxe foncière]]+Tableau1[[#This Row],[Marketing]],"") -> 92722 | AF6: / | AG6: / | AH6: 0.025 | AI6: En l'état du précédent locataire | AJ6: Non | AK6: Froide | AL6: Basic Fit, Normal, Micromania, Okaïdi, Marionnaud, Promod, Rougegorge, Mcdonald's | AM6: Flux de 4,4M annuel avec un hyper à 60 M€. 73 boutiques dans la Galerie. | AO6: 30% du loyer facial avec un minimum de 15 000 € HT | AP6: 49.205819 | AQ6: -0.328482 | AR6: 5.1 | AS6: https://pub-843c46afc4cb41489909bce00c9b143d.r2.dev/5.1%20-%20H%C3%A9rouville-Saint-Clair/1.jpg; https://pub-843c46afc4cb41489909bce00c9b143d.r2.dev/5.1%20-%20H%C3%A9rouville-Saint-Clair/2.jpg; https://pub-843c46afc4cb41489909bce00c9b143d.r2.dev/5.1%20-%20H%C3%A9rouville-Saint-Clair/3.jpg; https://pub-843c46afc4cb41489909bce00c9b143d.r2.dev/5.1%20-%20H%C3%A9rouville-Saint-Clair/4.jpg; https://pub-843c46afc4cb41489909bce00c9b143d.r2.dev/5.1%20-%20H%C3%A9rouville-Saint-Clair/5%20B1-B2%20-%20Division%202022%20-%20GO%20Cloison-Pr%C3%A9sentation%20AT%20(1)%20-%20La_Casa_de_la_Carcasas.jpg | AT6: Oui | AU6: Au BP | AV6: Twenty Two
A7: =VLOOKUP(Tableau1[[#This Row],[N° Département]],Feuil1!$C$6:$E$106,3) -> Normandie | B7: =VLOOKUP(Tableau1[[#This Row],[N° Département]],Feuil1!$C$6:$E$106,2) -> Calvados | C7: =LEFT(Tableau1[[#This Row],[Code Postal]],2)*1 -> 14 | D7: 103 Le Val | E7: 14200 | F7: Hérouville-Saint-Clair | G7: =Tableau1[[#This Row],[Rue]]&CHAR(10)&Tableau1[[#This Row],[Code Postal]]&" - "&Tableau1[[#This Row],[Ville]] -> 103 Le Val 14200 - Hérouville-Saint-Clair | H7: https://maps.app.goo.gl/yRNFdK1p6sWPThzm8 | I7: Périphérie | J7: Centre Commercial | K7: / | M7: / | N7: B4 | O7: 159 | P7: / | Q7: / | R7: / | S7: / | T7: =Tableau1[[#This Row],[Loyer €/m²]]*Tableau1[[#This Row],[Surface GLA]] -> 63600 | U7: =IFERROR(Tableau1[[#This Row],[Loyer annuel]]/12,"") -> 5300 | V7: 400 | W7: / | X7: =Tableau1[[#This Row],[Charges €/m²]]*Tableau1[[#This Row],[Surface GLA]] -> 11607 | Y7: =Tableau1[[#This Row],[Charges annuelles]]/12 -> 967.25 | Z7: 73 | AA7: =IFERROR(Tableau1[[#This Row],[Taxe foncière €/m²]]*Tableau1[[#This Row],[Surface GLA]],) -> 3816 | AB7: 24 | AC7: =IFERROR(Tableau1[[#This Row],[Marketing €/m²]]*Tableau1[[#This Row],[Surface GLA]],) -> 3339 | AD7: 21 | AE7: =IFERROR(Tableau1[[#This Row],[Loyer annuel]]+Tableau1[[#This Row],[Charges annuelles]]+Tableau1[[#This Row],[Taxe foncière]]+Tableau1[[#This Row],[Marketing]],"") -> 82362 | AF7: / | AG7: / | AH7: 0.025 | AI7: En l'état du précédent locataire | AJ7: Non | AK7: Froide | AL7: Basic Fit, Normal, Micromania, Okaïdi, Marionnaud, Promod, Rougegorge, Mcdonald's | AM7: Flux de 4,4M annuel avec un hyper à 60 M€. 73 boutiques dans la Galerie. | AO7: 30% du loyer facial avec un minimum de 15 000 € HT | AP7: 49.205645 | AQ7: -0.328361 | AR7: 5.2 | AS7: https://pub-843c46afc4cb41489909bce00c9b143d.r2.dev/5.1%20-%20H%C3%A9rouville-Saint-Clair/1.jpg; https://pub-843c46afc4cb41489909bce00c9b143d.r2.dev/5.1%20-%20H%C3%A9rouville-Saint-Clair/2.jpg; https://pub-843c46afc4cb41489909bce00c9b143d.r2.dev/5.1%20-%20H%C3%A9rouville-Saint-Clair/3.jpg; https://pub-843c46afc4cb41489909bce00c9b143d.r2.dev/5.1%20-%20H%C3%A9rouville-Saint-Clair/4.jpg; https://pub-843c46afc4cb41489909bce00c9b143d.r2.dev/5.2%20-%20H%C3%A9rouville-Saint-Clair/5%20B4%20-%205372-GLA-2019.07.12.jpg | AT7: Oui | AU7: Au BP | AV7: Twenty Two
A8: =VLOOKUP(Tableau1[[#This Row],[N° Département]],Feuil1!$C$6:$E$106,3) -> Normandie | B8: =VLOOKUP(Tableau1[[#This Row],[N° Département]],Feuil1!$C$6:$E$106,2) -> Calvados | C8: =LEFT(Tableau1[[#This Row],[Code Postal]],2)*1 -> 14 | D8: 103 Le Val | E8: 14200 | F8: Hérouville-Saint-Clair | G8: =Tableau1[[#This Row],[Rue]]&CHAR(10)&Tableau1[[#This Row],[Code Postal]]&" - "&Tableau1[[#This Row],[Ville]] -> 103 Le Val 14200 - Hérouville-Saint-Clair | H8: https://maps.app.goo.gl/yRNFdK1p6sWPThzm9 | I8: Périphérie | J8: Centre Commercial | K8: / | M8: / | N8: B6 | O8: 125 | P8: / | Q8: / | R8: / | S8: / | T8: =Tableau1[[#This Row],[Loyer €/m²]]*Tableau1[[#This Row],[Surface GLA]] -> 56250 | U8: =IFERROR(Tableau1[[#This Row],[Loyer annuel]]/12,"") -> 4687.5 | V8: 450 | W8: / | X8: =Tableau1[[#This Row],[Charges €/m²]]*Tableau1[[#This Row],[Surface GLA]] -> 9125 | Y8: =Tableau1[[#This Row],[Charges annuelles]]/12 -> 760.41667 | Z8: 73 | AA8: =IFERROR(Tableau1[[#This Row],[Taxe foncière €/m²]]*Tableau1[[#This Row],[Surface GLA]],) -> 3000 | AB8: 24 | AC8: =IFERROR(Tableau1[[#This Row],[Marketing €/m²]]*Tableau1[[#This Row],[Surface GLA]],) -> 2625 | AD8: 21 | AE8: =IFERROR(Tableau1[[#This Row],[Loyer annuel]]+Tableau1[[#This Row],[Charges annuelles]]+Tableau1[[#This Row],[Taxe foncière]]+Tableau1[[#This Row],[Marketing]],"") -> 71000 | AF8: / | AG8: / | AH8: 0.025 | AI8: En l'état du précédent locataire | AJ8: Non | AK8: Froide | AL8: Basic Fit, Normal, Micromania, Okaïdi, Marionnaud, Promod, Rougegorge, Mcdonald's | AM8: Flux de 4,4M annuel avec un hyper à 60 M€. 73 boutiques dans la Galerie. | AO8: 30% du loyer facial avec un minimum de 15 000 € HT | AP8: 49.206029 | AQ8: -0.328616 | AR8: 5.3 | AS8: https://pub-843c46afc4cb41489909bce00c9b143d.r2.dev/5.1%20-%20H%C3%A9rouville-Saint-Clair/1.jpg; https://pub-843c46afc4cb41489909bce00c9b143d.r2.dev/5.1%20-%20H%C3%A9rouville-Saint-Clair/2.jpg; https://pub-843c46afc4cb41489909bce00c9b143d.r2.dev/5.1%20-%20H%C3%A9rouville-Saint-Clair/3.jpg; https://pub-843c46afc4cb41489909bce00c9b143d.r2.dev/5.1%20-%20H%C3%A9rouville-Saint-Clair/4.jpg; https://pub-843c46afc4cb41489909bce00c9b143d.r2.dev/5.3%20-%20H%C3%A9rouville-Saint-Clair/5%20B6%20-%205372%20-%20GLA-2017.12.04.jpg | AT8: Oui | AU8: Au BP | AV8: Twenty Two
A9: =VLOOKUP(Tableau1[[#This Row],[N° Département]],Feuil1!$C$6:$E$106,3) -> Normandie | B9: =VLOOKUP(Tableau1[[#This Row],[N° Département]],Feuil1!$C$6:$E$106,2) -> Calvados | C9: =LEFT(Tableau1[[#This Row],[Code Postal]],2)*1 -> 14 | D9: 103 Le Val | E9: 14200 | F9: Hérouville-Saint-Clair | G9: =Tableau1[[#This Row],[Rue]]&CHAR(10)&Tableau1[[#This Row],[Code Postal]]&" - "&Tableau1[[#This Row],[Ville]] -> 103 Le Val 14200 - Hérouville-Saint-Clair | H9: https://maps.app.goo.gl/yRNFdK1p6sWPThzm10 | I9: Périphérie | J9: Centre Commercial | K9: / | M9: / | N9: B7 | O9: 156 | P9: / | Q9: 758 | R9: / | S9: / | T9: =Tableau1[[#This Row],[Loyer €/m²]]*Tableau1[[#This Row],[Surface GLA]] -> 62400 | U9: =IFERROR(Tableau1[[#This Row],[Loyer annuel]]/12,"") -> 5200 | V9: 400 | W9: / | X9: =Tableau1[[#This Row],[Charges €/m²]]*Tableau1[[#This Row],[Surface GLA]] -> 11388 | Y9: =Tableau1[[#This Row],[Charges annuelles]]/12 -> 949 | Z9: 73 | AA9: =IFERROR(Tableau1[[#This Row],[Taxe foncière €/m²]]*Tableau1[[#This Row],[Surface GLA]],) -> 3744 | AB9: 24 | AC9: =IFERROR(Tableau1[[#This Row],[Marketing €/m²]]*Tableau1[[#This Row],[Surface GLA]],) -> 3276 | AD9: 21 | AE9: =IFERROR(Tableau1[[#This Row],[Loyer annuel]]+Tableau1[[#This Row],[Charges annuelles]]+Tableau1[[#This Row],[Taxe foncière]]+Tableau1[[#This Row],[Marketing]],"") -> 80808 | AF9: / | AG9: / | AH9: 0.025 | AI9: En l'état du précédent locataire | AJ9: Non | AK9: Froide | AL9: Basic Fit, Normal, Micromania, Okaïdi, Marionnaud, Promod, Rougegorge, Mcdonald's | AM9: Flux de 4,4M annuel avec un hyper à 60 M€. 73 boutiques dans la Galerie. | AO9: 30% du loyer facial avec un minimum de 15 000 € HT | AP9: 49.206122 | AQ9: -0.328394 | AR9: 5.4 | AS9: https://pub-843c46afc4cb41489909bce00c9b143d.r2.dev/5.1%20-%20H%C3%A9rouville-Saint-Clair/1.jpg; https://pub-843c46afc4cb41489909bce00c9b143d.r2.dev/5.1%20-%20H%C3%A9rouville-Saint-Clair/2.jpg; https://pub-843c46afc4cb41489909bce00c9b143d.r2.dev/5.1%20-%20H%C3%A9rouville-Saint-Clair/3.jpg; https://pub-843c46afc4cb41489909bce00c9b143d.r2.dev/5.1%20-%20H%C3%A9rouville-Saint-Clair/4.jpg; https://pub-843c46afc4cb41489909bce00c9b143d.r2.dev/5.4%20-%20H%C3%A9rouville-Saint-Clair/5%20B7%20-%205372-GLA-2019.07.12.jpg | AT9: Oui | AU9: Au BP | AV9: Twenty Two
A10: =VLOOKUP(Tableau1[[#This Row],[N° Département]],Feuil1!$C$6:$E$106,3) -> Normandie | B10: =VLOOKUP(Tableau1[[#This Row],[N° Département]],Feuil1!$C$6:$E$106,2) -> Calvados | C10: =LEFT(Tableau1[[#This Row],[Code Postal]],2)*1 -> 14 | D10: 103 Le Val | E10: 14200 | F10: Hérouville-Saint-Clair | G10: =Tableau1[[#This Row],[Rue]]&CHAR(10)&Tableau1[[#This Row],[Code Postal]]&" - "&Tableau1[[#This Row],[Ville]] -> 103 Le Val 14200 - Hérouville-Saint-Clair | H10: https://maps.app.goo.gl/yRNFdK1p6sWPThzm11 | I10: Périphérie | J10: Centre Commercial | K10: / | M10: / | N10: B9 | O10: 178 | P10: / | Q10: 758 | R10: / | S10: / | T10: =Tableau1[[#This Row],[Loyer €/m²]]*Tableau1[[#This Row],[Surface GLA]] -> 71200 | U10: =IFERROR(Tableau1[[#This Row],[Loyer annuel]]/12,"") -> 5933.3333 | V10: 400 | W10: / | X10: =Tableau1[[#This Row],[Charges €/m²]]*Tableau1[[#This Row],[Surface GLA]] -> 12994 | Y10: =Tableau1[[#This Row],[Charges annuelles]]/12 -> 1082.8333 | Z10: 73 | AA10: =IFERROR(Tableau1[[#This Row],[Taxe foncière €/m²]]*Tableau1[[#This Row],[Surface GLA]],) -> 4272 | AB10: 24 | AC10: =IFERROR(Tableau1[[#This Row],[Marketing €/m²]]*Tableau1[[#This Row],[Surface GLA]],) -> 3738 | AD10: 21 | AE10: =IFERROR(Tableau1[[#This Row],[Loyer annuel]]+Tableau1[[#This Row],[Charges annuelles]]+Tableau1[[#This Row],[Taxe foncière]]+Tableau1[[#This Row],[Marketing]],"") -> 92204 | AF10: / | AG10: / | AH10: 0.025 | AI10: En l'état du précédent locataire | AJ10: Non | AK10: Froide | AL10: Basic Fit, Normal, Micromania, Okaïdi, Marionnaud, Promod, Rougegorge, Mcdonald's | AM10: Flux de 4,4M annuel avec un hyper à 60 M€. 73 boutiques dans la Galerie. | AO10: 30% du loyer facial avec un minimum de 15 000 € HT | AP10: 49.206071 | AQ10: -0.328211 | AR10: 5.5 | AS10: https://pub-843c46afc4cb41489909bce00c9b143d.r2.dev/5.1%20-%20H%C3%A9rouville-Saint-Clair/1.jpg; https://pub-843c46afc4cb41489909bce00c9b143d.r2.dev/5.1%20-%20H%C3%A9rouville-Saint-Clair/2.jpg; https://pub-843c46afc4cb41489909bce00c9b143d.r2.dev/5.1%20-%20H%C3%A9rouville-Saint-Clair/3.jpg; https://pub-843c46afc4cb41489909bce00c9b143d.r2.dev/5.1%20-%20H%C3%A9rouville-Saint-Clair/4.jpg; https://pub-843c46afc4cb41489909bce00c9b143d.r2.dev/5.5%20-%20H%C3%A9rouville-Saint-Clair/5%20B9%20-%205372-GLA-2019.07.12.jpg | AT10: Oui | AU10: Au BP | AV10: Twenty Two
A11: =VLOOKUP(Tableau1[[#This Row],[N° Département]],Feuil1!$C$6:$E$106,3) -> Normandie | B11: =VLOOKUP(Tableau1[[#This Row],[N° Département]],Feuil1!$C$6:$E$106,2) -> Calvados | C11: =LEFT(Tableau1[[#This Row],[Code Postal]],2)*1 -> 14 | D11: 103 Le Val | E11: 14200 | F11: Hérouville-Saint-Clair | G11: =Tableau1[[#This Row],[Rue]]&CHAR(10)&Tableau1[[#This Row],[Code Postal]]&" - "&Tableau1[[#This Row],[Ville]] -> 103 Le Val 14200 - Hérouville-Saint-Clair | H11: https://maps.app.goo.gl/yRNFdK1p6sWPThzm12 | I11: Périphérie | J11: Centre Commercial | K11: / | M11: / | N11: B11 | O11: 253 | P11: / | Q11: 758 | R11: / | S11: / | T11: =Tableau1[[#This Row],[Loyer €/m²]]*Tableau1[[#This Row],[Surface GLA]] -> 88550 | U11: =IFERROR(Tableau1[[#This Row],[Loyer annuel]]/12,"") -> 7379.1667 | V11: 350 | W11: / | X11: =Tableau1[[#This Row],[Charges €/m²]]*Tableau1[[#This Row],[Surface GLA]] -> 18469 | Y11: =Tableau1[[#This Row],[Charges annuelles]]/12 -> 1539.0833 | Z11: 73 | AA11: =IFERROR(Tableau1[[#This Row],[Taxe foncière €/m²]]*Tableau1[[#This Row],[Surface GLA]],) -> 6072 | AB11: 24 | AC11: =IFERROR(Tableau1[[#This Row],[Marketing €/m²]]*Tableau1[[#This Row],[Surface GLA]],) -> 5313 | AD11: 21 | AE11: =IFERROR(Tableau1[[#This Row],[Loyer annuel]]+Tableau1[[#This Row],[Charges annuelles]]+Tableau1[[#This Row],[Taxe foncière]]+Tableau1[[#This Row],[Marketing]],"") -> 118404 | AF11: / | AG11: / | AH11: 0.025 | AI11: En l'état du précédent locataire | AJ11: Non | AK11: Froide | AL11: Basic Fit, Normal, Micromania, Okaïdi, Marionnaud, Promod, Rougegorge, Mcdonald's | AM11: Flux de 4,4M annuel avec un hyper à 60 M€. 73 boutiques dans la Galerie. | AO11: 30% du loyer facial avec un minimum de 15 000 € HT | AP11: 49.206257 | AQ11: -0.327930 | AR11: 5.6 | AS11: https://pub-843c46afc4cb41489909bce00c9b143d.r2.dev/5.1%20-%20H%C3%A9rouville-Saint-Clair/1.jpg; https://pub-843c46afc4cb41489909bce00c9b143d.r2.dev/5.1%20-%20H%C3%A9rouville-Saint-Clair/2.jpg; https://pub-843c46afc4cb41489909bce00c9b143d.r2.dev/5.1%20-%20H%C3%A9rouville-Saint-Clair/3.jpg; https://pub-843c46afc4cb41489909bce00c9b143d.r2.dev/5.1%20-%20H%C3%A9rouville-Saint-Clair/4.jpg; https://pub-843c46afc4cb41489909bce00c9b143d.r2.dev/5.6%20-%20H%C3%A9rouville-Saint-Clair/5%20B11%20(ex%20Cama%C3%AFeu)%20(nouveau%20B69)%20-%205372-GLA-2019.07.12.jpg | AT11: Oui | AU11: Au BP | AV11: Twenty Two
A12: =VLOOKUP(Tableau1[[#This Row],[N° Département]],Feuil1!$C$6:$E$106,3) -> Normandie | B12: =VLOOKUP(Tableau1[[#This Row],[N° Département]],Feuil1!$C$6:$E$106,2) -> Calvados | C12: =LEFT(Tableau1[[#This Row],[Code Postal]],2)*1 -> 14 | D12: 103 Le Val | E12: 14200 | F12: Hérouville-Saint-Clair | G12: =Tableau1[[#This Row],[Rue]]&CHAR(10)&Tableau1[[#This Row],[Code Postal]]&" - "&Tableau1[[#This Row],[Ville]] -> 103 Le Val 14200 - Hérouville-Saint-Clair | H12: https://maps.app.goo.gl/yRNFdK1p6sWPThzm13 | I12: Périphérie | J12: Centre Commercial | K12: / | M12: / | N12: B12 | O12: 171 | P12: / | Q12: 758 | R12: / | S12: / | T12: =Tableau1[[#This Row],[Loyer €/m²]]*Tableau1[[#This Row],[Surface GLA]] -> 68400 | U12: =IFERROR(Tableau1[[#This Row],[Loyer annuel]]/12,"") -> 5700 | V12: 400 | W12: / | X12: =Tableau1[[#This Row],[Charges €/m²]]*Tableau1[[#This Row],[Surface GLA]] -> 12483 | Y12: =Tableau1[[#This Row],[Charges annuelles]]/12 -> 1040.25 | Z12: 73 | AA12: =IFERROR(Tableau1[[#This Row],[Taxe foncière €/m²]]*Tableau1[[#This Row],[Surface GLA]],) -> 4104 | AB12: 24 | AC12: =IFERROR(Tableau1[[#This Row],[Marketing €/m²]]*Tableau1[[#This Row],[Surface GLA]],) -> 3591 | AD12: 21 | AE12: =IFERROR(Tableau1[[#This Row],[Loyer annuel]]+Tableau1[[#This Row],[Charges annuelles]]+Tableau1[[#This Row],[Taxe foncière]]+Tableau1[[#This Row],[Marketing]],"") -> 88578 | AF12: / | AG12: / | AH12: 0.025 | AI12: En l'état du précédent locataire | AJ12: Non | AK12: Froide | AL12: Basic Fit, Normal, Micromania, Okaïdi, Marionnaud, Promod, Rougegorge, Mcdonald's | AM12: Flux de 4,4M annuel avec un hyper à 60 M€. 73 boutiques dans la Galerie. | AO12: 30% du loyer facial avec un minimum de 15 000 € HT | AP12: 49.206164 | AQ12: -0.327884 | AR12: 5.7 | AS12: https://pub-843c46afc4cb41489909bce00c9b143d.r2.dev/5.1%20-%20H%C3%A9rouville-Saint-Clair/1.jpg; https://pub-843c46afc4cb41489909bce00c9b143d.r2.dev/5.1%20-%20H%C3%A9rouville-Saint-Clair/2.jpg; https://pub-843c46afc4cb41489909bce00c9b143d.r2.dev/5.1%20-%20H%C3%A9rouville-Saint-Clair/3.jpg; https://pub-843c46afc4cb41489909bce00c9b143d.r2.dev/5.1%20-%20H%C3%A9rouville-Saint-Clair/4.jpg; https://pub-843c46afc4cb41489909bce00c9b143d.r2.dev/5.7%20-%20H%C3%A9rouville-Saint-Clair/5%20B12%20-%205372-GLA-2019.07.12.jpg | AT12: Oui | AU12: Au BP | AV12: Twenty Two
A13: =VLOOKUP(Tableau1[[#This Row],[N° Département]],Feuil1!$C$6:$E$106,3) -> Normandie | B13: =VLOOKUP(Tableau1[[#This Row],[N° Département]],Feuil1!$C$6:$E$106,2) -> Calvados | C13: =LEFT(Tableau1[[#This Row],[Code Postal]],2)*1 -> 14 | D13: 103 Le Val | E13: 14200 | F13: Hérouville-Saint-Clair | G13: =Tableau1[[#This Row],[Rue]]&CHAR(10)&Tableau1[[#This Row],[Code Postal]]&" - "&Tableau1[[#This Row],[Ville]] -> 103 Le Val 14200 - Hérouville-Saint-Clair | H13: https://maps.app.goo.gl/yRNFdK1p6sWPThzm14 | I13: Périphérie | J13: Centre Commercial | K13: / | M13: / | N13: B14A | O13: 200 | P13: / | Q13: 305 | R13: / | S13: / | T13: =Tableau1[[#This Row],[Loyer €/m²]]*Tableau1[[#This Row],[Surface GLA]] -> 70000 | U13: =IFERROR(Tableau1[[#This Row],[Loyer annuel]]/12,"") -> 5833.3333 | V13: 350 | W13: / | X13: =Tableau1[[#This Row],[Charges €/m²]]*Tableau1[[#This Row],[Surface GLA]] -> 14600 | Y13: =Tableau1[[#This Row],[Charges annuelles]]/12 -> 1216.6667 | Z13: 73 | AA13: =IFERROR(Tableau1[[#This Row],[Taxe foncière €/m²]]*Tableau1[[#This Row],[Surface GLA]],) -> 4800 | AB13: 24 | AC13: =IFERROR(Tableau1[[#This Row],[Marketing €/m²]]*Tableau1[[#This Row],[Surface GLA]],) -> 4200 | AD13: 21 | AE13: =IFERROR(Tableau1[[#This Row],[Loyer annuel]]+Tableau1[[#This Row],[Charges annuelles]]+Tableau1[[#This Row],[Taxe foncière]]+Tableau1[[#This Row],[Marketing]],"") -> 93600 | AF13: / | AG13: / | AH13: 0.025 | AI13: En l'état du précédent locataire | AJ13: Non | AK13: Froide | AL13: Basic Fit, Normal, Micromania, Okaïdi, Marionnaud, Promod, Rougegorge, Mcdonald's | AM13: Flux de 4,4M annuel avec un hyper à 60 M€. 73 boutiques dans la Galerie. | AO13: 30% du loyer facial avec un minimum de 15 000 € HT | AP13: 49.206310 | AQ13: -0.327702 | AR13: 5.8 | AS13: https://pub-843c46afc4cb41489909bce00c9b143d.r2.dev/5.1%20-%20H%C3%A9rouville-Saint-Clair/1.jpg; https://pub-843c46afc4cb41489909bce00c9b143d.r2.dev/5.1%20-%20H%C3%A9rouville-Saint-Clair/2.jpg; https://pub-843c46afc4cb41489909bce00c9b143d.r2.dev/5.1%20-%20H%C3%A9rouville-Saint-Clair/3.jpg; https://pub-843c46afc4cb41489909bce00c9b143d.r2.dev/5.1%20-%20H%C3%A9rouville-Saint-Clair/4.jpg; https://pub-843c46afc4cb41489909bce00c9b143d.r2.dev/5.8%20-%20H%C3%A9rouville-Saint-Clair/5%20B14A%20-%205372-GLA-2019.07.12.jpg | AT13: Oui | AU13: Au BP | AV13: Twenty Two
A14: =VLOOKUP(Tableau1[[#This Row],[N° Département]],Feuil1!$C$6:$E$106,3) -> Normandie | B14: =VLOOKUP(Tableau1[[#This Row],[N° Département]],Feuil1!$C$6:$E$106,2) -> Calvados | C14: =LEFT(Tableau1[[#This Row],[Code Postal]],2)*1 -> 14 | D14: 103 Le Val | E14: 14200 | F14: Hérouville-Saint-Clair | G14: =Tableau1[[#This Row],[Rue]]&CHAR(10)&Tableau1[[#This Row],[Code Postal]]&" - "&Tableau1[[#This Row],[Ville]] -> 103 Le Val 14200 - Hérouville-Saint-Clair | H14: https://maps.app.goo.gl/yRNFdK1p6sWPThzm15 | I14: Périphérie | J14: Centre Commercial | K14: / | M14: / | N14: B14B | O14: 105 | P14: / | Q14: 305 | R14: / | S14: / | T14: =Tableau1[[#This Row],[Loyer €/m²]]*Tableau1[[#This Row],[Surface GLA]] -> 47250 | U14: =IFERROR(Tableau1[[#This Row],[Loyer annuel]]/12,"") -> 3937.5 | V14: 450 | W14: / | X14: =Tableau1[[#This Row],[Charges €/m²]]*Tableau1[[#This Row],[Surface GLA]] -> 7665 | Y14: =Tableau1[[#This Row],[Charges annuelles]]/12 -> 638.75 | Z14: 73 | AA14: =IFERROR(Tableau1[[#This Row],[Taxe foncière €/m²]]*Tableau1[[#This Row],[Surface GLA]],) -> 2520 | AB14: 24 | AC14: =IFERROR(Tableau1[[#This Row],[Marketing €/m²]]*Tableau1[[#This Row],[Surface GLA]],) -> 2205 | AD14: 21 | AE14: =IFERROR(Tableau1[[#This Row],[Loyer annuel]]+Tableau1[[#This Row],[Charges annuelles]]+Tableau1[[#This Row],[Taxe foncière]]+Tableau1[[#This Row],[Marketing]],"") -> 59640 | AF14: / | AG14: / | AH14: 0.025 | AI14: En l'état du précédent locataire | AJ14: Non | AK14: Froide | AL14: Basic Fit, Normal, Micromania, Okaïdi, Marionnaud, Promod, Rougegorge, Mcdonald's | AM14: Flux de 4,4M annuel avec un hyper à 60 M€. 73 boutiques dans la Galerie. | AO14: 30% du loyer facial avec un minimum de 15 000 € HT | AP14: 49.206238 | AQ14: -0.327648 | AR14: 5.9 | AS14: https://pub-843c46afc4cb41489909bce00c9b143d.r2.dev/5.1%20-%20H%C3%A9rouville-Saint-Clair/1.jpg; https://pub-843c46afc4cb41489909bce00c9b143d.r2.dev/5.1%20-%20H%C3%A9rouville-Saint-Clair/2.jpg; https://pub-843c46afc4cb41489909bce00c9b143d.r2.dev/5.1%20-%20H%C3%A9rouville-Saint-Clair/3.jpg; https://pub-843c46afc4cb41489909bce00c9b143d.r2.dev/5.1%20-%20H%C3%A9rouville-Saint-Clair/4.jpg; https://pub-843c46afc4cb41489909bce00c9b143d.r2.dev/5.9%20-%20H%C3%A9rouville-Saint-Clair/5%20B14B%20-%205372-GLA-2019.07.12.jpg | AT14: Oui | AU14: Au BP | AV14: Twenty Two
A15: =VLOOKUP(Tableau1[[#This Row],[N° Département]],Feuil1!$C$6:$E$106,3) -> Normandie | B15: =VLOOKUP(Tableau1[[#This Row],[N° Département]],Feuil1!$C$6:$E$106,2) -> Calvados | C15: =LEFT(Tableau1[[#This Row],[Code Postal]],2)*1 -> 14 | D15: 103 Le Val | E15: 14200 | F15: Hérouville-Saint-Clair | G15: =Tableau1[[#This Row],[Rue]]&CHAR(10)&Tableau1[[#This Row],[Code Postal]]&" - "&Tableau1[[#This Row],[Ville]] -> 103 Le Val 14200 - Hérouville-Saint-Clair | H15: https://maps.app.goo.gl/yRNFdK1p6sWPThzm16 | I15: Périphérie | J15: Centre Commercial | K15: / | M15: / | N15: B21 | O15: 51 | P15: / | Q15: 166 | R15: / | S15: / | T15: =Tableau1[[#This Row],[Loyer €/m²]]*Tableau1[[#This Row],[Surface GLA]] -> 25500 | U15: =IFERROR(Tableau1[[#This Row],[Loyer annuel]]/12,"") -> 2125 | V15: 500 | W15: / | X15: =Tableau1[[#This Row],[Charges €/m²]]*Tableau1[[#This Row],[Surface GLA]] -> 3723 | Y15: =Tableau1[[#This Row],[Charges annuelles]]/12 -> 310.25 | Z15: 73 | AA15: =IFERROR(Tableau1[[#This Row],[Taxe foncière €/m²]]*Tableau1[[#This Row],[Surface GLA]],) -> 1224 | AB15: 24 | AC15: =IFERROR(Tableau1[[#This Row],[Marketing €/m²]]*Tableau1[[#This Row],[Surface GLA]],) -> 1071 | AD15: 21 | AE15: =IFERROR(Tableau1[[#This Row],[Loyer annuel]]+Tableau1[[#This Row],[Charges annuelles]]+Tableau1[[#This Row],[Taxe foncière]]+Tableau1[[#This Row],[Marketing]],"") -> 31518 | AF15: / | AG15: / | AH15: 0.025 | AI15: En l'état du précédent locataire | AJ15: Non | AK15: Froide | AL15: Basic Fit, Normal, Micromania, Okaïdi, Marionnaud, Promod, Rougegorge, Mcdonald's | AM15: Flux de 4,4M annuel avec un hyper à 60 M€. 73 boutiques dans la Galerie. | AO15: 30% du loyer facial avec un minimum de 15 000 € HT | AP15: 49.206083 | AQ15: -0.327479 | AR15: 5.10 | AS15: https://pub-843c46afc4cb41489909bce00c9b143d.r2.dev/5.1%20-%20H%C3%A9rouville-Saint-Clair/1.jpg; https://pub-843c46afc4cb41489909bce00c9b143d.r2.dev/5.1%20-%20H%C3%A9rouville-Saint-Clair/2.jpg; https://pub-843c46afc4cb41489909bce00c9b143d.r2.dev/5.1%20-%20H%C3%A9rouville-Saint-Clair/3.jpg; https://pub-843c46afc4cb41489909bce00c9b143d.r2.dev/5.1%20-%20H%C3%A9rouville-Saint-Clair/4.jpg; https://pub-843c46afc4cb41489909bce00c9b143d.r2.dev/5.10%20-%20H%C3%A9rouville-Saint-Clair/5%20B21%20-%205372%20-%20GLA-2017.12.04.jpg | AT15: Oui | AU15: Au BP | AV15: Twenty Two
A16: =VLOOKUP(Tableau1[[#This Row],[N° Département]],Feuil1!$C$6:$E$106,3) -> Normandie | B16: =VLOOKUP(Tableau1[[#This Row],[N° Département]],Feuil1!$C$6:$E$106,2) -> Calvados | C16: =LEFT(Tableau1[[#This Row],[Code Postal]],2)*1 -> 14 | D16: 103 Le Val | E16: 14200 | F16: Hérouville-Saint-Clair | G16: =Tableau1[[#This Row],[Rue]]&CHAR(10)&Tableau1[[#This Row],[Code Postal]]&" - "&Tableau1[[#This Row],[Ville]] -> 103 Le Val 14200 - Hérouville-Saint-Clair | H16: https://maps.app.goo.gl/yRNFdK1p6sWPThzm17 | I16: Périphérie | J16: Centre Commercial | K16: / | M16: / | N16: B23B | O16: 115 | P16: / | Q16: 166 | R16: / | S16: / | T16: =Tableau1[[#This Row],[Loyer €/m²]]*Tableau1[[#This Row],[Surface GLA]] -> 51750 | U16: =IFERROR(Tableau1[[#This Row],[Loyer annuel]]/12,"") -> 4312.5 | V16: 450 | W16: / | X16: =Tableau1[[#This Row],[Charges €/m²]]*Tableau1[[#This Row],[Surface GLA]] -> 8395 | Y16: =Tableau1[[#This Row],[Charges annuelles]]/12 -> 699.58333 | Z16: 73 | AA16: =IFERROR(Tableau1[[#This Row],[Taxe foncière €/m²]]*Tableau1[[#This Row],[Surface GLA]],) -> 2760 | AB16: 24 | AC16: =IFERROR(Tableau1[[#This Row],[Marketing €/m²]]*Tableau1[[#This Row],[Surface GLA]],) -> 2415 | AD16: 21 | AE16: =IFERROR(Tableau1[[#This Row],[Loyer annuel]]+Tableau1[[#This Row],[Charges annuelles]]+Tableau1[[#This Row],[Taxe foncière]]+Tableau1[[#This Row],[Marketing]],"") -> 65320 | AF16: / | AG16: / | AH16: 0.025 | AI16: En l'état du précédent locataire | AJ16: Non | AK16: Froide | AL16: Basic Fit, Normal, Micromania, Okaïdi, Marionnaud, Promod, Rougegorge, Mcdonald's | AM16: Flux de 4,4M annuel avec un hyper à 60 M€. 73 boutiques dans la Galerie. | AO16: 30% du loyer facial avec un minimum de 15 000 € HT | AP16: 49.206083 | AQ16: -0.327589 | AR16: 5.11 | AS16: https://pub-843c46afc4cb41489909bce00c9b143d.r2.dev/5.1%20-%20H%C3%A9rouville-Saint-Clair/1.jpg; https://pub-843c46afc4cb41489909bce00c9b143d.r2.dev/5.1%20-%20H%C3%A9rouville-Saint-Clair/2.jpg; https://pub-843c46afc4cb41489909bce00c9b143d.r2.dev/5.1%20-%20H%C3%A9rouville-Saint-Clair/3.jpg; https://pub-843c46afc4cb41489909bce00c9b143d.r2.dev/5.1%20-%20H%C3%A9rouville-Saint-Clair/4.jpg; https://pub-843c46afc4cb41489909bce00c9b143d.r2.dev/5.11%20-%20H%C3%A9rouville-Saint-Clair/5%20B23B%20-%205372%20-%20GLA-2017.12.04.jpg | AT16: Oui | AU16: Au BP | AV16: Twenty Two
A17: =VLOOKUP(Tableau1[[#This Row],[N° Département]],Feuil1!$C$6:$E$106,3) -> Normandie | B17: =VLOOKUP(Tableau1[[#This Row],[N° Département]],Feuil1!$C$6:$E$106,2) -> Calvados | C17: =LEFT(Tableau1[[#This Row],[Code Postal]],2)*1 -> 14 | D17: 103 Le Val | E17: 14200 | F17: Hérouville-Saint-Clair | G17: =Tableau1[[#This Row],[Rue]]&CHAR(10)&Tableau1[[#This Row],[Code Postal]]&" - "&Tableau1[[#This Row],[Ville]] -> 103 Le Val 14200 - Hérouville-Saint-Clair | H17: https://maps.app.goo.gl/yRNFdK1p6sWPThzm18 | I17: Périphérie | J17: Centre Commercial | K17: / | M17: / | N17: B20 | O17: 210 | P17: / | Q17: / | R17: / | S17: / | T17: =Tableau1[[#This Row],[Loyer €/m²]]*Tableau1[[#This Row],[Surface GLA]] -> 73500 | U17: =IFERROR(Tableau1[[#This Row],[Loyer annuel]]/12,"") -> 6125 | V17: 350 | W17: / | X17: =Tableau1[[#This Row],[Charges €/m²]]*Tableau1[[#This Row],[Surface GLA]] -> 15330 | Y17: =Tableau1[[#This Row],[Charges annuelles]]/12 -> 1277.5 | Z17: 73 | AA17: =IFERROR(Tableau1[[#This Row],[Taxe foncière €/m²]]*Tableau1[[#This Row],[Surface GLA]],) -> 5040 | AB17: 24 | AC17: =IFERROR(Tableau1[[#This Row],[Marketing €/m²]]*Tableau1[[#This Row],[Surface GLA]],) -> 4410 | AD17: 21 | AE17: =IFERROR(Tableau1[[#This Row],[Loyer annuel]]+Tableau1[[#This Row],[Charges annuelles]]+Tableau1[[#This Row],[Taxe foncière]]+Tableau1[[#This Row],[Marketing]],"") -> 98280 | AF17: / | AG17: / | AH17: 0.025 | AI17: En l'état du précédent locataire | AJ17: Non | AK17: Froide | AL17: Basic Fit, Normal, Micromania, Okaïdi, Marionnaud, Promod, Rougegorge, Mcdonald's | AM17: Flux de 4,4M annuel avec un hyper à 60 M€. 73 boutiques dans la Galerie. | AO17: 30% du loyer facial avec un minimum de 15 000 € HT | AP17: 49.205982 | AQ17: -0.327975 | AR17: 5.12 | AS17: https://pub-843c46afc4cb41489909bce00c9b143d.r2.dev/5.1%20-%20H%C3%A9rouville-Saint-Clair/1.jpg; https://pub-843c46afc4cb41489909bce00c9b143d.r2.dev/5.1%20-%20H%C3%A9rouville-Saint-Clair/2.jpg; https://pub-843c46afc4cb41489909bce00c9b143d.r2.dev/5.1%20-%20H%C3%A9rouville-Saint-Clair/3.jpg; https://pub-843c46afc4cb41489909bce00c9b143d.r2.dev/5.1%20-%20H%C3%A9rouville-Saint-Clair/4.jpg; https://pub-843c46afc4cb41489909bce00c9b143d.r2.dev/5.12%20-%20H%C3%A9rouville-Saint-Clair/5%20B20%20-%205372%20-%20GLA-2017.12.04.jpg | AT17: Oui | AU17: Au BP | AV17: Twenty Two
A18: =VLOOKUP(Tableau1[[#This Row],[N° Département]],Feuil1!$C$6:$E$106,3) -> Normandie | B18: =VLOOKUP(Tableau1[[#This Row],[N° Département]],Feuil1!$C$6:$E$106,2) -> Calvados | C18: =LEFT(Tableau1[[#This Row],[Code Postal]],2)*1 -> 14 | D18: 103 Le Val | E18: 14200 | F18: Hérouville-Saint-Clair | G18: =Tableau1[[#This Row],[Rue]]&CHAR(10)&Tableau1[[#This Row],[Code Postal]]&" - "&Tableau1[[#This Row],[Ville]] -> 103 Le Val 14200 - Hérouville-Saint-Clair | H18: https://maps.app.goo.gl/yRNFdK1p6sWPThzm19 | I18: Périphérie | J18: Centre Commercial | K18: / | M18: / | N18: B26B | O18: 30 | P18: / | Q18: / | R18: / | S18: / | T18: =Tableau1[[#This Row],[Loyer €/m²]]*Tableau1[[#This Row],[Surface GLA]] -> 15000 | U18: =IFERROR(Tableau1[[#This Row],[Loyer annuel]]/12,"") -> 1250 | V18: 500 | W18: / | X18: =Tableau1[[#This Row],[Charges €/m²]]*Tableau1[[#This Row],[Surface GLA]] -> 2190 | Y18: =Tableau1[[#This Row],[Charges annuelles]]/12 -> 182.5 | Z18: 73 | AA18: =IFERROR(Tableau1[[#This Row],[Taxe foncière €/m²]]*Tableau1[[#This Row],[Surface GLA]],) -> 720 | AB18: 24 | AC18: =IFERROR(Tableau1[[#This Row],[Marketing €/m²]]*Tableau1[[#This Row],[Surface GLA]],) -> 630 | AD18: 21 | AE18: =IFERROR(Tableau1[[#This Row],[Loyer annuel]]+Tableau1[[#This Row],[Charges annuelles]]+Tableau1[[#This Row],[Taxe foncière]]+Tableau1[[#This Row],[Marketing]],"") -> 18540 | AF18: / | AG18: / | AH18: 0.025 | AI18: En l'état du précédent locataire | AJ18: Oui | AK18: Chaude et froide | AL18: Basic Fit, Normal, Micromania, Okaïdi, Marionnaud, Promod, Rougegorge, Mcdonald's | AM18: Flux de 4,4M annuel avec un hyper à 60 M€. 73 boutiques dans la Galerie. | AO18: 30% du loyer facial avec un minimum de 15 000 € HT | AP18: 49.205712 | AQ18: -0.328139 | AR18: 5.13 | AS18: https://pub-843c46afc4cb41489909bce00c9b143d.r2.dev/5.1%20-%20H%C3%A9rouville-Saint-Clair/1.jpg; https://pub-843c46afc4cb41489909bce00c9b143d.r2.dev/5.1%20-%20H%C3%A9rouville-Saint-Clair/2.jpg; https://pub-843c46afc4cb41489909bce00c9b143d.r2.dev/5.1%20-%20H%C3%A9rouville-Saint-Clair/3.jpg; https://pub-843c46afc4cb41489909bce00c9b143d.r2.dev/5.1%20-%20H%C3%A9rouville-Saint-Clair/4.jpg; https://pub-843c46afc4cb41489909bce00c9b143d.r2.dev/5.13%20-%20H%C3%A9rouville-Saint-Clair/5%20B24%20et%20B26A%20et%20B%20-%205372-GLA-2019.07.12.jpg | AT18: Oui | AU18: Au BP | AV18: Twenty Two
A19: =VLOOKUP(Tableau1[[#This Row],[N° Département]],Feuil1!$C$6:$E$106,3) -> Bretagne | B19: =VLOOKUP(Tableau1[[#This Row],[N° Département]],Feuil1!$C$6:$E$106,2) -> Ille-et-Vilaine | C19: =LEFT(Tableau1[[#This Row],[Code Postal]],2)*1 -> 35 | D19: ZAC de Cap Malo | E19: 35520 | F19: La Mézière | G19: =Tableau1[[#This Row],[Rue]]&CHAR(10)&Tableau1[[#This Row],[Code Postal]]&" - "&Tableau1[[#This Row],[Ville]] -> ZAC de Cap Malo 35520 - La Mézière | H19: https://maps.app.goo.gl/jKvNrbE9PyvENUPV6 | I19: Périphérie | J19: Retail Park | K19: / | M19: / | N19: 1 | O19: 1200 | P19: / | Q19: 2400 | R19: / | S19: / | T19: =Tableau1[[#This Row],[Loyer €/m²]]*Tableau1[[#This Row],[Surface GLA]] -> 120000 | U19: =IFERROR(Tableau1[[#This Row],[Loyer annuel]]/12,"") -> 10000 | V19: 100 | W19: / | X19: =Tableau1[[#This Row],[Charges €/m²]]*Tableau1[[#This Row],[Surface GLA]] -> 30000 | Y19: =Tableau1[[#This Row],[Charges annuelles]]/12 -> 2500 | Z19: 25 | AA19: =IFERROR(Tableau1[[#This Row],[Taxe foncière €/m²]]*Tableau1[[#This Row],[Surface GLA]],) -> 9600 | AB19: 8 | AC19: =IFERROR(Tableau1[[#This Row],[Marketing €/m²]]*Tableau1[[#This Row],[Surface GLA]],) -> 25200 | AD19: 21 | AE19: =IFERROR(Tableau1[[#This Row],[Loyer annuel]]+Tableau1[[#This Row],[Charges annuelles]]+Tableau1[[#This Row],[Taxe foncière]]+Tableau1[[#This Row],[Marketing]],"") -> 184800 | AF19: / | AG19: / | AH19: / | AI19: En l'état du précédent locataire | AJ19: A étudier | AK19: Chaude et froide | AL19: Cash Piscine, Lyre, Kraft, Vib's, Cache Cache, Grain de Malice, Bréal, Canadian Store | AM19: 1 000 places de parking. | AN19: 2 500 € HT | AO19: 30% du loyer facial avec un minimum de 15 000 € HT | AP19: 48.197608 | AQ19: -1.725854 | AR19: 6.1 | AS19: https://pub-843c46afc4cb41489909bce00c9b143d.r2.dev/6.1%20-%20La%20M%C3%A9zi%C3%A8re/1.jpg | AT19: Oui | AU19: Au BP | AV19: Twenty Two
A20: =VLOOKUP(Tableau1[[#This Row],[N° Département]],Feuil1!$C$6:$E$106,3) -> Bretagne | B20: =VLOOKUP(Tableau1[[#This Row],[N° Département]],Feuil1!$C$6:$E$106,2) -> Ille-et-Vilaine | C20: =LEFT(Tableau1[[#This Row],[Code Postal]],2)*1 -> 35 | D20: ZAC de Cap Malo | E20: 35520 | F20: La Mézière | G20: =Tableau1[[#This Row],[Rue]]&CHAR(10)&Tableau1[[#This Row],[Code Postal]]&" - "&Tableau1[[#This Row],[Ville]] -> ZAC de Cap Malo 35520 - La Mézière | H20: https://maps.app.goo.gl/jKvNrbE9PyvENUPV6 | I20: Périphérie | J20: Retail Park | K20: / | M20: / | N20: 2 | O20: 1200 | P20: / | Q20: 2400 | R20: / | S20: / | T20: =Tableau1[[#This Row],[Loyer €/m²]]*Tableau1[[#This Row],[Surface GLA]] -> 120000 | U20: =IFERROR(Tableau1[[#This Row],[Loyer annuel]]/12,"") -> 10000 | V20: 100 | W20: / | X20: =Tableau1[[#This Row],[Charges €/m²]]*Tableau1[[#This Row],[Surface GLA]] -> 30000 | Y20: =Tableau1[[#This Row],[Charges annuelles]]/12 -> 2500 | Z20: 25 | AA20: =IFERROR(Tableau1[[#This Row],[Taxe foncière €/m²]]*Tableau1[[#This Row],[Surface GLA]],) -> 9600 | AB20: 8 | AC20: =IFERROR(Tableau1[[#This Row],[Marketing €/m²]]*Tableau1[[#This Row],[Surface GLA]],) -> 0 | AD20: / | AE20: =IFERROR(Tableau1[[#This Row],[Loyer annuel]]+Tableau1[[#This Row],[Charges annuelles]]+Tableau1[[#This Row],[Taxe foncière]]+Tableau1[[#This Row],[Marketing]],"") -> 159600 | AF20: / | AG20: / | AH20: / | AI20: En l'état du précédent locataire | AJ20: A étudier | AK20: Chaude et froide | AL20: Cash Piscine, Lyre, Kraft, Vib's, Cache Cache, Grain de Malice, Bréal, Canadian Store | AM20: 1 000 places de parking. | AN20: 2 500 € HT | AO20: 30% du loyer facial avec un minimum de 15 000 € HT | AP20: 48.197772 | AQ20: -1.725999 | AR20: 6.2 | AS20: https://pub-843c46afc4cb41489909bce00c9b143d.r2.dev/6.2%20-%20La%20M%C3%A9zi%C3%A8re/1.jpg | AT20: Oui | AU20: Au BP | AV20: Twenty Two
A21: =VLOOKUP(Tableau1[[#This Row],[N° Département]],Feuil1!$C$6:$E$106,3) -> Bretagne | B21: =VLOOKUP(Tableau1[[#This Row],[N° Département]],Feuil1!$C$6:$E$106,2) -> Ille-et-Vilaine | C21: =LEFT(Tableau1[[#This Row],[Code Postal]],2)*1 -> 35 | D21: ZAC de Cap Malo | E21: 35520 | F21: La Mézière | G21: =Tableau1[[#This Row],[Rue]]&CHAR(10)&Tableau1[[#This Row],[Code Postal]]&" - "&Tableau1[[#This Row],[Ville]] -> ZAC de Cap Malo 35520 - La Mézière | H21: https://maps.app.goo.gl/jKvNrbE9PyvENUPV6 | I21: Périphérie | J21: Retail Park | K21: / | M21: / | N21: 3 | O21: 549 | P21: / | Q21: 1051 | R21: / | S21: / | T21: =Tableau1[[#This Row],[Loyer €/m²]]*Tableau1[[#This Row],[Surface GLA]] -> 82350 | U21: =IFERROR(Tableau1[[#This Row],[Loyer annuel]]/12,"") -> 6862.5 | V21: 150 | W21: / | X21: =Tableau1[[#This Row],[Charges €/m²]]*Tableau1[[#This Row],[Surface GLA]] -> 13725 | Y21: =Tableau1[[#This Row],[Charges annuelles]]/12 -> 1143.75 | Z21: 25 | AA21: =IFERROR(Tableau1[[#This Row],[Taxe foncière €/m²]]*Tableau1[[#This Row],[Surface GLA]],) -> 4392 | AB21: 8 | AC21: =IFERROR(Tableau1[[#This Row],[Marketing €/m²]]*Tableau1[[#This Row],[Surface GLA]],) -> 0 | AD21: / | AE21: =IFERROR(Tableau1[[#This Row],[Loyer annuel]]+Tableau1[[#This Row],[Charges annuelles]]+Tableau1[[#This Row],[Taxe foncière]]+Tableau1[[#This Row],[Marketing]],"") -> 100467 | AF21: / | AG21: / | AH21: / | AI21: En l'état du précédent locataire | AJ21: A étudier | AK21: Chaude et froide | AL21: Cash Piscine, Lyre, Kraft, Vib's, Cache Cache, Grain de Malice, Bréal, Canadian Store | AM21: 1 000 places de parking. | AN21: 2 500 € HT | AO21: 30% du loyer facial avec un minimum de 15 000 € HT | AP21: 48.198039 | AQ21: -1.726240 | AR21: 6.3 | AS21: https://pub-843c46afc4cb41489909bce00c9b143d.r2.dev/6.3%20-%20La%20M%C3%A9zi%C3%A8re/1.jpg | AT21: Oui | AU21: Au BP | AV21: Twenty Two
A22: =VLOOKUP(Tableau1[[#This Row],[N° Département]],Feuil1!$C$6:$E$106,3) -> Bretagne | B22: =VLOOKUP(Tableau1[[#This Row],[N° Département]],Feuil1!$C$6:$E$106,2) -> Ille-et-Vilaine | C22: =LEFT(Tableau1[[#This Row],[Code Postal]],2)*1 -> 35 | D22: ZAC de Cap Malo | E22: 35520 | F22: La Mézière | G22: =Tableau1[[#This Row],[Rue]]&CHAR(10)&Tableau1[[#This Row],[Code Postal]]&" - "&Tableau1[[#This Row],[Ville]] -> ZAC de Cap Malo 35520 - La Mézière | H22: https://maps.app.goo.gl/jKvNrbE9PyvENUPV6 | I22: Périphérie | J22: Retail Park | K22: / | M22: / | N22: 4 | O22: 502 | P22: / | Q22: 1051 | R22: / | S22: / | T22: =Tableau1[[#This Row],[Loyer €/m²]]*Tableau1[[#This Row],[Surface GLA]] -> 75300 | U22: =IFERROR(Tableau1[[#This Row],[Loyer annuel]]/12,"") -> 6275 | V22: 150 | W22: / | X22: =Tableau1[[#This Row],[Charges €/m²]]*Tableau1[[#This Row],[Surface GLA]] -> 12550 | Y22: =Tableau1[[#This Row],[Charges annuelles]]/12 -> 1045.8333 | Z22: 25 | AA22: =IFERROR(Tableau1[[#This Row],[Taxe foncière €/m²]]*Tableau1[[#This Row],[Surface GLA]],) -> 4016 | AB22: 8 | AC22: =IFERROR(Tableau1[[#This Row],[Marketing €/m²]]*Tableau1[[#This Row],[Surface GLA]],) -> 0 | AD22: / | AE22: =IFERROR(Tableau1[[#This Row],[Loyer annuel]]+Tableau1[[#This Row],[Charges annuelles]]+Tableau1[[#This Row],[Taxe foncière]]+Tableau1[[#This Row],[Marketing]],"") -> 91866 | AF22: / | AG22: / | AH22: / | AI22: En l'état du précédent locataire | AJ22: A étudier | AK22: Chaude et froide | AL22: Cash Piscine, Lyre, Kraft, Vib's, Cache Cache, Grain de Malice, Bréal, Canadian Store | AM22: 1 000 places de parking. | AN22: 2 500 € HT | AO22: 30% du loyer facial avec un minimum de 15 000 € HT | AP22: 48.198166 | AQ22: -1.726390 | AR22: 6.4 | AS22: https://pub-843c46afc4cb41489909bce00c9b143d.r2.dev/6.4%20-%20La%20M%C3%A9zi%C3%A8re/1.jpg | AT22: Oui | AU22: Au BP | AV22: Twenty Two
A23: =VLOOKUP(Tableau1[[#This Row],[N° Département]],Feuil1!$C$6:$E$106,3) -> Bretagne | B23: =VLOOKUP(Tableau1[[#This Row],[N° Département]],Feuil1!$C$6:$E$106,2) -> Ille-et-Vilaine | C23: =LEFT(Tableau1[[#This Row],[Code Postal]],2)*1 -> 35 | D23: ZAC de Cap Malo | E23: 35520 | F23: La Mézière | G23: =Tableau1[[#This Row],[Rue]]&CHAR(10)&Tableau1[[#This Row],[Code Postal]]&" - "&Tableau1[[#This Row],[Ville]] -> ZAC de Cap Malo 35520 - La Mézière | H23: https://maps.app.goo.gl/jKvNrbE9PyvENUPV6 | I23: Périphérie | J23: Retail Park | K23: / | M23: / | N23: 5 | O23: 250 | P23: / | Q23: 514 | R23: / | S23: / | T23: =Tableau1[[#This Row],[Loyer €/m²]]*Tableau1[[#This Row],[Surface GLA]] -> 50000 | U23: =IFERROR(Tableau1[[#This Row],[Loyer annuel]]/12,"") -> 4166.6667 | V23: 200 | W23: / | X23: =Tableau1[[#This Row],[Charges €/m²]]*Tableau1[[#This Row],[Surface GLA]] -> 6250 | Y23: =Tableau1[[#This Row],[Charges annuelles]]/12 -> 520.83333 | Z23: 25 | AA23: =IFERROR(Tableau1[[#This Row],[Taxe foncière €/m²]]*Tableau1[[#This Row],[Surface GLA]],) -> 2000 | AB23: 8 | AC23: =IFERROR(Tableau1[[#This Row],[Marketing €/m²]]*Tableau1[[#This Row],[Surface GLA]],) -> 0 | AD23: / | AE23: =IFERROR(Tableau1[[#This Row],[Loyer annuel]]+Tableau1[[#This Row],[Charges annuelles]]+Tableau1[[#This Row],[Taxe foncière]]+Tableau1[[#This Row],[Marketing]],"") -> 58250 | AF23: / | AG23: / | AH23: / | AI23: En l'état du précédent locataire | AJ23: A étudier | AK23: Chaude et froide | AL23: Cash Piscine, Lyre, Kraft, Vib's, Cache Cache, Grain de Malice, Bréal, Canadian Store | AM23: 1 000 places de parking. | AN23: 2 500 € HT | AO23: 30% du loyer facial avec un minimum de 15 000 € HT | AP23: 48.198348 | AQ23: -1.726557 | AR23: 6.5 | AS23: https://pub-843c46afc4cb41489909bce00c9b143d.r2.dev/6.5%20-%20La%20M%C3%A9zi%C3%A8re/1.jpg | AT23: Oui | AU23: Au BP | AV23: Twenty Two
A24: =VLOOKUP(Tableau1[[#This Row],[N° Département]],Feuil1!$C$6:$E$106,3) -> Bretagne | B24: =VLOOKUP(Tableau1[[#This Row],[N° Département]],Feuil1!$C$6:$E$106,2) -> Ille-et-Vilaine | C24: =LEFT(Tableau1[[#This Row],[Code Postal]],2)*1 -> 35 | D24: ZAC de Cap Malo | E24: 35520 | F24: La Mézière | G24: =Tableau1[[#This Row],[Rue]]&CHAR(10)&Tableau1[[#This Row],[Code Postal]]&" - "&Tableau1[[#This Row],[Ville]] -> ZAC de Cap Malo 35520 - La Mézière | H24: https://maps.app.goo.gl/jKvNrbE9PyvENUPV6 | I24: Périphérie | J24: Retail Park | K24: / | M24: / | N24: 6 | O24: 264 | P24: / | Q24: 514 | R24: / | S24: / | T24: =Tableau1[[#This Row],[Loyer €/m²]]*Tableau1[[#This Row],[Surface GLA]] -> 52800 | U24: =IFERROR(Tableau1[[#This Row],[Loyer annuel]]/12,"") -> 4400 | V24: 200 | W24: / | X24: =Tableau1[[#This Row],[Charges €/m²]]*Tableau1[[#This Row],[Surface GLA]] -> 6600 | Y24: =Tableau1[[#This Row],[Charges annuelles]]/12 -> 550 | Z24: 25 | AA24: =IFERROR(Tableau1[[#This Row],[Taxe foncière €/m²]]*Tableau1[[#This Row],[Surface GLA]],) -> 2112 | AB24: 8 | AC24: =IFERROR(Tableau1[[#This Row],[Marketing €/m²]]*Tableau1[[#This Row],[Surface GLA]],) -> 0 | AD24: / | AE24: =IFERROR(Tableau1[[#This Row],[Loyer annuel]]+Tableau1[[#This Row],[Charges annuelles]]+Tableau1[[#This Row],[Taxe foncière]]+Tableau1[[#This Row],[Marketing]],"") -> 61512 | AF24: / | AG24: / | AH24: / | AI24: En l'état du précédent locataire | AJ24: A étudier | AK24: Chaude et froide | AL24: Cash Piscine, Lyre, Kraft, Vib's, Cache Cache, Grain de Malice, Bréal, Canadian Store | AM24: 1 000 places de parking. | AN24: 2 500 € HT | AO24: 30% du loyer facial avec un minimum de 15 000 € HT | AP24: 48.198452 | AQ24: -1.726667 | AR24: 6.6 | AS24: https://pub-843c46afc4cb41489909bce00c9b143d.r2.dev/6.6%20-%20La%20M%C3%A9zi%C3%A8re/1.jpg | AT24: Oui | AU24: Au BP | AV24: Twenty Two
A25: =VLOOKUP(Tableau1[[#This Row],[N° Département]],Feuil1!$C$6:$E$106,3) -> Bretagne | B25: =VLOOKUP(Tableau1[[#This Row],[N° Département]],Feuil1!$C$6:$E$106,2) -> Ille-et-Vilaine | C25: =LEFT(Tableau1[[#This Row],[Code Postal]],2)*1 -> 35 | D25: ZAC de Cap Malo | E25: 35520 | F25: La Mézière | G25: =Tableau1[[#This Row],[Rue]]&CHAR(10)&Tableau1[[#This Row],[Code Postal]]&" - "&Tableau1[[#This Row],[Ville]] -> ZAC de Cap Malo 35520 - La Mézière | H25: https://maps.app.goo.gl/jKvNrbE9PyvENUPV6 | I25: Périphérie | J25: Retail Park | K25: / | M25: / | N25: 7 | O25: 486 | P25: / | Q25: / | R25: / | S25: / | T25: =Tableau1[[#This Row],[Loyer €/m²]]*Tableau1[[#This Row],[Surface GLA]] -> 72900 | U25: =IFERROR(Tableau1[[#This Row],[Loyer annuel]]/12,"") -> 6075 | V25: 150 | W25: / | X25: =Tableau1[[#This Row],[Charges €/m²]]*Tableau1[[#This Row],[Surface GLA]] -> 12150 | Y25: =Tableau1[[#This Row],[Charges annuelles]]/12 -> 1012.5 | Z25: 25 | AA25: =IFERROR(Tableau1[[#This Row],[Taxe foncière €/m²]]*Tableau1[[#This Row],[Surface GLA]],) -> 3888 | AB25: 8 | AC25: =IFERROR(Tableau1[[#This Row],[Marketing €/m²]]*Tableau1[[#This Row],[Surface GLA]],) -> 0 | AD25: / | AE25: =IFERROR(Tableau1[[#This Row],[Loyer annuel]]+Tableau1[[#This Row],[Charges annuelles]]+Tableau1[[#This Row],[Taxe foncière]]+Tableau1[[#This Row],[Marketing]],"") -> 88938 | AF25: / | AG25: / | AH25: / | AI25: En l'état du précédent locataire | AJ25: A étudier | AK25: Chaude et froide | AL25: Cash Piscine, Lyre, Kraft, Vib's, Cache Cache, Grain de Malice, Bréal, Canadian Store | AM25: 1 000 places de parking. | AN25: 2 500 € HT | AO25: 30% du loyer facial avec un minimum de 15 000 € HT | AP25: 48.198584 | AQ25: -1.726814 | AR25: 6.7 | AS25: https://pub-843c46afc4cb41489909bce00c9b143d.r2.dev/6.7%20-%20La%20M%C3%A9zi%C3%A8re/1.jpg | AT25: Oui | AU25: Au BP | AV25: Twenty Two
A26: =VLOOKUP(Tableau1[[#This Row],[N° Département]],Feuil1!$C$6:$E$106,3) -> Bretagne | B26: =VLOOKUP(Tableau1[[#This Row],[N° Département]],Feuil1!$C$6:$E$106,2) -> Ille-et-Vilaine | C26: =LEFT(Tableau1[[#This Row],[Code Postal]],2)*1 -> 35 | D26: ZAC de Cap Malo | E26: 35520 | F26: La Mézière | G26: =Tableau1[[#This Row],[Rue]]&CHAR(10)&Tableau1[[#This Row],[Code Postal]]&" - "&Tableau1[[#This Row],[Ville]] -> ZAC de Cap Malo 35520 - La Mézière | H26: https://maps.app.goo.gl/jKvNrbE9PyvENUPV6 | I26: Périphérie | J26: Retail Park | K26: / | M26: / | N26: 8 | O26: 267 | P26: / | Q26: 1060 | R26: / | S26: / | T26: =Tableau1[[#This Row],[Loyer €/m²]]*Tableau1[[#This Row],[Surface GLA]] -> 53400 | U26: =IFERROR(Tableau1[[#This Row],[Loyer annuel]]/12,"") -> 4450 | V26: 200 | W26: / | X26: =Tableau1[[#This Row],[Charges €/m²]]*Tableau1[[#This Row],[Surface GLA]] -> 6675 | Y26: =Tableau1[[#This Row],[Charges annuelles]]/12 -> 556.25 | Z26: 25 | AA26: =IFERROR(Tableau1[[#This Row],[Taxe foncière €/m²]]*Tableau1[[#This Row],[Surface GLA]],) -> 2136 | AB26: 8 | AC26: =IFERROR(Tableau1[[#This Row],[Marketing €/m²]]*Tableau1[[#This Row],[Surface GLA]],) -> 0 | AD26: / | AE26: =IFERROR(Tableau1[[#This Row],[Loyer annuel]]+Tableau1[[#This Row],[Charges annuelles]]+Tableau1[[#This Row],[Taxe foncière]]+Tableau1[[#This Row],[Marketing]],"") -> 62211 | AF26: / | AG26: / | AH26: / | AI26: En l'état du précédent locataire | AJ26: A étudier | AK26: Chaude et froide | AL26: Cash Piscine, Lyre, Kraft, Vib's, Cache Cache, Grain de Malice, Bréal, Canadian Store | AM26: 1 000 places de parking. | AN26: 2 500 € HT | AO26: 30% du loyer facial avec un minimum de 15 000 € HT | AP26: 48.198731 | AQ26: -1.726769 | AR26: 6.8 | AS26: https://pub-843c46afc4cb41489909bce00c9b143d.r2.dev/6.8%20-%20La%20M%C3%A9zi%C3%A8re/1.jpg | AT26: Oui | AU26: Au BP | AV26: Twenty Two
A27: =VLOOKUP(Tableau1[[#This Row],[N° Département]],Feuil1!$C$6:$E$106,3) -> Bretagne | B27: =VLOOKUP(Tableau1[[#This Row],[N° Département]],Feuil1!$C$6:$E$106,2) -> Ille-et-Vilaine | C27: =LEFT(Tableau1[[#This Row],[Code Postal]],2)*1 -> 35 | D27: ZAC de Cap Malo | E27: 35520 | F27: La Mézière | G27: =Tableau1[[#This Row],[Rue]]&CHAR(10)&Tableau1[[#This Row],[Code Postal]]&" - "&Tableau1[[#This Row],[Ville]] -> ZAC de Cap Malo 35520 - La Mézière | H27: https://maps.app.goo.gl/jKvNrbE9PyvENUPV6 | I27: Périphérie | J27: Retail Park | K27: / | M27: / | N27: 9 | O27: 321 | P27: / | Q27: 1060 | R27: / | S27: / | T27: =Tableau1[[#This Row],[Loyer €/m²]]*Tableau1[[#This Row],[Surface GLA]] -> 48150 | U27: =IFERROR(Tableau1[[#This Row],[Loyer annuel]]/12,"") -> 4012.5 | V27: 150 | W27: / | X27: =Tableau1[[#This Row],[Charges €/m²]]*Tableau1[[#This Row],[Surface GLA]] -> 8025 | Y27: =Tableau1[[#This Row],[Charges annuelles]]/12 -> 668.75 | Z27: 25 | AA27: =IFERROR(Tableau1[[#This Row],[Taxe foncière €/m²]]*Tableau1[[#This Row],[Surface GLA]],) -> 2568 | AB27: 8 | AC27: =IFERROR(Tableau1[[#This Row],[Marketing €/m²]]*Tableau1[[#This Row],[Surface GLA]],) -> 0 | AD27: / | AE27: =IFERROR(Tableau1[[#This Row],[Loyer annuel]]+Tableau1[[#This Row],[Charges annuelles]]+Tableau1[[#This Row],[Taxe foncière]]+Tableau1[[#This Row],[Marketing]],"") -> 58743 | AF27: / | AG27: / | AH27: / | AI27: En l'état du précédent locataire | AJ27: A étudier | AK27: Chaude et froide | AL27: Cash Piscine, Lyre, Kraft, Vib's, Cache Cache, Grain de Malice, Bréal, Canadian Store | AM27: 1 000 places de parking. | AN27: 2 500 € HT | AO27: 30% du loyer facial avec un minimum de 15 000 € HT | AP27: 48.198775 | AQ27: -1.726648 | AR27: 6.9 | AS27: https://pub-843c46afc4cb41489909bce00c9b143d.r2.dev/6.9%20-%20La%20M%C3%A9zi%C3%A8re/1.jpg | AT27: Oui | AU27: Au BP | AV27: Twenty Two
A28: =VLOOKUP(Tableau1[[#This Row],[N° Département]],Feuil1!$C$6:$E$106,3) -> Bretagne | B28: =VLOOKUP(Tableau1[[#This Row],[N° Département]],Feuil1!$C$6:$E$106,2) -> Ille-et-Vilaine | C28: =LEFT(Tableau1[[#This Row],[Code Postal]],2)*1 -> 35 | D28: ZAC de Cap Malo | E28: 35520 | F28: La Mézière | G28: =Tableau1[[#This Row],[Rue]]&CHAR(10)&Tableau1[[#This Row],[Code Postal]]&" - "&Tableau1[[#This Row],[Ville]] -> ZAC de Cap Malo 35520 - La Mézière | H28: https://maps.app.goo.gl/jKvNrbE9PyvENUPV6 | I28: Périphérie | J28: Retail Park | K28: / | M28: / | N28: 10 | O28: 472 | P28: / | Q28: 1060 | R28: / | S28: / | T28: =Tableau1[[#This Row],[Loyer €/m²]]*Tableau1[[#This Row],[Surface GLA]] -> 70800 | U28: =IFERROR(Tableau1[[#This Row],[Loyer annuel]]/12,"") -> 5900 | V28: 150 | W28: / | X28: =Tableau1[[#This Row],[Charges €/m²]]*Tableau1[[#This Row],[Surface GLA]] -> 11800 | Y28: =Tableau1[[#This Row],[Charges annuelles]]/12 -> 983.33333 | Z28: 25 | AA28: =IFERROR(Tableau1[[#This Row],[Taxe foncière €/m²]]*Tableau1[[#This Row],[Surface GLA]],) -> 3776 | AB28: 8 | AC28: =IFERROR(Tableau1[[#This Row],[Marketing €/m²]]*Tableau1[[#This Row],[Surface GLA]],) -> 0 | AD28: / | AE28: =IFERROR(Tableau1[[#This Row],[Loyer annuel]]+Tableau1[[#This Row],[Charges annuelles]]+Tableau1[[#This Row],[Taxe foncière]]+Tableau1[[#This Row],[Marketing]],"") -> 86376 | AF28: / | AG28: / | AH28: / | AI28: En l'état du précédent locataire | AJ28: A étudier | AK28: Chaude et froide | AL28: Cash Piscine, Lyre, Kraft, Vib's, Cache Cache, Grain de Malice, Bréal, Canadian Store | AM28: 1 000 places de parking. | AN28: 2 500 € HT | AO28: 30% du loyer facial avec un minimum de 15 000 € HT | AP28: 48.198827 | AQ28: -1.726519 | AR28: 6.10 | AS28: https://pub-843c46afc4cb41489909bce00c9b143d.r2.dev/6.10%20-%20La%20M%C3%A9zi%C3%A8re/1.jpg | AT28: Oui | AU28: Au BP | AV28: Twenty Two
A29: =VLOOKUP(Tableau1[[#This Row],[N° Département]],Feuil1!$C$6:$E$106,3) -> Bretagne | B29: =VLOOKUP(Tableau1[[#This Row],[N° Département]],Feuil1!$C$6:$E$106,2) -> Ille-et-Vilaine | C29: =LEFT(Tableau1[[#This Row],[Code Postal]],2)*1 -> 35 | D29: ZAC de Cap Malo | E29: 35520 | F29: La Mézière | G29: =Tableau1[[#This Row],[Rue]]&CHAR(10)&Tableau1[[#This Row],[Code Postal]]&" - "&Tableau1[[#This Row],[Ville]] -> ZAC de Cap Malo 35520 - La Mézière | H29: https://maps.app.goo.gl/jKvNrbE9PyvENUPV6 | I29: Périphérie | J29: Retail Park | K29: / | M29: / | N29: 11 | O29: 1195 | P29: / | Q29: 1365 | R29: / | S29: / | T29: =Tableau1[[#This Row],[Loyer €/m²]]*Tableau1[[#This Row],[Surface GLA]] -> 119500 | U29: =IFERROR(Tableau1[[#This Row],[Loyer annuel]]/12,"") -> 9958.3333 | V29: 100 | W29: / | X29: =Tableau1[[#This Row],[Charges €/m²]]*Tableau1[[#This Row],[Surface GLA]] -> 29875 | Y29: =Tableau1[[#This Row],[Charges annuelles]]/12 -> 2489.5833 | Z29: 25 | AA29: =IFERROR(Tableau1[[#This Row],[Taxe foncière €/m²]]*Tableau1[[#This Row],[Surface GLA]],) -> 9560 | AB29: 8 | AC29: =IFERROR(Tableau1[[#This Row],[Marketing €/m²]]*Tableau1[[#This Row],[Surface GLA]],) -> 0 | AD29: / | AE29: =IFERROR(Tableau1[[#This Row],[Loyer annuel]]+Tableau1[[#This Row],[Charges annuelles]]+Tableau1[[#This Row],[Taxe foncière]]+Tableau1[[#This Row],[Marketing]],"") -> 158935 | AF29: / | AG29: / | AH29: / | AI29: En l'état du précédent locataire | AJ29: A étudier | AK29: Chaude et froide | AL29: Cash Piscine, Lyre, Kraft, Vib's, Cache Cache, Grain de Malice, Bréal, Canadian Store | AM29: 1 000 places de parking. | AN29: 2 500 € HT | AO29: 30% du loyer facial avec un minimum de 15 000 € HT | AP29: 48.199004 | AQ29: -1.726162 | AR29: 6.11 | AS29: https://pub-843c46afc4cb41489909bce00c9b143d.r2.dev/6.11%20-%20La%20M%C3%A9zi%C3%A8re/1.jpg; https://pub-843c46afc4cb41489909bce00c9b143d.r2.dev/6.11%20-%20La%20M%C3%A9zi%C3%A8re/2.jpg | AT29: Oui | AU29: Au BP | AV29: Twenty Two
A30: =VLOOKUP(Tableau1[[#This Row],[N° Département]],Feuil1!$C$6:$E$106,3) -> Bretagne | B30: =VLOOKUP(Tableau1[[#This Row],[N° Département]],Feuil1!$C$6:$E$106,2) -> Ille-et-Vilaine | C30: =LEFT(Tableau1[[#This Row],[Code Postal]],2)*1 -> 35 | D30: ZAC de Cap Malo | E30: 35520 | F30: La Mézière | G30: =Tableau1[[#This Row],[Rue]]&CHAR(10)&Tableau1[[#This Row],[Code Postal]]&" - "&Tableau1[[#This Row],[Ville]] -> ZAC de Cap Malo 35520 - La Mézière | H30: https://maps.app.goo.gl/jKvNrbE9PyvENUPV6 | I30: Périphérie | J30: Retail Park | K30: / | M30: / | N30: 12 | O30: 170 | P30: / | Q30: 1365 | R30: / | S30: / | T30: =Tableau1[[#This Row],[Loyer €/m²]]*Tableau1[[#This Row],[Surface GLA]] -> 34000 | U30: =IFERROR(Tableau1[[#This Row],[Loyer annuel]]/12,"") -> 2833.3333 | V30: 200 | W30: / | X30: =Tableau1[[#This Row],[Charges €/m²]]*Tableau1[[#This Row],[Surface GLA]] -> 4250 | Y30: =Tableau1[[#This Row],[Charges annuelles]]/12 -> 354.16667 | Z30: 25 | AA30: =IFERROR(Tableau1[[#This Row],[Taxe foncière €/m²]]*Tableau1[[#This Row],[Surface GLA]],) -> 1360 | AB30: 8 | AC30: =IFERROR(Tableau1[[#This Row],[Marketing €/m²]]*Tableau1[[#This Row],[Surface GLA]],) -> 0 | AD30: / | AE30: =IFERROR(Tableau1[[#This Row],[Loyer annuel]]+Tableau1[[#This Row],[Charges annuelles]]+Tableau1[[#This Row],[Taxe foncière]]+Tableau1[[#This Row],[Marketing]],"") -> 39610 | AF30: / | AG30: / | AH30: / | AI30: En l'état du précédent locataire | AJ30: A étudier | AK30: Chaude et froide | AL30: Cash Piscine, Lyre, Kraft, Vib's, Cache Cache, Grain de Malice, Bréal, Canadian Store | AM30: 1 000 places de parking. | AN30: 2 500 € HT | AO30: 30% du loyer facial avec un minimum de 15 000 € HT | AP30: 48.199088 | AQ30: -1.725948 | AR30: 6.12 | AS30: https://pub-843c46afc4cb41489909bce00c9b143d.r2.dev/6.12%20-%20La%20M%C3%A9zi%C3%A8re/1.jpg; https://pub-843c46afc4cb41489909bce00c9b143d.r2.dev/6.12%20-%20La%20M%C3%A9zi%C3%A8re/2.jpg | AT30: Oui | AU30: Au BP | AV30: Twenty Two
A31: =VLOOKUP(Tableau1[[#This Row],[N° Département]],Feuil1!$C$6:$E$106,3) -> Pays de la Loire | B31: =VLOOKUP(Tableau1[[#This Row],[N° Département]],Feuil1!$C$6:$E$106,2) -> Sarthe | C31: =LEFT(Tableau1[[#This Row],[Code Postal]],2)*1 -> 72 | D31: 18 Avenue Pierre Mendès France | E31: 72100 | F31: Le Mans | G31: =Tableau1[[#This Row],[Rue]]&CHAR(10)&Tableau1[[#This Row],[Code Postal]]&" - "&Tableau1[[#This Row],[Ville]] -> 18 Avenue Pierre Mendès France 72100 - Le Mans | H31: https://maps.app.goo.gl/ngVAd1ZcuWEZcS5U8 | I31: Centre Ville | J31: Centre Commercial | K31: / | M31: / | N31: 12 | O31: 61 | P31: / | Q31: / | R31: / | S31: / | T31: =Tableau1[[#This Row],[Loyer €/m²]]*Tableau1[[#This Row],[Surface GLA]] -> 36600 | U31: =IFERROR(Tableau1[[#This Row],[Loyer annuel]]/12,"") -> 3050 | V31: 600 | W31: / | X31: =Tableau1[[#This Row],[Charges €/m²]]*Tableau1[[#This Row],[Surface GLA]] -> 13420 | Y31: =Tableau1[[#This Row],[Charges annuelles]]/12 -> 1118.3333 | Z31: 220 | AA31: =IFERROR(Tableau1[[#This Row],[Taxe foncière €/m²]]*Tableau1[[#This Row],[Surface GLA]],) -> 0 | AB31: / | AC31: =IFERROR(Tableau1[[#This Row],[Marketing €/m²]]*Tableau1[[#This Row],[Surface GLA]],) -> 0 | AD31: / | AE31: =IFERROR(Tableau1[[#This Row],[Loyer annuel]]+Tableau1[[#This Row],[Charges annuelles]]+Tableau1[[#This Row],[Taxe foncière]]+Tableau1[[#This Row],[Marketing]],"") -> 50020 | AF31: / | AG31: / | AH31: / | AI31: En l'état du précédent locataire | AJ31: Non | AK31: Froide | AL31: Fnac, Natures et Découvertes, C&A, Sostrene Grene, Nocibé, Devred, Micormania, Franck Provost, Moa, Adopt | AM31: Local situé au niveau inférieur. Centre commercial en cœur de ville. Toutes charges incluses | AO31: 30% du loyer facial avec un minimum de 15 000 € HT | AP31: 48.006866 | AQ31: 0.198918 | AR31: 7.1 | AS31: https://pub-843c46afc4cb41489909bce00c9b143d.r2.dev/7.1%20-%20Le%20Mans/1.jpg; https://pub-843c46afc4cb41489909bce00c9b143d.r2.dev/7.1%20-%20Le%20Mans/2.jpg; https://pub-843c46afc4cb41489909bce00c9b143d.r2.dev/7.1%20-%20Le%20Mans/3.jpg; https://pub-843c46afc4cb41489909bce00c9b143d.r2.dev/7.1%20-%20Le%20Mans/4.jpg; https://pub-843c46afc4cb41489909bce00c9b143d.r2.dev/7.1%20-%20Le%20Mans/5%20Niveau%20inf%C3%A9rieur.jpg; https://pub-843c46afc4cb41489909bce00c9b143d.r2.dev/7.1%20-%20Le%20Mans/6%20Niveau%20sup%C3%A9rieur.jpg | AT31: Oui | AU31: 500 €/m² | AV31: Othrys
A32: =VLOOKUP(Tableau1[[#This Row],[N° Département]],Feuil1!$C$6:$E$106,3) -> Pays de la Loire | B32: =VLOOKUP(Tableau1[[#This Row],[N° Département]],Feuil1!$C$6:$E$106,2) -> Sarthe | C32: =LEFT(Tableau1[[#This Row],[Code Postal]],2)*1 -> 72 | D32: 19 Avenue Pierre Mendès France | E32: 72101 | F32: Le Mans | G32: =Tableau1[[#This Row],[Rue]]&CHAR(10)&Tableau1[[#This Row],[Code Postal]]&" - "&Tableau1[[#This Row],[Ville]] -> 19 Avenue Pierre Mendès France 72101 - Le Mans | H32: https://maps.app.goo.gl/ngVAd1ZcuWEZcS5U9 | I32: Centre Ville | J32: Centre Commercial | K32: / | M32: / | N32: 19 | O32: 10 | P32: / | Q32: / | R32: / | S32: / | T32: =Tableau1[[#This Row],[Loyer €/m²]]*Tableau1[[#This Row],[Surface GLA]] -> 15000 | U32: =IFERROR(Tableau1[[#This Row],[Loyer annuel]]/12,"") -> 1250 | V32: 1500 | X32: =Tableau1[[#This Row],[Charges €/m²]]*Tableau1[[#This Row],[Surface GLA]] -> 2200 | Y32: =Tableau1[[#This Row],[Charges annuelles]]/12 -> 183.33333 | Z32: 220 | AA32: =IFERROR(Tableau1[[#This Row],[Taxe foncière €/m²]]*Tableau1[[#This Row],[Surface GLA]],) -> 0 | AB32: / | AC32: =IFERROR(Tableau1[[#This Row],[Marketing €/m²]]*Tableau1[[#This Row],[Surface GLA]],) -> 0 | AD32: / | AE32: =IFERROR(Tableau1[[#This Row],[Loyer annuel]]+Tableau1[[#This Row],[Charges annuelles]]+Tableau1[[#This Row],[Taxe foncière]]+Tableau1[[#This Row],[Marketing]],"") -> 17200 | AF32: / | AG32: / | AH32: / | AI32: En l'état du précédent locataire | AJ32: Non | AK32: Froide | AL32: Fnac, Natures et Découvertes, C&A, Sostrene Grene, Nocibé, Devred, Micormania, Franck Provost, Moa, Adopt | AM32: Kiosque situé au niveau inférieur. Centre commercial en cœur de ville. Toutes charges incluses | AO32: 30% du loyer facial avec un minimum de 15 000 € HT | AP32: 48.006664 | AQ32: 0.199208 | AR32: 7.2 | AS32: https://pub-843c46afc4cb41489909bce00c9b143d.r2.dev/7.1%20-%20Le%20Mans/1.jpg; https://pub-843c46afc4cb41489909bce00c9b143d.r2.dev/7.1%20-%20Le%20Mans/2.jpg; https://pub-843c46afc4cb41489909bce00c9b143d.r2.dev/7.1%20-%20Le%20Mans/3.jpg; https://pub-843c46afc4cb41489909bce00c9b143d.r2.dev/7.1%20-%20Le%20Mans/4.jpg; https://pub-843c46afc4cb41489909bce00c9b143d.r2.dev/7.1%20-%20Le%20Mans/5%20Niveau%20inf%C3%A9rieur.jpg; https://pub-843c46afc4cb41489909bce00c9b143d.r2.dev/7.1%20-%20Le%20Mans/6%20Niveau%20sup%C3%A9rieur.jpg | AT32: Oui | AU32: 500 €/m² | AV32: Othrys
A33: =VLOOKUP(Tableau1[[#This Row],[N° Département]],Feuil1!$C$6:$E$106,3) -> Pays de la Loire | B33: =VLOOKUP(Tableau1[[#This Row],[N° Département]],Feuil1!$C$6:$E$106,2) -> Sarthe | C33: =LEFT(Tableau1[[#This Row],[Code Postal]],2)*1 -> 72 | D33: 18 Avenue Pierre Mendès France | E33: 72100 | F33: Le Mans | G33: =Tableau1[[#This Row],[Rue]]&CHAR(10)&Tableau1[[#This Row],[Code Postal]]&" - "&Tableau1[[#This Row],[Ville]] -> 18 Avenue Pierre Mendès France 72100 - Le Mans | H33: https://maps.app.goo.gl/ngVAd1ZcuWEZcS5U8 | I33: Centre Ville | J33: Centre Commercial | K33: / | M33: / | N33: 26 | O33: 227 | P33: / | Q33: / | R33: / | S33: / | T33: =Tableau1[[#This Row],[Loyer €/m²]]*Tableau1[[#This Row],[Surface GLA]] -> 90800 | U33: =IFERROR(Tableau1[[#This Row],[Loyer annuel]]/12,"") -> 7566.6667 | V33: 400 | W33: / | X33: =Tableau1[[#This Row],[Charges €/m²]]*Tableau1[[#This Row],[Surface GLA]] -> 49940 | Y33: =Tableau1[[#This Row],[Charges annuelles]]/12 -> 4161.6667 | Z33: 220 | AA33: =IFERROR(Tableau1[[#This Row],[Taxe foncière €/m²]]*Tableau1[[#This Row],[Surface GLA]],) -> 0 | AB33: / | AC33: =IFERROR(Tableau1[[#This Row],[Marketing €/m²]]*Tableau1[[#This Row],[Surface GLA]],) -> 0 | AD33: / | AE33: =IFERROR(Tableau1[[#This Row],[Loyer annuel]]+Tableau1[[#This Row],[Charges annuelles]]+Tableau1[[#This Row],[Taxe foncière]]+Tableau1[[#This Row],[Marketing]],"") -> 140740 | AF33: / | AG33: / | AH33: / | AI33: En l'état du précédent locataire | AJ33: Non | AK33: Froide | AL33: Fnac, Natures et Découvertes, C&A, Sostrene Grene, Nocibé, Devred, Micormania, Franck Provost, Moa, Adopt | AM33: Local situé au niveau inférieur. Centre commercial en cœur de ville. Toutes charges incluses | AO33: 30% du loyer facial avec un minimum de 15 000 € HT | AP33: 48.006755 | AQ33: 0.199409 | AR33: 7.3 | AS33: https://pub-843c46afc4cb41489909bce00c9b143d.r2.dev/7.1%20-%20Le%20Mans/1.jpg; https://pub-843c46afc4cb41489909bce00c9b143d.r2.dev/7.1%20-%20Le%20Mans/2.jpg; https://pub-843c46afc4cb41489909bce00c9b143d.r2.dev/7.1%20-%20Le%20Mans/3.jpg; https://pub-843c46afc4cb41489909bce00c9b143d.r2.dev/7.1%20-%20Le%20Mans/4.jpg; https://pub-843c46afc4cb41489909bce00c9b143d.r2.dev/7.1%20-%20Le%20Mans/5%20Niveau%20inf%C3%A9rieur.jpg; https://pub-843c46afc4cb41489909bce00c9b143d.r2.dev/7.1%20-%20Le%20Mans/6%20Niveau%20sup%C3%A9rieur.jpg | AT33: Oui | AU33: 500 €/m² | AV33: Othrys
A34: =VLOOKUP(Tableau1[[#This Row],[N° Département]],Feuil1!$C$6:$E$106,3) -> Pays de la Loire | B34: =VLOOKUP(Tableau1[[#This Row],[N° Département]],Feuil1!$C$6:$E$106,2) -> Sarthe | C34: =LEFT(Tableau1[[#This Row],[Code Postal]],2)*1 -> 72 | D34: 18 Avenue Pierre Mendès France | E34: 72100 | F34: Le Mans | G34: =Tableau1[[#This Row],[Rue]]&CHAR(10)&Tableau1[[#This Row],[Code Postal]]&" - "&Tableau1[[#This Row],[Ville]] -> 18 Avenue Pierre Mendès France 72100 - Le Mans | H34: https://maps.app.goo.gl/ngVAd1ZcuWEZcS5U8 | I34: Centre Ville | J34: Centre Commercial | K34: / | M34: / | N34: 32 | O34: 102 | P34: / | Q34: / | R34: / | S34: / | T34: =Tableau1[[#This Row],[Loyer €/m²]]*Tableau1[[#This Row],[Surface GLA]] -> 51000 | U34: =IFERROR(Tableau1[[#This Row],[Loyer annuel]]/12,"") -> 4250 | V34: 500 | W34: / | X34: =Tableau1[[#This Row],[Charges €/m²]]*Tableau1[[#This Row],[Surface GLA]] -> 22440 | Y34: =Tableau1[[#This Row],[Charges annuelles]]/12 -> 1870 | Z34: 220 | AA34: =IFERROR(Tableau1[[#This Row],[Taxe foncière €/m²]]*Tableau1[[#This Row],[Surface GLA]],) -> 0 | AB34: / | AC34: =IFERROR(Tableau1[[#This Row],[Marketing €/m²]]*Tableau1[[#This Row],[Surface GLA]],) -> 0 | AD34: / | AE34: =IFERROR(Tableau1[[#This Row],[Loyer annuel]]+Tableau1[[#This Row],[Charges annuelles]]+Tableau1[[#This Row],[Taxe foncière]]+Tableau1[[#This Row],[Marketing]],"") -> 73440 | AF34: / | AG34: / | AH34: / | AI34: En l'état du précédent locataire | AJ34: Non | AK34: Froide | AL34: Fnac, Natures et Découvertes, C&A, Sostrene Grene, Nocibé, Devred, Micormania, Franck Provost, Moa, Adopt | AM34: Local situé au niveau supérieur. Centre commercial en cœur de ville. Toutes charges incluses | AO34: 30% du loyer facial avec un minimum de 15 000 € HT | AP34: 48.006917 | AQ34: 0.198996 | AR34: 7.4 | AS34: https://pub-843c46afc4cb41489909bce00c9b143d.r2.dev/7.1%20-%20Le%20Mans/1.jpg; https://pub-843c46afc4cb41489909bce00c9b143d.r2.dev/7.1%20-%20Le%20Mans/2.jpg; https://pub-843c46afc4cb41489909bce00c9b143d.r2.dev/7.1%20-%20Le%20Mans/3.jpg; https://pub-843c46afc4cb41489909bce00c9b143d.r2.dev/7.1%20-%20Le%20Mans/4.jpg; https://pub-843c46afc4cb41489909bce00c9b143d.r2.dev/7.1%20-%20Le%20Mans/5%20Niveau%20inf%C3%A9rieur.jpg; https://pub-843c46afc4cb41489909bce00c9b143d.r2.dev/7.1%20-%20Le%20Mans/6%20Niveau%20sup%C3%A9rieur.jpg | AT34: Oui | AU34: 500 €/m² | AV34: Othrys
A35: =VLOOKUP(Tableau1[[#This Row],[N° Département]],Feuil1!$C$6:$E$106,3) -> Pays de la Loire | B35: =VLOOKUP(Tableau1[[#This Row],[N° Département]],Feuil1!$C$6:$E$106,2) -> Sarthe | C35: =LEFT(Tableau1[[#This Row],[Code Postal]],2)*1 -> 72 | D35: 18 Avenue Pierre Mendès France | E35: 72100 | F35: Le Mans | G35: =Tableau1[[#This Row],[Rue]]&CHAR(10)&Tableau1[[#This Row],[Code Postal]]&" - "&Tableau1[[#This Row],[Ville]] -> 18 Avenue Pierre Mendès France 72100 - Le Mans | H35: https://maps.app.goo.gl/ngVAd1ZcuWEZcS5U8 | I35: Centre Ville | J35: Centre Commercial | K35: / | M35: / | N35: 40 | O35: 62 | P35: / | Q35: / | R35: / | S35: / | T35: =Tableau1[[#This Row],[Loyer €/m²]]*Tableau1[[#This Row],[Surface GLA]] -> 37200 | U35: =IFERROR(Tableau1[[#This Row],[Loyer annuel]]/12,"") -> 3100 | V35: 600 | W35: / | X35: =Tableau1[[#This Row],[Charges €/m²]]*Tableau1[[#This Row],[Surface GLA]] -> 13640 | Y35: =Tableau1[[#This Row],[Charges annuelles]]/12 -> 1136.6667 | Z35: 220 | AA35: =IFERROR(Tableau1[[#This Row],[Taxe foncière €/m²]]*Tableau1[[#This Row],[Surface GLA]],) -> 0 | AB35: / | AC35: =IFERROR(Tableau1[[#This Row],[Marketing €/m²]]*Tableau1[[#This Row],[Surface GLA]],) -> 0 | AD35: / | AE35: =IFERROR(Tableau1[[#This Row],[Loyer annuel]]+Tableau1[[#This Row],[Charges annuelles]]+Tableau1[[#This Row],[Taxe foncière]]+Tableau1[[#This Row],[Marketing]],"") -> 50840 | AF35: / | AG35: / | AH35: / | AI35: En l'état du précédent locataire | AJ35: Non | AK35: Froide | AL35: Fnac, Natures et Découvertes, C&A, Sostrene Grene, Nocibé, Devred, Micormania, Franck Provost, Moa, Adopt | AM35: Local situé au niveau supérieur. Centre commercial en cœur de ville. Toutes charges incluses | AO35: 30% du loyer facial avec un minimum de 15 000 € HT | AP35: 48.006669 | AQ35: 0.199009 | AR35: 7.5 | AS35: https://pub-843c46afc4cb41489909bce00c9b143d.r2.dev/7.1%20-%20Le%20Mans/1.jpg; https://pub-843c46afc4cb41489909bce00c9b143d.r2.dev/7.1%20-%20Le%20Mans/2.jpg; https://pub-843c46afc4cb41489909bce00c9b143d.r2.dev/7.1%20-%20Le%20Mans/3.jpg; https://pub-843c46afc4cb41489909bce00c9b143d.r2.dev/7.1%20-%20Le%20Mans/4.jpg; https://pub-843c46afc4cb41489909bce00c9b143d.r2.dev/7.1%20-%20Le%20Mans/5%20Niveau%20inf%C3%A9rieur.jpg; https://pub-843c46afc4cb41489909bce00c9b143d.r2.dev/7.1%20-%20Le%20Mans/6%20Niveau%20sup%C3%A9rieur.jpg | AT35: Oui | AU35: 500 €/m² | AV35: Othrys
A36: =VLOOKUP(Tableau1[[#This Row],[N° Département]],Feuil1!$C$6:$E$106,3) -> Pays de la Loire | B36: =VLOOKUP(Tableau1[[#This Row],[N° Département]],Feuil1!$C$6:$E$106,2) -> Sarthe | C36: =LEFT(Tableau1[[#This Row],[Code Postal]],2)*1 -> 72 | D36: 18 Avenue Pierre Mendès France | E36: 72100 | F36: Le Mans | G36: =Tableau1[[#This Row],[Rue]]&CHAR(10)&Tableau1[[#This Row],[Code Postal]]&" - "&Tableau1[[#This Row],[Ville]] -> 18 Avenue Pierre Mendès France 72100 - Le Mans | H36: https://maps.app.goo.gl/ngVAd1ZcuWEZcS5U8 | I36: Centre Ville | J36: Centre Commercial | K36: / | M36: / | N36: 50 | O36: 22 | P36: / | Q36: / | R36: / | S36: / | T36: =Tableau1[[#This Row],[Loyer €/m²]]*Tableau1[[#This Row],[Surface GLA]] -> 15400 | U36: =IFERROR(Tableau1[[#This Row],[Loyer annuel]]/12,"") -> 1283.3333 | V36: 700 | W36: / | X36: =Tableau1[[#This Row],[Charges €/m²]]*Tableau1[[#This Row],[Surface GLA]] -> 4840 | Y36: =Tableau1[[#This Row],[Charges annuelles]]/12 -> 403.33333 | Z36: 220 | AA36: =IFERROR(Tableau1[[#This Row],[Taxe foncière €/m²]]*Tableau1[[#This Row],[Surface GLA]],) -> 0 | AB36: / | AC36: =IFERROR(Tableau1[[#This Row],[Marketing €/m²]]*Tableau1[[#This Row],[Surface GLA]],) -> 0 | AD36: / | AE36: =IFERROR(Tableau1[[#This Row],[Loyer annuel]]+Tableau1[[#This Row],[Charges annuelles]]+Tableau1[[#This Row],[Taxe foncière]]+Tableau1[[#This Row],[Marketing]],"") -> 20240 | AF36: / | AG36: / | AH36: / | AI36: En l'état du précédent locataire | AJ36: Non | AK36: Froide | AL36: Fnac, Natures et Découvertes, C&A, Sostrene Grene, Nocibé, Devred, Micormania, Franck Provost, Moa, Adopt | AM36: Local situé au niveau supérieur. Centre commercial en cœur de ville. Toutes charges incluses | AO36: 30% du loyer facial avec un minimum de 15 000 € HT | AP36: 48.006018 | AQ36: 0.199543 | AR36: 7.6 | AS36: https://pub-843c46afc4cb41489909bce00c9b143d.r2.dev/7.1%20-%20Le%20Mans/1.jpg; https://pub-843c46afc4cb41489909bce00c9b143d.r2.dev/7.1%20-%20Le%20Mans/2.jpg; https://pub-843c46afc4cb41489909bce00c9b143d.r2.dev/7.1%20-%20Le%20Mans/3.jpg; https://pub-843c46afc4cb41489909bce00c9b143d.r2.dev/7.1%20-%20Le%20Mans/4.jpg; https://pub-843c46afc4cb41489909bce00c9b143d.r2.dev/7.1%20-%20Le%20Mans/5%20Niveau%20inf%C3%A9rieur.jpg; https://pub-843c46afc4cb41489909bce00c9b143d.r2.dev/7.1%20-%20Le%20Mans/6%20Niveau%20sup%C3%A9rieur.jpg | AT36: Oui | AU36: 500 €/m² | AV36: Othrys
A37: =VLOOKUP(Tableau1[[#This Row],[N° Département]],Feuil1!$C$6:$E$106,3) -> Pays de la Loire | B37: =VLOOKUP(Tableau1[[#This Row],[N° Département]],Feuil1!$C$6:$E$106,2) -> Sarthe | C37: =LEFT(Tableau1[[#This Row],[Code Postal]],2)*1 -> 72 | D37: 18 Avenue Pierre Mendès France | E37: 72100 | F37: Le Mans | G37: =Tableau1[[#This Row],[Rue]]&CHAR(10)&Tableau1[[#This Row],[Code Postal]]&" - "&Tableau1[[#This Row],[Ville]] -> 18 Avenue Pierre Mendès France 72100 - Le Mans | H37: https://maps.app.goo.gl/ngVAd1ZcuWEZcS5U8 | I37: Centre Ville | J37: Centre Commercial | K37: / | M37: / | N37: 53 | O37: 9 | P37: / | Q37: / | R37: / | S37: / | T37: =Tableau1[[#This Row],[Loyer €/m²]]*Tableau1[[#This Row],[Surface GLA]] -> 7200 | U37: =IFERROR(Tableau1[[#This Row],[Loyer annuel]]/12,"") -> 600 | V37: 800 | W37: / | X37: =Tableau1[[#This Row],[Charges €/m²]]*Tableau1[[#This Row],[Surface GLA]] -> 1980 | Y37: =Tableau1[[#This Row],[Charges annuelles]]/12 -> 165 | Z37: 220 | AA37: =IFERROR(Tableau1[[#This Row],[Taxe foncière €/m²]]*Tableau1[[#This Row],[Surface GLA]],) -> 0 | AB37: / | AC37: =IFERROR(Tableau1[[#This Row],[Marketing €/m²]]*Tableau1[[#This Row],[Surface GLA]],) -> 0 | AD37: / | AE37: =IFERROR(Tableau1[[#This Row],[Loyer annuel]]+Tableau1[[#This Row],[Charges annuelles]]+Tableau1[[#This Row],[Taxe foncière]]+Tableau1[[#This Row],[Marketing]],"") -> 9180 | AF37: / | AG37: / | AH37: / | AI37: En l'état du précédent locataire | AJ37: Non | AK37: Froide | AL37: Fnac, Natures et Découvertes, C&A, Sostrene Grene, Nocibé, Devred, Micormania, Franck Provost, Moa, Adopt | AM37: Local situé au niveau supérieur. Centre commercial en cœur de ville. Toutes charges incluses | AO37: 30% du loyer facial avec un minimum de 15 000 € HT | AP37: 48.005872 | AQ37: 0.199548 | AR37: 7.7 | AS37: https://pub-843c46afc4cb41489909bce00c9b143d.r2.dev/7.1%20-%20Le%20Mans/1.jpg; https://pub-843c46afc4cb41489909bce00c9b143d.r2.dev/7.1%20-%20Le%20Mans/2.jpg; https://pub-843c46afc4cb41489909bce00c9b143d.r2.dev/7.1%20-%20Le%20Mans/3.jpg; https://pub-843c46afc4cb41489909bce00c9b143d.r2.dev/7.1%20-%20Le%20Mans/4.jpg; https://pub-843c46afc4cb41489909bce00c9b143d.r2.dev/7.1%20-%20Le%20Mans/5%20Niveau%20inf%C3%A9rieur.jpg; https://pub-843c46afc4cb41489909bce00c9b143d.r2.dev/7.1%20-%20Le%20Mans/6%20Niveau%20sup%C3%A9rieur.jpg | AT37: Oui | AU37: 500 €/m² | AV37: Othrys
A38: =VLOOKUP(Tableau1[[#This Row],[N° Département]],Feuil1!$C$6:$E$106,3) -> Pays de la Loire | B38: =VLOOKUP(Tableau1[[#This Row],[N° Département]],Feuil1!$C$6:$E$106,2) -> Sarthe | C38: =LEFT(Tableau1[[#This Row],[Code Postal]],2)*1 -> 72 | D38: 18 Avenue Pierre Mendès France | E38: 72100 | F38: Le Mans | G38: =Tableau1[[#This Row],[Rue]]&CHAR(10)&Tableau1[[#This Row],[Code Postal]]&" - "&Tableau1[[#This Row],[Ville]] -> 18 Avenue Pierre Mendès France 72100 - Le Mans | H38: https://maps.app.goo.gl/ngVAd1ZcuWEZcS5U8 | I38: Centre Ville | J38: Centre Commercial | K38: / | M38: / | N38: 68A | O38: 71 | P38: / | Q38: / | R38: / | S38: / | T38: =Tableau1[[#This Row],[Loyer €/m²]]*Tableau1[[#This Row],[Surface GLA]] -> 42600 | U38: =IFERROR(Tableau1[[#This Row],[Loyer annuel]]/12,"") -> 3550 | V38: 600 | W38: / | X38: =Tableau1[[#This Row],[Charges €/m²]]*Tableau1[[#This Row],[Surface GLA]] -> 15620 | Y38: =Tableau1[[#This Row],[Charges annuelles]]/12 -> 1301.6667 | Z38: 220 | AA38: =IFERROR(Tableau1[[#This Row],[Taxe foncière €/m²]]*Tableau1[[#This Row],[Surface GLA]],) -> 0 | AB38: / | AC38: =IFERROR(Tableau1[[#This Row],[Marketing €/m²]]*Tableau1[[#This Row],[Surface GLA]],) -> 0 | AD38: / | AE38: =IFERROR(Tableau1[[#This Row],[Loyer annuel]]+Tableau1[[#This Row],[Charges annuelles]]+Tableau1[[#This Row],[Taxe foncière]]+Tableau1[[#This Row],[Marketing]],"") -> 58220 | AF38: / | AG38: / | AH38: / | AI38: En l'état du précédent locataire | AJ38: Non | AK38: Froide | AL38: Fnac, Natures et Découvertes, C&A, Sostrene Grene, Nocibé, Devred, Micormania, Franck Provost, Moa, Adopt | AM38: Local situé au niveau supérieur. Centre commercial en cœur de ville. Toutes charges incluses | AO38: 30% du loyer facial avec un minimum de 15 000 € HT | AP38: 48.006380 | AQ38: 0.199481 | AR38: 7.8 | AS38: https://pub-843c46afc4cb41489909bce00c9b143d.r2.dev/7.1%20-%20Le%20Mans/1.jpg; https://pub-843c46afc4cb41489909bce00c9b143d.r2.dev/7.1%20-%20Le%20Mans/2.jpg; https://pub-843c46afc4cb41489909bce00c9b143d.r2.dev/7.1%20-%20Le%20Mans/3.jpg; https://pub-843c46afc4cb41489909bce00c9b143d.r2.dev/7.1%20-%20Le%20Mans/4.jpg; https://pub-843c46afc4cb41489909bce00c9b143d.r2.dev/7.1%20-%20Le%20Mans/5%20Niveau%20inf%C3%A9rieur.jpg; https://pub-843c46afc4cb41489909bce00c9b143d.r2.dev/7.1%20-%20Le%20Mans/6%20Niveau%20sup%C3%A9rieur.jpg | AT38: Oui | AU38: 500 €/m² | AV38: Othrys
A39: =VLOOKUP(Tableau1[[#This Row],[N° Département]],Feuil1!$C$6:$E$106,3) -> Pays de la Loire | B39: =VLOOKUP(Tableau1[[#This Row],[N° Département]],Feuil1!$C$6:$E$106,2) -> Sarthe | C39: =LEFT(Tableau1[[#This Row],[Code Postal]],2)*1 -> 72 | D39: 18 Avenue Pierre Mendès France | E39: 72100 | F39: Le Mans | G39: =Tableau1[[#This Row],[Rue]]&CHAR(10)&Tableau1[[#This Row],[Code Postal]]&" - "&Tableau1[[#This Row],[Ville]] -> 18 Avenue Pierre Mendès France 72100 - Le Mans | H39: https://maps.app.goo.gl/ngVAd1ZcuWEZcS5U8 | I39: Centre Ville | J39: Centre Commercial | K39: / | M39: / | N39: 78 | O39: 45 | P39: / | Q39: / | R39: / | S39: / | T39: =Tableau1[[#This Row],[Loyer €/m²]]*Tableau1[[#This Row],[Surface GLA]] -> 31500 | U39: =IFERROR(Tableau1[[#This Row],[Loyer annuel]]/12,"") -> 2625 | V39: 700 | W39: / | X39: =Tableau1[[#This Row],[Charges €/m²]]*Tableau1[[#This Row],[Surface GLA]] -> 9900 | Y39: =Tableau1[[#This Row],[Charges annuelles]]/12 -> 825 | Z39: 220 | AA39: =IFERROR(Tableau1[[#This Row],[Taxe foncière €/m²]]*Tableau1[[#This Row],[Surface GLA]],) -> 0 | AB39: / | AC39: =IFERROR(Tableau1[[#This Row],[Marketing €/m²]]*Tableau1[[#This Row],[Surface GLA]],) -> 0 | AD39: / | AE39: =IFERROR(Tableau1[[#This Row],[Loyer annuel]]+Tableau1[[#This Row],[Charges annuelles]]+Tableau1[[#This Row],[Taxe foncière]]+Tableau1[[#This Row],[Marketing]],"") -> 41400 | AF39: / | AG39: / | AH39: / | AI39: En l'état du précédent locataire | AJ39: Non | AK39: Froide | AL39: Fnac, Natures et Découvertes, C&A, Sostrene Grene, Nocibé, Devred, Micormania, Franck Provost, Moa, Adopt | AM39: Local situé au niveau supérieur. Centre commercial en cœur de ville. Toutes charges incluses | AO39: 30% du loyer facial avec un minimum de 15 000 € HT | AP39: 48.006694 | AQ39: 0.199414 | AR39: 7.9 | AS39: https://pub-843c46afc4cb41489909bce00c9b143d.r2.dev/7.1%20-%20Le%20Mans/1.jpg; https://pub-843c46afc4cb41489909bce00c9b143d.r2.dev/7.1%20-%20Le%20Mans/2.jpg; https://pub-843c46afc4cb41489909bce00c9b143d.r2.dev/7.1%20-%20Le%20Mans/3.jpg; https://pub-843c46afc4cb41489909bce00c9b143d.r2.dev/7.1%20-%20Le%20Mans/4.jpg; https://pub-843c46afc4cb41489909bce00c9b143d.r2.dev/7.1%20-%20Le%20Mans/5%20Niveau%20inf%C3%A9rieur.jpg; https://pub-843c46afc4cb41489909bce00c9b143d.r2.dev/7.1%20-%20Le%20Mans/6%20Niveau%20sup%C3%A9rieur.jpg | AT39: Oui | AU39: 500 €/m² | AV39: Othrys
A40: =VLOOKUP(Tableau1[[#This Row],[N° Département]],Feuil1!$C$6:$E$106,3) -> Auvergne-Rhône-Alpes | B40: =VLOOKUP(Tableau1[[#This Row],[N° Département]],Feuil1!$C$6:$E$106,2) -> Rhône | C40: =LEFT(Tableau1[[#This Row],[Code Postal]],2)*1 -> 69 | D40: 18 Rue du Général Mouton-Duvernet | E40: 69003 | F40: Lyon | G40: =Tableau1[[#This Row],[Rue]]&CHAR(10)&Tableau1[[#This Row],[Code Postal]]&" - "&Tableau1[[#This Row],[Ville]] -> 18 Rue du Général Mouton-Duvernet 69003 - Lyon | H40: https://www.google.com/maps/place/18+Rue+du+G%C3%A9n%C3%A9ral+Mouton-Duvernet,+69003+Lyon | I40: Centre Ville | J40: Pied d'immeuble | K40: / | M40: / | N40: / | O40: 274 | P40: / | Q40: / | R40: 200 | S40: / | T40: =Tableau1[[#This Row],[Loyer €/m²]]*Tableau1[[#This Row],[Surface GLA]] -> 49320 | U40: =IFERROR(Tableau1[[#This Row],[Loyer annuel]]/12,"") -> 4110 | V40: 180 | W40: / | X40: =Tableau1[[#This Row],[Charges €/m²]]*Tableau1[[#This Row],[Surface GLA]] -> 10138 | Y40: =IFERROR(Tableau1[[#This Row],[Charges annuelles]]/12,"") -> 844.83333 | Z40: 37 | AA40: =IFERROR(Tableau1[[#This Row],[Taxe foncière €/m²]]*Tableau1[[#This Row],[Surface GLA]],) -> 4110 | AB40: 15 | AC40: =IFERROR(Tableau1[[#This Row],[Marketing €/m²]]*Tableau1[[#This Row],[Surface GLA]],) -> 0 | AD40: / | AE40: =IFERROR(Tableau1[[#This Row],[Loyer annuel]]+Tableau1[[#This Row],[Charges annuelles]]+Tableau1[[#This Row],[Taxe foncière]]+Tableau1[[#This Row],[Marketing]],"") -> 63568 | AF40: / | AG40: / | AH40: / | AI40: Brut de béton | AJ40: Oui | AK40: Chaude et froide | AL40: En plein cœur de Lyon | AM40: 2,4 M de flux par an. Quartier d'affaires de Lyon, à 15 minutes de la gare de Lyon Part-Dieu. 15 m de linéaire. Terrasse sous réserve de validation de la Mairie | AO40: 30% du loyer facial avec un minimum de 15 000 € HT | AP40: 45.753459 | AQ40: 4.861311 | AR40: 8 | AS40: https://pub-843c46afc4cb41489909bce00c9b143d.r2.dev/8%20-%20Lyon/1%20Vue%20d'ensemble.jpg; https://pub-843c46afc4cb41489909bce00c9b143d.r2.dev/8%20-%20Lyon/2.jpg; https://pub-843c46afc4cb41489909bce00c9b143d.r2.dev/8%20-%20Lyon/3.jpg; https://pub-843c46afc4cb41489909bce00c9b143d.r2.dev/8%20-%20Lyon/4%20Plan.jpg | AT40: Oui | AU40: Au BP | AV40: Gecina
A41: =VLOOKUP(Tableau1[[#This Row],[N° Département]],Feuil1!$C$6:$E$106,3) -> Ile-de-France | B41: =VLOOKUP(Tableau1[[#This Row],[N° Département]],Feuil1!$C$6:$E$106,2) -> Yvelines | C41: =LEFT(Tableau1[[#This Row],[Code Postal]],2)*1 -> 78 | D41: 3 Avenue Louis Pasteur | E41: 78310 | F41: Maurepas | G41: =Tableau1[[#This Row],[Rue]]&CHAR(10)&Tableau1[[#This Row],[Code Postal]]&" - "&Tableau1[[#This Row],[Ville]] -> 3 Avenue Louis Pasteur 78310 - Maurepas | H41: https://maps.app.goo.gl/eqCTz2HAdE1NfPPD8 | I41: Périphérie | J41: Retail Park | K41: / | M41: / | N41: 116 | O41: 168 | P41: 141 + 27 | Q41: / | R41: 156 | S41: 131 + 25 | T41: =Tableau1[[#This Row],[Loyer €/m²]]*Tableau1[[#This Row],[Surface GLA]] -> 42000 | U41: =IFERROR(Tableau1[[#This Row],[Loyer annuel]]/12,"") -> 3500 | V41: 250 | W41: / | X41: =Tableau1[[#This Row],[Charges €/m²]]*Tableau1[[#This Row],[Surface GLA]] -> 5880 | Y41: =IFERROR(Tableau1[[#This Row],[Charges annuelles]]/12,"") -> 490 | Z41: 35 | AA41: =IFERROR(Tableau1[[#This Row],[Taxe foncière €/m²]]*Tableau1[[#This Row],[Surface GLA]],) -> 0 | AB41: / | AC41: =IFERROR(Tableau1[[#This Row],[Marketing €/m²]]*Tableau1[[#This Row],[Surface GLA]],) -> 0 | AD41: / | AE41: =IFERROR(Tableau1[[#This Row],[Loyer annuel]]+Tableau1[[#This Row],[Charges annuelles]]+Tableau1[[#This Row],[Taxe foncière]]+Tableau1[[#This Row],[Marketing]],"") -> 47880 | AF41: / | AG41: / | AH41: / | AI41: En l'état du précédent locataire | AJ41: Oui | AK41: Chaude et froide | AL41: Fitness, Esthétique, La Vie Claire, Padel, Bowling, Restaurant, bar | AM41: Retail Park dans une belle zone commerciale : Auchan, Gemo, Burger King, Kiabi, Noz, Intersport, Automobile. Taxes comprises | AO41: 30% du loyer facial avec un minimum de 15 000 € HT | AP41: 48.761808 | AQ41: 1.912911 | AR41: 9.1 | AS41: https://pub-843c46afc4cb41489909bce00c9b143d.r2.dev/9.1%20-%20Maurepas/1%20Vue%20d'ensemble.jpg; https://pub-843c46afc4cb41489909bce00c9b143d.r2.dev/9.1%20-%20Maurepas/2.jpg; https://pub-843c46afc4cb41489909bce00c9b143d.r2.dev/9.1%20-%20Maurepas/3%20Plan.PNG | AT41: Oui | AU41: 150 €/m² | AV41: Praemia
A42: =VLOOKUP(Tableau1[[#This Row],[N° Département]],Feuil1!$C$6:$E$106,3) -> Ile-de-France | B42: =VLOOKUP(Tableau1[[#This Row],[N° Département]],Feuil1!$C$6:$E$106,2) -> Yvelines | C42: =LEFT(Tableau1[[#This Row],[Code Postal]],2)*1 -> 78 | D42: 3 Avenue Louis Pasteur | E42: 78310 | F42: Maurepas | G42: =Tableau1[[#This Row],[Rue]]&CHAR(10)&Tableau1[[#This Row],[Code Postal]]&" - "&Tableau1[[#This Row],[Ville]] -> 3 Avenue Louis Pasteur 78310 - Maurepas | H42: https://maps.app.goo.gl/eqCTz2HAdE1NfPPD8 | I42: Périphérie | J42: Retail Park | K42: / | M42: / | N42: 12 | O42: 87 | Q42: / | R42: 82 | T42: =Tableau1[[#This Row],[Loyer €/m²]]*Tableau1[[#This Row],[Surface GLA]] -> 17400 | U42: =IFERROR(Tableau1[[#This Row],[Loyer annuel]]/12,"") -> 1450 | V42: 200 | W42: / | X42: =Tableau1[[#This Row],[Charges €/m²]]*Tableau1[[#This Row],[Surface GLA]] -> 3045 | Y42: =IFERROR(Tableau1[[#This Row],[Charges annuelles]]/12,"") -> 253.75 | Z42: 35 | AA42: =IFERROR(Tableau1[[#This Row],[Taxe foncière €/m²]]*Tableau1[[#This Row],[Surface GLA]],) -> 0 | AB42: / | AC42: =IFERROR(Tableau1[[#This Row],[Marketing €/m²]]*Tableau1[[#This Row],[Surface GLA]],) -> 0 | AD42: / | AE42: =IFERROR(Tableau1[[#This Row],[Loyer annuel]]+Tableau1[[#This Row],[Charges annuelles]]+Tableau1[[#This Row],[Taxe foncière]]+Tableau1[[#This Row],[Marketing]],"") -> 20445 | AF42: / | AG42: / | AH42: / | AI42: En l'état du précédent locataire | AJ42: A étudier | AK42: Chaude et froide | AL42: Fitness, Esthétique, La Vie Claire, Padel, Bowling, Restaurant, bar | AM42: Retail Park dans une belle zone commerciale : Auchan, Gemo, Burger King, Kiabi, Noz, Intersport, Automobile. Taxes comprises | AO42: 30% du loyer facial avec un minimum de 15 000 € HT | AP42: 48.761497 | AQ42: 1.912919 | AR42: 9.2 | AS42: https://pub-843c46afc4cb41489909bce00c9b143d.r2.dev/9.1%20-%20Maurepas/1%20Vue%20d'ensemble.jpg; https://pub-843c46afc4cb41489909bce00c9b143d.r2.dev/9.2%20-%20Maurepas/2.jpg; https://pub-843c46afc4cb41489909bce00c9b143d.r2.dev/9.2%20-%20Maurepas/3%20Plan.PNG | AT42: Oui | AU42: 150 €/m² | AV42: Praemia
A43: =VLOOKUP(Tableau1[[#This Row],[N° Département]],Feuil1!$C$6:$E$106,3) -> Ile-de-France | B43: =VLOOKUP(Tableau1[[#This Row],[N° Département]],Feuil1!$C$6:$E$106,2) -> Yvelines | C43: =LEFT(Tableau1[[#This Row],[Code Postal]],2)*1 -> 78 | D43: 3 Avenue Louis Pasteur | E43: 78310 | F43: Maurepas | G43: =Tableau1[[#This Row],[Rue]]&CHAR(10)&Tableau1[[#This Row],[Code Postal]]&" - "&Tableau1[[#This Row],[Ville]] -> 3 Avenue Louis Pasteur 78310 - Maurepas | H43: https://maps.app.goo.gl/eqCTz2HAdE1NfPPD8 | I43: Périphérie | J43: Retail Park | K43: / | M43: / | N43: 106 | O43: 197 | Q43: / | R43: 182 | T43: =Tableau1[[#This Row],[Loyer €/m²]]*Tableau1[[#This Row],[Surface GLA]] -> 39400 | U43: =IFERROR(Tableau1[[#This Row],[Loyer annuel]]/12,"") -> 3283.3333 | V43: 200 | W43: / | X43: =Tableau1[[#This Row],[Charges €/m²]]*Tableau1[[#This Row],[Surface GLA]] -> 6895 | Y43: =IFERROR(Tableau1[[#This Row],[Charges annuelles]]/12,"") -> 574.58333 | Z43: 35 | AA43: =IFERROR(Tableau1[[#This Row],[Taxe foncière €/m²]]*Tableau1[[#This Row],[Surface GLA]],) -> 0 | AB43: / | AC43: =IFERROR(Tableau1[[#This Row],[Marketing €/m²]]*Tableau1[[#This Row],[Surface GLA]],) -> 0 | AD43: / | AE43: =IFERROR(Tableau1[[#This Row],[Loyer annuel]]+Tableau1[[#This Row],[Charges annuelles]]+Tableau1[[#This Row],[Taxe foncière]]+Tableau1[[#This Row],[Marketing]],"") -> 46295 | AF43: / | AG43: / | AH43: / | AI43: En l'état du précédent locataire | AJ43: A étudier | AK43: Chaude et froide | AL43: Fitness, Esthétique, La Vie Claire, Padel, Bowling, Restaurant, bar | AM43: Retail Park dans une belle zone commerciale : Auchan, Gemo, Burger King, Kiabi, Noz, Intersport, Automobile. Taxes comprises | AO43: 30% du loyer facial avec un minimum de 15 000 € HT | AP43: 48.761274 | AQ43: 1.913268 | AR43: 9.3 | AS43: https://pub-843c46afc4cb41489909bce00c9b143d.r2.dev/9.1%20-%20Maurepas/1%20Vue%20d'ensemble.jpg; https://pub-843c46afc4cb41489909bce00c9b143d.r2.dev/9.3%20-%20Maurepas/2.jpg; https://pub-843c46afc4cb41489909bce00c9b143d.r2.dev/9.3%20-%20Maurepas/3%20Plan.PNG | AT43: Oui | AU43: 150 €/m² | AV43: Praemia
A44: =VLOOKUP(Tableau1[[#This Row],[N° Département]],Feuil1!$C$6:$E$106,3) -> Ile-de-France | B44: =VLOOKUP(Tableau1[[#This Row],[N° Département]],Feuil1!$C$6:$E$106,2) -> Yvelines | C44: =LEFT(Tableau1[[#This Row],[Code Postal]],2)*1 -> 78 | D44: 3 Avenue Louis Pasteur | E44: 78310 | F44: Maurepas | G44: =Tableau1[[#This Row],[Rue]]&CHAR(10)&Tableau1[[#This Row],[Code Postal]]&" - "&Tableau1[[#This Row],[Ville]] -> 3 Avenue Louis Pasteur 78310 - Maurepas | H44: https://maps.app.goo.gl/eqCTz2HAdE1NfPPD8 | I44: Périphérie | J44: Retail Park | K44: / | M44: / | N44: 105 | O44: 576 | P44: 1257 | Q44: / | R44: 543 | T44: =Tableau1[[#This Row],[Loyer €/m²]]*Tableau1[[#This Row],[Surface GLA]] -> 100800 | U44: =IFERROR(Tableau1[[#This Row],[Loyer annuel]]/12,"") -> 8400 | V44: 175 | W44: / | X44: =Tableau1[[#This Row],[Charges €/m²]]*Tableau1[[#This Row],[Surface GLA]] -> 20160 | Y44: =IFERROR(Tableau1[[#This Row],[Charges annuelles]]/12,"") -> 1680 | Z44: 35 | AA44: =IFERROR(Tableau1[[#This Row],[Taxe foncière €/m²]]*Tableau1[[#This Row],[Surface GLA]],) -> 0 | AB44: / | AC44: =IFERROR(Tableau1[[#This Row],[Marketing €/m²]]*Tableau1[[#This Row],[Surface GLA]],) -> 0 | AD44: / | AE44: =IFERROR(Tableau1[[#This Row],[Loyer annuel]]+Tableau1[[#This Row],[Charges annuelles]]+Tableau1[[#This Row],[Taxe foncière]]+Tableau1[[#This Row],[Marketing]],"") -> 120960 | AF44: / | AG44: / | AH44: / | AI44: En l'état du précédent locataire | AJ44: Oui | AK44: Chaude et froide | AL44: Fitness, Esthétique, La Vie Claire, Padel, Bowling, Restaurant, bar | AM44: Retail Park dans une belle zone commerciale : Auchan, Gemo, Burger King, Kiabi, Noz, Intersport, Automobile. Taxes comprises | AO44: 30% du loyer facial avec un minimum de 15 000 € HT | AP44: 48.761218 | AQ44: 1.913512 | AR44: 9.4 | AS44: https://pub-843c46afc4cb41489909bce00c9b143d.r2.dev/9.1%20-%20Maurepas/1%20Vue%20d'ensemble.jpg; https://pub-843c46afc4cb41489909bce00c9b143d.r2.dev/9.4%20-%20Maurepas/2.jpg; https://pub-843c46afc4cb41489909bce00c9b143d.r2.dev/9.4%20-%20Maurepas/3%20Plan.PNG | AT44: Oui | AU44: 150 €/m² | AV44: Praemia
A45: =VLOOKUP(Tableau1[[#This Row],[N° Département]],Feuil1!$C$6:$E$106,3) -> Ile-de-France | B45: =VLOOKUP(Tableau1[[#This Row],[N° Département]],Feuil1!$C$6:$E$106,2) -> Yvelines | C45: =LEFT(Tableau1[[#This Row],[Code Postal]],2)*1 -> 78 | D45: 3 Avenue Louis Pasteur | E45: 78310 | F45: Maurepas | G45: =Tableau1[[#This Row],[Rue]]&CHAR(10)&Tableau1[[#This Row],[Code Postal]]&" - "&Tableau1[[#This Row],[Ville]] -> 3 Avenue Louis Pasteur 78310 - Maurepas | H45: https://maps.app.goo.gl/eqCTz2HAdE1NfPPD8 | I45: Périphérie | J45: Retail Park | K45: / | M45: / | N45: 123 | O45: 237 | P45: 210 + 26 | Q45: / | R45: 221 | S45: 195 + 26 | T45: =Tableau1[[#This Row],[Loyer €/m²]]*Tableau1[[#This Row],[Surface GLA]] -> 47400 | U45: =IFERROR(Tableau1[[#This Row],[Loyer annuel]]/12,"") -> 3950 | V45: 200 | W45: / | X45: =Tableau1[[#This Row],[Charges €/m²]]*Tableau1[[#This Row],[Surface GLA]] -> 8295 | Y45: =IFERROR(Tableau1[[#This Row],[Charges annuelles]]/12,"") -> 691.25 | Z45: 35 | AA45: =IFERROR(Tableau1[[#This Row],[Taxe foncière €/m²]]*Tableau1[[#This Row],[Surface GLA]],) -> 0 | AB45: / | AC45: =IFERROR(Tableau1[[#This Row],[Marketing €/m²]]*Tableau1[[#This Row],[Surface GLA]],) -> 0 | AD45: / | AE45: =IFERROR(Tableau1[[#This Row],[Loyer annuel]]+Tableau1[[#This Row],[Charges annuelles]]+Tableau1[[#This Row],[Taxe foncière]]+Tableau1[[#This Row],[Marketing]],"") -> 55695 | AF45: / | AG45: / | AH45: / | AI45: En l'état du précédent locataire | AJ45: Oui | AK45: Chaude et froide | AL45: Fitness, Esthétique, La Vie Claire, Padel, Bowling, Restaurant, bar | AM45: Retail Park dans une belle zone commerciale : Auchan, Gemo, Burger King, Kiabi, Noz, Intersport, Automobile. Taxes comprises | AO45: 30% du loyer facial avec un minimum de 15 000 € HT | AP45: 48.761691 | AQ45: 1.913319 | AR45: 9.5 | AS45: https://pub-843c46afc4cb41489909bce00c9b143d.r2.dev/9.1%20-%20Maurepas/1%20Vue%20d'ensemble.jpg; https://pub-843c46afc4cb41489909bce00c9b143d.r2.dev/9.5%20-%20Maurepas/2.jpg; https://pub-843c46afc4cb41489909bce00c9b143d.r2.dev/9.5%20-%20Maurepas/3%20Plan.PNG | AT45: Oui | AU45: 150 €/m² | AV45: Praemia
A46: =VLOOKUP(Tableau1[[#This Row],[N° Département]],Feuil1!$C$6:$E$106,3) -> Ile-de-France | B46: =VLOOKUP(Tableau1[[#This Row],[N° Département]],Feuil1!$C$6:$E$106,2) -> Yvelines | C46: =LEFT(Tableau1[[#This Row],[Code Postal]],2)*1 -> 78 | D46: 3 Avenue Louis Pasteur | E46: 78310 | F46: Maurepas | G46: =Tableau1[[#This Row],[Rue]]&CHAR(10)&Tableau1[[#This Row],[Code Postal]]&" - "&Tableau1[[#This Row],[Ville]] -> 3 Avenue Louis Pasteur 78310 - Maurepas | H46: https://maps.app.goo.gl/eqCTz2HAdE1NfPPD8 | I46: Périphérie | J46: Retail Park | K46: / | M46: / | N46: 121 | O46: 236 | P46: 219 + 16 | Q46: / | R46: 218 | S46: 204 + 14 | T46: =Tableau1[[#This Row],[Loyer €/m²]]*Tableau1[[#This Row],[Surface GLA]] -> 47200 | U46: =IFERROR(Tableau1[[#This Row],[Loyer annuel]]/12,"") -> 3933.3333 | V46: 200 | W46: / | X46: =Tableau1[[#This Row],[Charges €/m²]]*Tableau1[[#This Row],[Surface GLA]] -> 8260 | Y46: =IFERROR(Tableau1[[#This Row],[Charges annuelles]]/12,"") -> 688.33333 | Z46: 35 | AA46: =IFERROR(Tableau1[[#This Row],[Taxe foncière €/m²]]*Tableau1[[#This Row],[Surface GLA]],) -> 0 | AB46: / | AC46: =IFERROR(Tableau1[[#This Row],[Marketing €/m²]]*Tableau1[[#This Row],[Surface GLA]],) -> 0 | AD46: / | AE46: =IFERROR(Tableau1[[#This Row],[Loyer annuel]]+Tableau1[[#This Row],[Charges annuelles]]+Tableau1[[#This Row],[Taxe foncière]]+Tableau1[[#This Row],[Marketing]],"") -> 55460 | AF46: / | AG46: / | AH46: / | AI46: En l'état du précédent locataire | AJ46: Oui | AK46: Chaude et froide | AL46: Fitness, Esthétique, La Vie Claire, Padel, Bowling, Restaurant, bar | AM46: Retail Park dans une belle zone commerciale : Auchan, Gemo, Burger King, Kiabi, Noz, Intersport, Automobile. Taxes comprises | AO46: 30% du loyer facial avec un minimum de 15 000 € HT | AP46: 48.761626 | AQ46: 1.913576 | AR46: 9.6 | AS46: https://pub-843c46afc4cb41489909bce00c9b143d.r2.dev/9.1%20-%20Maurepas/1%20Vue%20d'ensemble.jpg; https://pub-843c46afc4cb41489909bce00c9b143d.r2.dev/9.6%20-%20Maurepas/2.jpg; https://pub-843c46afc4cb41489909bce00c9b143d.r2.dev/9.6%20-%20Maurepas/3%20Plan.PNG | AT46: Non | AU46: 150 €/m² | AV46: Praemia
A47: =VLOOKUP(Tableau1[[#This Row],[N° Département]],Feuil1!$C$6:$E$106,3) -> Grand Est | B47: =VLOOKUP(Tableau1[[#This Row],[N° Département]],Feuil1!$C$6:$E$106,2) -> Moselle | C47: =LEFT(Tableau1[[#This Row],[Code Postal]],2)*1 -> 57 | D47: 60 Rue Serpenoise | E47: 57000 | F47: Metz | G47: =Tableau1[[#This Row],[Rue]]&CHAR(10)&Tableau1[[#This Row],[Code Postal]]&" - "&Tableau1[[#This Row],[Ville]] -> 60 Rue Serpenoise 57000 - Metz | H47: https://www.google.com/maps/place/60+Rue+Serpenoise,+57000+Metz | I47: Centre Ville | J47: Pied d'immeuble | K47: / | M47: / | N47: / | O47: 370 | P47: 127 (SS) + 242 | Q47: / | R47: / | S47: / | T47: =Tableau1[[#This Row],[Loyer €/m²]]*Tableau1[[#This Row],[Surface GLA]] -> 55500 | U47: =IFERROR(Tableau1[[#This Row],[Loyer annuel]]/12,"") -> 4625 | V47: 150 | W47: / | X47: =Tableau1[[#This Row],[Charges €/m²]]*Tableau1[[#This Row],[Surface GLA]] -> 22200 | Y47: =IFERROR(Tableau1[[#This Row],[Charges annuelles]]/12,"") -> 1850 | Z47: 60 | AA47: =IFERROR(Tableau1[[#This Row],[Taxe foncière €/m²]]*Tableau1[[#This Row],[Surface GLA]],) -> 0 | AB47: / | AC47: =IFERROR(Tableau1[[#This Row],[Marketing €/m²]]*Tableau1[[#This Row],[Surface GLA]],) -> 0 | AD47: / | AE47: =IFERROR(Tableau1[[#This Row],[Loyer annuel]]+Tableau1[[#This Row],[Charges annuelles]]+Tableau1[[#This Row],[Taxe foncière]]+Tableau1[[#This Row],[Marketing]],"") -> 77700 | AF47: / | AG47: / | AH47: / | AI47: En l'état du précédent locataire | AJ47: Non | AK47: Froide | AL47: Devred, Burger King, Peggy Sage, Alain Afflelou, Promod, Eram, Madura, Maison 123 | AM47: Ancien Kim K. Taxes comprises | AO47: 30% du loyer facial avec un minimum de 15 000 € HT | AP47: 49.115823 | AQ47: 6.174367 | AR47: 10.1 | AS47: https://pub-843c46afc4cb41489909bce00c9b143d.r2.dev/10.1%20-%20Metz/1.jpg; https://pub-843c46afc4cb41489909bce00c9b143d.r2.dev/10.1%20-%20Metz/2%20Plan%20R-1.jpg; https://pub-843c46afc4cb41489909bce00c9b143d.r2.dev/10.1%20-%20Metz/3%20Plan%20RDC.jpg | AT47: Oui | AU47: 100 €/m² = 37 000 € | AV47: Praemia
A48: =VLOOKUP(Tableau1[[#This Row],[N° Département]],Feuil1!$C$6:$E$106,3) -> Grand Est | B48: =VLOOKUP(Tableau1[[#This Row],[N° Département]],Feuil1!$C$6:$E$106,2) -> Moselle | C48: =LEFT(Tableau1[[#This Row],[Code Postal]],2)*1 -> 57 | D48: 60 Rue Serpenoise | E48: 57000 | F48: Metz | G48: =Tableau1[[#This Row],[Rue]]&CHAR(10)&Tableau1[[#This Row],[Code Postal]]&" - "&Tableau1[[#This Row],[Ville]] -> 60 Rue Serpenoise 57000 - Metz | H48: https://www.google.com/maps/place/60+Rue+Serpenoise,+57000+Metz | I48: Centre Ville | J48: Pied d'immeuble | K48: / | M48: / | N48: / | O48: 486 | P48: 255 (SS) + 231 | Q48: / | R48: / | S48: / | T48: =Tableau1[[#This Row],[Loyer €/m²]]*Tableau1[[#This Row],[Surface GLA]] -> 63180 | U48: =IFERROR(Tableau1[[#This Row],[Loyer annuel]]/12,"") -> 5265 | V48: 130 | W48: / | X48: =Tableau1[[#This Row],[Charges €/m²]]*Tableau1[[#This Row],[Surface GLA]] -> 29646 | Y48: =IFERROR(Tableau1[[#This Row],[Charges annuelles]]/12,"") -> 2470.5 | Z48: 61 | AA48: =IFERROR(Tableau1[[#This Row],[Taxe foncière €/m²]]*Tableau1[[#This Row],[Surface GLA]],) -> 0 | AB48: / | AC48: =IFERROR(Tableau1[[#This Row],[Marketing €/m²]]*Tableau1[[#This Row],[Surface GLA]],) -> 0 | AD48: / | AE48: =IFERROR(Tableau1[[#This Row],[Loyer annuel]]+Tableau1[[#This Row],[Charges annuelles]]+Tableau1[[#This Row],[Taxe foncière]]+Tableau1[[#This Row],[Marketing]],"") -> 92826 | AF48: / | AG48: / | AH48: / | AI48: En l'état du précédent locataire | AJ48: Non | AK48: Froide | AL48: Devred, Burger King, Peggy Sage, Alain Afflelou, Promod, Eram, Madura, Maison 123 | AM48: Ancien Sacha. Taxes comprises | AO48: 30% du loyer facial avec un minimum de 15 000 € HT | AP48: 49.115904 | AQ48: 6.174453 | AR48: 10.2 | AS48: https://pub-843c46afc4cb41489909bce00c9b143d.r2.dev/10.2%20-%20Metz/1.jpg; https://pub-843c46afc4cb41489909bce00c9b143d.r2.dev/10.2%20-%20Metz/2.jpg; https://pub-843c46afc4cb41489909bce00c9b143d.r2.dev/10.2%20-%20Metz/3%20Plan%20R-1.jpg; https://pub-843c46afc4cb41489909bce00c9b143d.r2.dev/10.2%20-%20Metz/4%20Plan%20RDC.jpg | AT48: Oui | AU48: 100 €/m² = 48 600 € | AV48: Praemia
A49: =VLOOKUP(Tableau1[[#This Row],[N° Département]],Feuil1!$C$6:$E$106,3) -> Ile-de-France | B49: =VLOOKUP(Tableau1[[#This Row],[N° Département]],Feuil1!$C$6:$E$106,2) -> Paris | C49: =LEFT(Tableau1[[#This Row],[Code Postal]],2)*1 -> 75 | D49: 32 Rue Marbeuf | E49: 75008 | F49: Paris | G49: =Tableau1[[#This Row],[Rue]]&CHAR(10)&Tableau1[[#This Row],[Code Postal]]&" - "&Tableau1[[#This Row],[Ville]] -> 32 Rue Marbeuf 75008 - Paris | H49: https://www.google.com/maps/place/32+Rue+Marbeuf,+75008+Paris | I49: Centre Ville | J49: Pied d'immeuble | K49: / | M49: / | N49: / | O49: 681 | P49: 436 m² + 245 réserve déportée | Q49: / | R49: / | S49: / | T49: =Tableau1[[#This Row],[Loyer €/m²]]*Tableau1[[#This Row],[Surface GLA]] -> 630606 | U49: =IFERROR(Tableau1[[#This Row],[Loyer annuel]]/12,"") -> 52550.5 | V49: 926 | W49: / | X49: =Tableau1[[#This Row],[Charges €/m²]]*Tableau1[[#This Row],[Surface GLA]] -> 64695 | Y49: =Tableau1[[#This Row],[Charges annuelles]]/12 -> 5391.25 | Z49: 95 | AA49: =IFERROR(Tableau1[[#This Row],[Taxe foncière €/m²]]*Tableau1[[#This Row],[Surface GLA]],) -> 26559 | AB49: 39 | AC49: =IFERROR(Tableau1[[#This Row],[Marketing €/m²]]*Tableau1[[#This Row],[Surface GLA]],) -> 0 | AD49: / | AE49: =IFERROR(Tableau1[[#This Row],[Loyer annuel]]+Tableau1[[#This Row],[Charges annuelles]]+Tableau1[[#This Row],[Taxe foncière]]+Tableau1[[#This Row],[Marketing]],"") -> 721860 | AF49: / | AG49: / | AH49: / | AI49: Brut de béton | AJ49: Non | AK49: / | AL49: Vilebrequin, Kiton, Marbeuf Optique, Franprix, Berluti, Façonnable, Samlto, Restaurant | AM49: Proximité Champs-Elysées. 8M de flux devant avec 11m de linéaire et 3 de hauteur sous plafond | AO49: 30% du loyer facial avec un minimum de 15 000 € HT | AP49: 48.869316 | AQ49: 2.305064 | AR49: 11 | AS49: https://pub-843c46afc4cb41489909bce00c9b143d.r2.dev/11%20-%20Paris/1.jpg; https://pub-843c46afc4cb41489909bce00c9b143d.r2.dev/11%20-%20Paris/2.jpg; https://pub-843c46afc4cb41489909bce00c9b143d.r2.dev/11%20-%20Paris/3%20Plan%20RDC.jpg; https://pub-843c46afc4cb41489909bce00c9b143d.r2.dev/11%20-%20Paris/4%20Plan%20R%C3%A9serves%20d%C3%A9port%C3%A9es%20R%20-2.jpg | AT49: Oui | AU49: Au BP | AV49: Gecina
A50: =VLOOKUP(Tableau1[[#This Row],[N° Département]],Feuil1!$C$6:$E$106,3) -> Ile-de-France | B50: =VLOOKUP(Tableau1[[#This Row],[N° Département]],Feuil1!$C$6:$E$106,2) -> Paris | C50: =LEFT(Tableau1[[#This Row],[Code Postal]],2)*1 -> 75 | D50: 18 - 20 Rue Treilhard | E50: 75008 | F50: Paris | G50: =Tableau1[[#This Row],[Rue]]&CHAR(10)&Tableau1[[#This Row],[Code Postal]]&" - "&Tableau1[[#This Row],[Ville]] -> 18 - 20 Rue Treilhard 75008 - Paris | H50: https://www.google.com/maps/place/18+Rue+Treilhard,+75008+Paris | I50: Centre Ville | J50: Pied d'immeuble | K50: / | M50: / | N50: / | O50: 672 | P50: 672 m² au R-2 | Q50: / | R50: / | S50: / | T50: =Tableau1[[#This Row],[Loyer €/m²]]*Tableau1[[#This Row],[Surface GLA]] -> 140448 | U50: =IFERROR(Tableau1[[#This Row],[Loyer annuel]]/12,"") -> 11704 | V50: 209 | W50: / | X50: =Tableau1[[#This Row],[Charges €/m²]]*Tableau1[[#This Row],[Surface GLA]] -> 51744 | Y50: =Tableau1[[#This Row],[Charges annuelles]]/12 -> 4312 | Z50: 77 | AA50: =IFERROR(Tableau1[[#This Row],[Taxe foncière €/m²]]*Tableau1[[#This Row],[Surface GLA]],) -> 15456 | AB50: 23 | AC50: =IFERROR(Tableau1[[#This Row],[Marketing €/m²]]*Tableau1[[#This Row],[Surface GLA]],) -> 0 | AD50: / | AE50: =IFERROR(Tableau1[[#This Row],[Loyer annuel]]+Tableau1[[#This Row],[Charges annuelles]]+Tableau1[[#This Row],[Taxe foncière]]+Tableau1[[#This Row],[Marketing]],"") -> 207648 | AF50: / | AG50: / | AH50: / | AI50: Brut de béton | AJ50: Oui | AK50: Chaude et froide | AL50: Restaurant, bureaux, Keepcool, Supermarché | AM50: 1M de flux par an. Ancien restaurant d'entreprise dans un immeuble de bureaux avec accès indépendant par escalier et ascenseur. Charges en cours. | AO50: 30% du loyer facial avec un minimum de 15 000 € HT | AP50: 48.877116 | AQ50: 2.313703 | AR50: 12 | AS50: https://pub-843c46afc4cb41489909bce00c9b143d.r2.dev/12%20-%20Paris/1%20Vue%20d'ensemble.jpg; https://pub-843c46afc4cb41489909bce00c9b143d.r2.dev/12%20-%20Paris/2.jpg; https://pub-843c46afc4cb41489909bce00c9b143d.r2.dev/12%20-%20Paris/3.jpg; https://pub-843c46afc4cb41489909bce00c9b143d.r2.dev/12%20-%20Paris/4.jpg; https://pub-843c46afc4cb41489909bce00c9b143d.r2.dev/12%20-%20Paris/5%20Plan.jpg | AT50: Oui | AU50: Au BP | AV50: Gecina
A51: =VLOOKUP(Tableau1[[#This Row],[N° Département]],Feuil1!$C$6:$E$106,3) -> Ile-de-France | B51: =VLOOKUP(Tableau1[[#This Row],[N° Département]],Feuil1!$C$6:$E$106,2) -> Paris | C51: =LEFT(Tableau1[[#This Row],[Code Postal]],2)*1 -> 75 | D51: 1 Rue de Caumartin | E51: 75009 | F51: Paris | G51: =Tableau1[[#This Row],[Rue]]&CHAR(10)&Tableau1[[#This Row],[Code Postal]]&" - "&Tableau1[[#This Row],[Ville]] -> 1 Rue de Caumartin 75009 - Paris | H51: https://maps.app.goo.gl/wJkBLPh5R3fTCHhg8 | I51: Centre Ville | J51: Pied d'immeuble | K51: / | M51: / | N51: / | O51: 115 | P51: 30 (SS) + 85 | Q51: / | R51: / | S51: / | T51: =Tableau1[[#This Row],[Loyer €/m²]]*Tableau1[[#This Row],[Surface GLA]] -> 115000 | U51: =IFERROR(Tableau1[[#This Row],[Loyer annuel]]/12,"") -> 9583.3333 | V51: 1000 | W51: / | X51: =Tableau1[[#This Row],[Charges €/m²]]*Tableau1[[#This Row],[Surface GLA]] -> 11615 | Y51: =Tableau1[[#This Row],[Charges annuelles]]/12 -> 967.91667 | Z51: 101 | AA51: =IFERROR(Tableau1[[#This Row],[Taxe foncière €/m²]]*Tableau1[[#This Row],[Surface GLA]],) -> 3910 | AB51: 34 | AC51: =IFERROR(Tableau1[[#This Row],[Marketing €/m²]]*Tableau1[[#This Row],[Surface GLA]],) -> 0 | AD51: / | AE51: =IFERROR(Tableau1[[#This Row],[Loyer annuel]]+Tableau1[[#This Row],[Charges annuelles]]+Tableau1[[#This Row],[Taxe foncière]]+Tableau1[[#This Row],[Marketing]],"") -> 130525 | AF51: / | AG51: / | AH51: / | AI51: En l'état du précédent locataire | AJ51: Non | AK51: / | AL51: / | AM51: Ancien Upper Shoes. 5m de linéaire | AO51: 30% du loyer facial avec un minimum de 15 000 € HT | AP51: 48.870287 | AQ51: 2.327921 | AR51: 13 | AT51: Non | AU51: 783 €/m² = 90 000 € | AV51: Gecina
A52: =VLOOKUP(Tableau1[[#This Row],[N° Département]],Feuil1!$C$6:$E$106,3) -> Ile-de-France | B52: =VLOOKUP(Tableau1[[#This Row],[N° Département]],Feuil1!$C$6:$E$106,2) -> Paris | C52: =LEFT(Tableau1[[#This Row],[Code Postal]],2)*1 -> 75 | D52: 204 Quai de Jemmapes | E52: 75010 | F52: Paris | G52: =Tableau1[[#This Row],[Rue]]&CHAR(10)&Tableau1[[#This Row],[Code Postal]]&" - "&Tableau1[[#This Row],[Ville]] -> 204 Quai de Jemmapes 75010 - Paris | H52: https://www.google.com/maps/place/204+Quai+de+Jemmapes,+75010+Paris | I52: Centre Ville | J52: Pied d'immeuble | K52: / | M52: / | N52: / | O52: 189 | P52: 72 (SS) + 117 | Q52: / | R52: / | S52: / | T52: =Tableau1[[#This Row],[Loyer €/m²]]*Tableau1[[#This Row],[Surface GLA]] -> 54999 | U52: =IFERROR(Tableau1[[#This Row],[Loyer annuel]]/12,"") -> 4583.25 | V52: 291 | W52: / | X52: =Tableau1[[#This Row],[Charges €/m²]]*Tableau1[[#This Row],[Surface GLA]] -> 11718 | Y52: =Tableau1[[#This Row],[Charges annuelles]]/12 -> 976.5 | Z52: 62 | AA52: =IFERROR(Tableau1[[#This Row],[Taxe foncière €/m²]]*Tableau1[[#This Row],[Surface GLA]],) -> 1890 | AB52: 10 | AC52: =IFERROR(Tableau1[[#This Row],[Marketing €/m²]]*Tableau1[[#This Row],[Surface GLA]],) -> 0 | AD52: / | AE52: =IFERROR(Tableau1[[#This Row],[Loyer annuel]]+Tableau1[[#This Row],[Charges annuelles]]+Tableau1[[#This Row],[Taxe foncière]]+Tableau1[[#This Row],[Marketing]],"") -> 68607 | AF52: / | AG52: / | AH52: / | AI52: En l'état du précédent locataire | AJ52: Non | AK52: Froide | AL52: Canal Saint-Martin, Restaurant | AM52: 1,55M de flux par an. 9m de linéaire au pied d'un immeuble de bureaux | AO52: 30% du loyer facial avec un minimum de 15 000 € HT | AP52: 48.880875 | AQ52: 2.369469 | AR52: 14 | AS52: https://pub-843c46afc4cb41489909bce00c9b143d.r2.dev/14%20-%20Paris/1.jpg; https://pub-843c46afc4cb41489909bce00c9b143d.r2.dev/14%20-%20Paris/2.jpg; https://pub-843c46afc4cb41489909bce00c9b143d.r2.dev/14%20-%20Paris/3.jpg; https://pub-843c46afc4cb41489909bce00c9b143d.r2.dev/14%20-%20Paris/4%20Plan%20R%20-1.jpg; https://pub-843c46afc4cb41489909bce00c9b143d.r2.dev/14%20-%20Paris/5%20Plan%20RDC.jpg | AT52: Oui | AU52: Au BP | AV52: Gecina
A53: =VLOOKUP(Tableau1[[#This Row],[N° Département]],Feuil1!$C$6:$E$106,3) -> Ile-de-France | B53: =VLOOKUP(Tableau1[[#This Row],[N° Département]],Feuil1!$C$6:$E$106,2) -> Paris | C53: =LEFT(Tableau1[[#This Row],[Code Postal]],2)*1 -> 75 | D53: 9 Avenue Ledru Rollin | E53: 75012 | F53: Paris | G53: =Tableau1[[#This Row],[Rue]]&CHAR(10)&Tableau1[[#This Row],[Code Postal]]&" - "&Tableau1[[#This Row],[Ville]] -> 9 Avenue Ledru Rollin 75012 - Paris | H53: https://www.google.com/maps/place/9+Av.+Ledru+Rollin,+75012+Paris | I53: Centre Ville | J53: Pied d'immeuble | K53: / | M53: / | N53: / | O53: 177 | P53: 10 + 24m² < 1m80 (SS) + 165 | Q53: / | R53: / | S53: / | T53: =Tableau1[[#This Row],[Loyer €/m²]]*Tableau1[[#This Row],[Surface GLA]] -> 75048 | U53: =IFERROR(Tableau1[[#This Row],[Loyer annuel]]/12,"") -> 6254 | V53: 424 | W53: / | X53: =Tableau1[[#This Row],[Charges €/m²]]*Tableau1[[#This Row],[Surface GLA]] -> 7257 | Y53: =Tableau1[[#This Row],[Charges annuelles]]/12 -> 604.75 | Z53: 41 | AA53: =IFERROR(Tableau1[[#This Row],[Taxe foncière €/m²]]*Tableau1[[#This Row],[Surface GLA]],) -> 4248 | AB53: 24 | AC53: =IFERROR(Tableau1[[#This Row],[Marketing €/m²]]*Tableau1[[#This Row],[Surface GLA]],) -> 0 | AD53: / | AE53: =IFERROR(Tableau1[[#This Row],[Loyer annuel]]+Tableau1[[#This Row],[Charges annuelles]]+Tableau1[[#This Row],[Taxe foncière]]+Tableau1[[#This Row],[Marketing]],"") -> 86553 | AF53: / | AG53: / | AH53: / | AI53: En l'état du précédent locataire | AJ53: Non | AK53: Froide | AL53: Action, bureaux, chaussures, Atelier Doma, boulangerie | AM53: 9M de flux par an. Résidence, bureau, étudiant, proximité gare de Lyon | AO53: 30% du loyer facial avec un minimum de 15 000 € HT | AP53: 48.846523 | AQ53: 2.368460 | AR53: 15 | AS53: https://pub-843c46afc4cb41489909bce00c9b143d.r2.dev/15%20-%20Paris/1%20Vue%20d'ensemble.jpg; https://pub-843c46afc4cb41489909bce00c9b143d.r2.dev/15%20-%20Paris/2.jpg; https://pub-843c46afc4cb41489909bce00c9b143d.r2.dev/15%20-%20Paris/3%20Plan%20R-1.jpg; https://pub-843c46afc4cb41489909bce00c9b143d.r2.dev/15%20-%20Paris/4%20Plan%20RDC.jpg | AT53: Oui | AU53: Au BP | AV53: Gecina
A54: =VLOOKUP(Tableau1[[#This Row],[N° Département]],Feuil1!$C$6:$E$106,3) -> Ile-de-France | B54: =VLOOKUP(Tableau1[[#This Row],[N° Département]],Feuil1!$C$6:$E$106,2) -> Paris | C54: =LEFT(Tableau1[[#This Row],[Code Postal]],2)*1 -> 75 | D54: 25 Avenue de Saint-Mandé | E54: 75012 | F54: Paris | G54: =Tableau1[[#This Row],[Rue]]&CHAR(10)&Tableau1[[#This Row],[Code Postal]]&" - "&Tableau1[[#This Row],[Ville]] -> 25 Avenue de Saint-Mandé 75012 - Paris | H54: https://www.google.com/maps/place/25+Av.+de+Saint-Mand%C3%A9,+75012+Paris | I54: Centre Ville | J54: Pied d'immeuble | K54: / | M54: / | N54: / | O54: 85 | P54: / | Q54: / | R54: / | S54: / | T54: =Tableau1[[#This Row],[Loyer €/m²]]*Tableau1[[#This Row],[Surface GLA]] -> 55250 | U54: =IFERROR(Tableau1[[#This Row],[Loyer annuel]]/12,"") -> 4604.1667 | V54: 650 | W54: / | X54: =Tableau1[[#This Row],[Charges €/m²]]*Tableau1[[#This Row],[Surface GLA]] -> 6205 | Y54: =IFERROR(Tableau1[[#This Row],[Charges annuelles]]/12,"") -> 517.08333 | Z54: 73 | AA54: =IFERROR(Tableau1[[#This Row],[Taxe foncière €/m²]]*Tableau1[[#This Row],[Surface GLA]],) -> 1785 | AB54: 21 | AC54: =IFERROR(Tableau1[[#This Row],[Marketing €/m²]]*Tableau1[[#This Row],[Surface GLA]],) -> 0 | AD54: / | AE54: =IFERROR(Tableau1[[#This Row],[Loyer annuel]]+Tableau1[[#This Row],[Charges annuelles]]+Tableau1[[#This Row],[Taxe foncière]]+Tableau1[[#This Row],[Marketing]],"") -> 63240 | AF54: / | AG54: / | AH54: / | AI54: En l'état du précédent locataire | AJ54: A étudier | AK54: Chaude et froide | AL54: Restaurant, supermaché | AM54: Quartier résidentiel, bureau et universitaire | AO54: 30% du loyer facial avec un minimum de 15 000 € HT | AP54: 48.845406 | AQ54: 2.399531 | AR54: 16 | AS54: https://pub-843c46afc4cb41489909bce00c9b143d.r2.dev/16%20-%20Paris/1%20Immeuble.jpg; https://pub-843c46afc4cb41489909bce00c9b143d.r2.dev/16%20-%20Paris/2.jpg; https://pub-843c46afc4cb41489909bce00c9b143d.r2.dev/16%20-%20Paris/3.jpg; https://pub-843c46afc4cb41489909bce00c9b143d.r2.dev/16%20-%20Paris/4.jpg; https://pub-843c46afc4cb41489909bce00c9b143d.r2.dev/16%20-%20Paris/5.jpg; https://pub-843c46afc4cb41489909bce00c9b143d.r2.dev/16%20-%20Paris/6%20Plan.jpg | AT54: Non | AU54: 588 €/m² = 50 000 € | AV54: Gecina
A55: =VLOOKUP(Tableau1[[#This Row],[N° Département]],Feuil1!$C$6:$E$106,3) -> Ile-de-France | B55: =VLOOKUP(Tableau1[[#This Row],[N° Département]],Feuil1!$C$6:$E$106,2) -> Paris | C55: =LEFT(Tableau1[[#This Row],[Code Postal]],2)*1 -> 75 | D55: 16 Avenue Mozart | E55: 75016 | F55: Paris | G55: =Tableau1[[#This Row],[Rue]]&CHAR(10)&Tableau1[[#This Row],[Code Postal]]&" - "&Tableau1[[#This Row],[Ville]] -> 16 Avenue Mozart 75016 - Paris | H55: https://maps.app.goo.gl/TpC5354fvwyNN33v5 | I55: Centre Ville | J55: Pied d'immeuble | K55: / | M55: / | N55: / | O55: 26 | P55: 12 (SS) + 14 | Q55: / | R55: / | S55: / | T55: =Tableau1[[#This Row],[Loyer €/m²]]*Tableau1[[#This Row],[Surface GLA]] -> 31200 | U55: =IFERROR(Tableau1[[#This Row],[Loyer annuel]]/12,"") -> 2600 | V55: 1200 | W55: / | X55: =Tableau1[[#This Row],[Charges €/m²]]*Tableau1[[#This Row],[Surface GLA]] -> 1300 | Y55: =Tableau1[[#This Row],[Charges annuelles]]/12 -> 108.33333 | Z55: 50 | AA55: =IFERROR(Tableau1[[#This Row],[Taxe foncière €/m²]]*Tableau1[[#This Row],[Surface GLA]],) -> 0 | AB55: / | AC55: =IFERROR(Tableau1[[#This Row],[Marketing €/m²]]*Tableau1[[#This Row],[Surface GLA]],) -> 0 | AD55: / | AE55: =IFERROR(Tableau1[[#This Row],[Loyer annuel]]+Tableau1[[#This Row],[Charges annuelles]]+Tableau1[[#This Row],[Taxe foncière]]+Tableau1[[#This Row],[Marketing]],"") -> 32500 | AF55: / | AG55: / | AH55: / | AI55: En l'état du précédent locataire | AJ55: Non | AK55: Froide | AL55: Librairie, onglerie, restaurant, supermarché, vêtement,s chaussures, bijouterie | AM55: Quartier commerçant avec fort flux quotidien. A proximité immédiate de la rue de Passy. | AO55: 30% du loyer facial avec un minimum de 15 000 € HT | AP55: 48.857212 | AQ55: 2.272657 | AR55: 17 | AS55: https://pub-843c46afc4cb41489909bce00c9b143d.r2.dev/17%20-%20Paris/1.jpg | AT55: Oui | AU55: 923 €/m² = 24 000 € | AV55: Quentin Breton
A56: =VLOOKUP(Tableau1[[#This Row],[N° Département]],Feuil1!$C$6:$E$106,3) -> Ile-de-France | B56: =VLOOKUP(Tableau1[[#This Row],[N° Département]],Feuil1!$C$6:$E$106,2) -> Paris | C56: =LEFT(Tableau1[[#This Row],[Code Postal]],2)*1 -> 75 | D56: 14 Rue de Rémusat | E56: 75016 | F56: Paris | G56: =Tableau1[[#This Row],[Rue]]&CHAR(10)&Tableau1[[#This Row],[Code Postal]]&" - "&Tableau1[[#This Row],[Ville]] -> 14 Rue de Rémusat 75016 - Paris | H56: https://maps.app.goo.gl/bRUcnSM5Cuttscrc9 | I56: Centre Ville | J56: Pied d'immeuble | K56: / | M56: / | N56: / | O56: 87 | P56: 30 (SS) + 55 | Q56: / | R56: / | S56: / | T56: =Tableau1[[#This Row],[Loyer €/m²]]*Tableau1[[#This Row],[Surface GLA]] -> 35061 | U56: =IFERROR(Tableau1[[#This Row],[Loyer annuel]]/12,"") -> 2921.75 | V56: 403 | W56: / | X56: =Tableau1[[#This Row],[Charges €/m²]]*Tableau1[[#This Row],[Surface GLA]] -> 2697 | Y56: =Tableau1[[#This Row],[Charges annuelles]]/12 -> 224.75 | Z56: 31 | AA56: =IFERROR(Tableau1[[#This Row],[Taxe foncière €/m²]]*Tableau1[[#This Row],[Surface GLA]],) -> 1479 | AB56: 17 | AC56: =IFERROR(Tableau1[[#This Row],[Marketing €/m²]]*Tableau1[[#This Row],[Surface GLA]],) -> 0 | AD56: / | AE56: =IFERROR(Tableau1[[#This Row],[Loyer annuel]]+Tableau1[[#This Row],[Charges annuelles]]+Tableau1[[#This Row],[Taxe foncière]]+Tableau1[[#This Row],[Marketing]],"") -> 39237 | AF56: / | AG56: / | AH56: / | AI56: En l'état du précédent locataire | AJ56: Non | AK56: Froide | AL56: Carrefour City, Pressing, Meuble, Epicerie fine, Quincaillerie, Restaurant | AM56: 2,6M de flux par an. Quartier résidentiel et de commerce de proximité. Fréquentation équilibrée toute la semaine, dans un quartier haut de gamme. | AO56: 30% du loyer facial avec un minimum de 15 000 € HT | AP56: 48.848202 | AQ56: 2.271099 | AR56: 18 | AS56: https://pub-843c46afc4cb41489909bce00c9b143d.r2.dev/18%20-%20Paris/1.jpg; https://pub-843c46afc4cb41489909bce00c9b143d.r2.dev/18%20-%20Paris/2%20Plan%20R-1.jpg; https://pub-843c46afc4cb41489909bce00c9b143d.r2.dev/18%20-%20Paris/3%20Plan%20RDC.jpg | AT56: Oui | AU56: Au BP | AV56: Gecina
A57: =VLOOKUP(Tableau1[[#This Row],[N° Département]],Feuil1!$C$6:$E$106,3) -> Ile-de-France | B57: =VLOOKUP(Tableau1[[#This Row],[N° Département]],Feuil1!$C$6:$E$106,2) -> Hauts-de-Seine | C57: =LEFT(Tableau1[[#This Row],[Code Postal]],2)*1 -> 92 | D57: Passage Châteaudun | E57: 92100 | F57: Boulogne-Billancourt | G57: =Tableau1[[#This Row],[Rue]]&CHAR(10)&Tableau1[[#This Row],[Code Postal]]&" - "&Tableau1[[#This Row],[Ville]] -> Passage Châteaudun 92100 - Boulogne-Billancourt | H57: https://maps.app.goo.gl/HLGbMrDwLnc5Q19B6 | I57: Centre Ville | J57: Pied d'immeuble | K57: / | M57: / | N57: A | O57: 110 | P57: / | Q57: / | R57: / | S57: / | T57: =Tableau1[[#This Row],[Loyer €/m²]]*Tableau1[[#This Row],[Surface GLA]] -> 60500 | U57: =IFERROR(Tableau1[[#This Row],[Loyer annuel]]/12,"") -> 5041.6667 | V57: 550 | W57: / | X57: =Tableau1[[#This Row],[Charges €/m²]]*Tableau1[[#This Row],[Surface GLA]] -> 770 | Y57: =Tableau1[[#This Row],[Charges annuelles]]/12 -> 64.166667 | Z57: 7 | AA57: =IFERROR(Tableau1[[#This Row],[Taxe foncière €/m²]]*Tableau1[[#This Row],[Surface GLA]],) -> 1430 | AB57: 13 | AC57: =IFERROR(Tableau1[[#This Row],[Marketing €/m²]]*Tableau1[[#This Row],[Surface GLA]],) -> 0 | AD57: / | AE57: =IFERROR(Tableau1[[#This Row],[Loyer annuel]]+Tableau1[[#This Row],[Charges annuelles]]+Tableau1[[#This Row],[Taxe foncière]]+Tableau1[[#This Row],[Marketing]],"") -> 62700 | AF57: ="3 mois = "&TEXT(ROUND(3/12*T57,0),"### ### ##0 €") -> 3 mois = 15 125 € | AG57: / | AH57: / | AI57: Brut de béton | AJ57: A étudier | AK57: Chaude et froide | AL57: / | AM57: Rue de quartier complétement réhabilitée avec 120 nouveaux logements et commerces | AO57: 30% du loyer facial avec un minimum de 15 000 € HT | AP57: 48.839245 | AQ57: 2.236142 | AR57: 19.1 | AS57: https://pub-843c46afc4cb41489909bce00c9b143d.r2.dev/19.1%20-%20Boulogne-Billancourt/1%20Vue%20d'ensemble.jpg; https://pub-843c46afc4cb41489909bce00c9b143d.r2.dev/19.1%20-%20Boulogne-Billancourt/2%20Plan%20de%20quartier.jpg; https://pub-843c46afc4cb41489909bce00c9b143d.r2.dev/19.1%20-%20Boulogne-Billancourt/3%20Plan%20de%20masse.jpg; https://pub-843c46afc4cb41489909bce00c9b143d.r2.dev/19.1%20-%20Boulogne-Billancourt/4%20Plan.jpg | AT57: Oui | AU57: Au BP | AV57: Altixia
A58: =VLOOKUP(Tableau1[[#This Row],[N° Département]],Feuil1!$C$6:$E$106,3) -> Ile-de-France | B58: =VLOOKUP(Tableau1[[#This Row],[N° Département]],Feuil1!$C$6:$E$106,2) -> Hauts-de-Seine | C58: =LEFT(Tableau1[[#This Row],[Code Postal]],2)*1 -> 92 | D58: Passage Châteaudun | E58: 92100 | F58: Boulogne-Billancourt | G58: =Tableau1[[#This Row],[Rue]]&CHAR(10)&Tableau1[[#This Row],[Code Postal]]&" - "&Tableau1[[#This Row],[Ville]] -> Passage Châteaudun 92100 - Boulogne-Billancourt | H58: https://maps.app.goo.gl/HLGbMrDwLnc5Q19B6 | I58: Centre Ville | J58: Pied d'immeuble | K58: / | M58: / | N58: B | O58: 66 | P58: / | Q58: / | R58: / | S58: / | T58: =Tableau1[[#This Row],[Loyer €/m²]]*Tableau1[[#This Row],[Surface GLA]] -> 29700 | U58: =IFERROR(Tableau1[[#This Row],[Loyer annuel]]/12,"") -> 2475 | V58: 450 | W58: / | X58: =Tableau1[[#This Row],[Charges €/m²]]*Tableau1[[#This Row],[Surface GLA]] -> 462 | Y58: =Tableau1[[#This Row],[Charges annuelles]]/12 -> 38.5 | Z58: 7 | AA58: =IFERROR(Tableau1[[#This Row],[Taxe foncière €/m²]]*Tableau1[[#This Row],[Surface GLA]],) -> 858 | AB58: 13 | AC58: =IFERROR(Tableau1[[#This Row],[Marketing €/m²]]*Tableau1[[#This Row],[Surface GLA]],) -> 0 | AD58: / | AE58: =IFERROR(Tableau1[[#This Row],[Loyer annuel]]+Tableau1[[#This Row],[Charges annuelles]]+Tableau1[[#This Row],[Taxe foncière]]+Tableau1[[#This Row],[Marketing]],"") -> 31020 | AF58: ="3 mois = "&TEXT(ROUND(3/12*T58,0),"### ### ##0 €") -> 3 mois = 7 425 € | AG58: / | AH58: / | AI58: Brut de béton | AJ58: A étudier | AK58: Chaude et froide | AL58: / | AM58: Rue de quartier complétement réhabilitée avec 120 nouveaux logements et commerces | AO58: 30% du loyer facial avec un minimum de 15 000 € HT | AP58: 48.839286 | AQ58: 2.236471 | AR58: 19.2 | AS58: https://pub-843c46afc4cb41489909bce00c9b143d.r2.dev/19.1%20-%20Boulogne-Billancourt/1%20Vue%20d'ensemble.jpg; https://pub-843c46afc4cb41489909bce00c9b143d.r2.dev/19.1%20-%20Boulogne-Billancourt/2%20Plan%20de%20quartier.jpg; https://pub-843c46afc4cb41489909bce00c9b143d.r2.dev/19.1%20-%20Boulogne-Billancourt/3%20Plan%20de%20masse.jpg; https://pub-843c46afc4cb41489909bce00c9b143d.r2.dev/19.2%20-%20Boulogne-Billancourt/4%20Plan.jpg | AT58: Oui | AU58: Au BP | AV58: Altixia
A59: =VLOOKUP(Tableau1[[#This Row],[N° Département]],Feuil1!$C$6:$E$106,3) -> Ile-de-France | B59: =VLOOKUP(Tableau1[[#This Row],[N° Département]],Feuil1!$C$6:$E$106,2) -> Hauts-de-Seine | C59: =LEFT(Tableau1[[#This Row],[Code Postal]],2)*1 -> 92 | D59: Passage Châteaudun | E59: 92100 | F59: Boulogne-Billancourt | G59: =Tableau1[[#This Row],[Rue]]&CHAR(10)&Tableau1[[#This Row],[Code Postal]]&" - "&Tableau1[[#This Row],[Ville]] -> Passage Châteaudun 92100 - Boulogne-Billancourt | H59: https://maps.app.goo.gl/HLGbMrDwLnc5Q19B6 | I59: Centre Ville | J59: Pied d'immeuble | K59: / | M59: / | N59: C | O59: 79 | P59: / | Q59: / | R59: / | S59: / | T59: =Tableau1[[#This Row],[Loyer €/m²]]*Tableau1[[#This Row],[Surface GLA]] -> 35550 | U59: =IFERROR(Tableau1[[#This Row],[Loyer annuel]]/12,"") -> 2962.5 | V59: 450 | W59: / | X59: =Tableau1[[#This Row],[Charges €/m²]]*Tableau1[[#This Row],[Surface GLA]] -> 553 | Y59: =Tableau1[[#This Row],[Charges annuelles]]/12 -> 46.083333 | Z59: 7 | AA59: =IFERROR(Tableau1[[#This Row],[Taxe foncière €/m²]]*Tableau1[[#This Row],[Surface GLA]],) -> 1027 | AB59: 13 | AC59: =IFERROR(Tableau1[[#This Row],[Marketing €/m²]]*Tableau1[[#This Row],[Surface GLA]],) -> 0 | AD59: / | AE59: =IFERROR(Tableau1[[#This Row],[Loyer annuel]]+Tableau1[[#This Row],[Charges annuelles]]+Tableau1[[#This Row],[Taxe foncière]]+Tableau1[[#This Row],[Marketing]],"") -> 37130 | AF59: ="3 mois = "&TEXT(ROUND(3/12*T59,0),"### ### ##0 €") -> 3 mois = 8 888 € | AG59: / | AH59: / | AI59: Brut de béton | AJ59: A étudier | AK59: Chaude et froide | AL59: / | AM59: Rue de quartier complétement réhabilitée avec 120 nouveaux logements et commerces | AO59: 30% du loyer facial avec un minimum de 15 000 € HT | AP59: 48.839353 | AQ59: 2.236992 | AR59: 19.3 | AS59: https://pub-843c46afc4cb41489909bce00c9b143d.r2.dev/19.1%20-%20Boulogne-Billancourt/1%20Vue%20d'ensemble.jpg; https://pub-843c46afc4cb41489909bce00c9b143d.r2.dev/19.1%20-%20Boulogne-Billancourt/2%20Plan%20de%20quartier.jpg; https://pub-843c46afc4cb41489909bce00c9b143d.r2.dev/19.1%20-%20Boulogne-Billancourt/3%20Plan%20de%20masse.jpg; https://pub-843c46afc4cb41489909bce00c9b143d.r2.dev/19.3%20-%20Boulogne-Billancourt/4%20Plan.jpg | AT59: Oui | AU59: Au BP | AV59: Altixia
A60: =VLOOKUP(Tableau1[[#This Row],[N° Département]],Feuil1!$C$6:$E$106,3) -> Ile-de-France | B60: =VLOOKUP(Tableau1[[#This Row],[N° Département]],Feuil1!$C$6:$E$106,2) -> Hauts-de-Seine | C60: =LEFT(Tableau1[[#This Row],[Code Postal]],2)*1 -> 92 | D60: Passage Châteaudun | E60: 92100 | F60: Boulogne-Billancourt | G60: =Tableau1[[#This Row],[Rue]]&CHAR(10)&Tableau1[[#This Row],[Code Postal]]&" - "&Tableau1[[#This Row],[Ville]] -> Passage Châteaudun 92100 - Boulogne-Billancourt | H60: https://maps.app.goo.gl/HLGbMrDwLnc5Q19B6 | I60: Centre Ville | J60: Pied d'immeuble | K60: / | M60: / | N60: D1 | O60: 47 | P60: / | Q60: 188 | R60: / | S60: / | T60: =Tableau1[[#This Row],[Loyer €/m²]]*Tableau1[[#This Row],[Surface GLA]] -> 25850 | U60: =IFERROR(Tableau1[[#This Row],[Loyer annuel]]/12,"") -> 2154.1667 | V60: 550 | W60: / | X60: =Tableau1[[#This Row],[Charges €/m²]]*Tableau1[[#This Row],[Surface GLA]] -> 329 | Y60: =Tableau1[[#This Row],[Charges annuelles]]/12 -> 27.416667 | Z60: 7 | AA60: =IFERROR(Tableau1[[#This Row],[Taxe foncière €/m²]]*Tableau1[[#This Row],[Surface GLA]],) -> 611 | AB60: 13 | AC60: =IFERROR(Tableau1[[#This Row],[Marketing €/m²]]*Tableau1[[#This Row],[Surface GLA]],) -> 0 | AD60: / | AE60: =IFERROR(Tableau1[[#This Row],[Loyer annuel]]+Tableau1[[#This Row],[Charges annuelles]]+Tableau1[[#This Row],[Taxe foncière]]+Tableau1[[#This Row],[Marketing]],"") -> 26790 | AF60: ="3 mois = "&TEXT(ROUND(3/12*T60,0),"### ### ##0 €") -> 3 mois = 6 463 € | AG60: / | AH60: / | AI60: Brut de béton | AJ60: A étudier | AK60: Chaude et froide | AL60: / | AM60: Rue de quartier complétement réhabilitée avec 120 nouveaux logements et commerces | AO60: 30% du loyer facial avec un minimum de 15 000 € HT | AP60: 48.839392 | AQ60: 2.237437 | AR60: 19.4 | AS60: https://pub-843c46afc4cb41489909bce00c9b143d.r2.dev/19.1%20-%20Boulogne-Billancourt/1%20Vue%20d'ensemble.jpg; https://pub-843c46afc4cb41489909bce00c9b143d.r2.dev/19.1%20-%20Boulogne-Billancourt/2%20Plan%20de%20quartier.jpg; https://pub-843c46afc4cb41489909bce00c9b143d.r2.dev/19.1%20-%20Boulogne-Billancourt/3%20Plan%20de%20masse.jpg; https://pub-843c46afc4cb41489909bce00c9b143d.r2.dev/19.4%20-%20Boulogne-Billancourt/4%20Plan.jpg | AT60: Oui | AU60: Au BP | AV60: Altixia
A61: =VLOOKUP(Tableau1[[#This Row],[N° Département]],Feuil1!$C$6:$E$106,3) -> Ile-de-France | B61: =VLOOKUP(Tableau1[[#This Row],[N° Département]],Feuil1!$C$6:$E$106,2) -> Hauts-de-Seine | C61: =LEFT(Tableau1[[#This Row],[Code Postal]],2)*1 -> 92 | D61: Passage Châteaudun | E61: 92100 | F61: Boulogne-Billancourt | G61: =Tableau1[[#This Row],[Rue]]&CHAR(10)&Tableau1[[#This Row],[Code Postal]]&" - "&Tableau1[[#This Row],[Ville]] -> Passage Châteaudun 92100 - Boulogne-Billancourt | H61: https://maps.app.goo.gl/HLGbMrDwLnc5Q19B6 | I61: Centre Ville | J61: Pied d'immeuble | K61: / | M61: / | N61: D2 | O61: 60 | P61: / | Q61: 188 | R61: / | S61: / | T61: =Tableau1[[#This Row],[Loyer €/m²]]*Tableau1[[#This Row],[Surface GLA]] -> 33000 | U61: =IFERROR(Tableau1[[#This Row],[Loyer annuel]]/12,"") -> 2750 | V61: 550 | W61: / | X61: =Tableau1[[#This Row],[Charges €/m²]]*Tableau1[[#This Row],[Surface GLA]] -> 420 | Y61: =Tableau1[[#This Row],[Charges annuelles]]/12 -> 35 | Z61: 7 | AA61: =IFERROR(Tableau1[[#This Row],[Taxe foncière €/m²]]*Tableau1[[#This Row],[Surface GLA]],) -> 780 | AB61: 13 | AC61: =IFERROR(Tableau1[[#This Row],[Marketing €/m²]]*Tableau1[[#This Row],[Surface GLA]],) -> 0 | AD61: / | AE61: =IFERROR(Tableau1[[#This Row],[Loyer annuel]]+Tableau1[[#This Row],[Charges annuelles]]+Tableau1[[#This Row],[Taxe foncière]]+Tableau1[[#This Row],[Marketing]],"") -> 34200 | AF61: ="3 mois = "&TEXT(ROUND(3/12*T61,0),"### ### ##0 €") -> 3 mois = 8 250 € | AG61: / | AH61: / | AI61: Brut de béton | AJ61: A étudier | AK61: Chaude et froide | AL61: / | AM61: Rue de quartier complétement réhabilitée avec 120 nouveaux logements et commerces | AO61: 30% du loyer facial avec un minimum de 15 000 € HT | AP61: 48.839450 | AQ61: 2.237432 | AR61: 19.5 | AS61: https://pub-843c46afc4cb41489909bce00c9b143d.r2.dev/19.1%20-%20Boulogne-Billancourt/1%20Vue%20d'ensemble.jpg; https://pub-843c46afc4cb41489909bce00c9b143d.r2.dev/19.1%20-%20Boulogne-Billancourt/2%20Plan%20de%20quartier.jpg; https://pub-843c46afc4cb41489909bce00c9b143d.r2.dev/19.1%20-%20Boulogne-Billancourt/3%20Plan%20de%20masse.jpg; https://pub-843c46afc4cb41489909bce00c9b143d.r2.dev/19.5%20-%20Boulogne-Billancourt/4%20Plan.jpg | AT61: Oui | AU61: Au BP | AV61: Altixia
A62: =VLOOKUP(Tableau1[[#This Row],[N° Département]],Feuil1!$C$6:$E$106,3) -> Ile-de-France | B62: =VLOOKUP(Tableau1[[#This Row],[N° Département]],Feuil1!$C$6:$E$106,2) -> Hauts-de-Seine | C62: =LEFT(Tableau1[[#This Row],[Code Postal]],2)*1 -> 92 | D62: Passage Châteaudun | E62: 92100 | F62: Boulogne-Billancourt | G62: =Tableau1[[#This Row],[Rue]]&CHAR(10)&Tableau1[[#This Row],[Code Postal]]&" - "&Tableau1[[#This Row],[Ville]] -> Passage Châteaudun 92100 - Boulogne-Billancourt | H62: https://maps.app.goo.gl/HLGbMrDwLnc5Q19B6 | I62: Centre Ville | J62: Pied d'immeuble | K62: / | M62: / | N62: D3 | O62: 81 | P62: / | Q62: 188 | R62: / | S62: / | T62: =Tableau1[[#This Row],[Loyer €/m²]]*Tableau1[[#This Row],[Surface GLA]] -> 44550 | U62: =IFERROR(Tableau1[[#This Row],[Loyer annuel]]/12,"") -> 3712.5 | V62: 550 | W62: / | X62: =Tableau1[[#This Row],[Charges €/m²]]*Tableau1[[#This Row],[Surface GLA]] -> 567 | Y62: =Tableau1[[#This Row],[Charges annuelles]]/12 -> 47.25 | Z62: 7 | AA62: =IFERROR(Tableau1[[#This Row],[Taxe foncière €/m²]]*Tableau1[[#This Row],[Surface GLA]],) -> 1053 | AB62: 13 | AC62: =IFERROR(Tableau1[[#This Row],[Marketing €/m²]]*Tableau1[[#This Row],[Surface GLA]],) -> 0 | AD62: / | AE62: =IFERROR(Tableau1[[#This Row],[Loyer annuel]]+Tableau1[[#This Row],[Charges annuelles]]+Tableau1[[#This Row],[Taxe foncière]]+Tableau1[[#This Row],[Marketing]],"") -> 46170 | AF62: ="3 mois = "&TEXT(ROUND(3/12*T62,0),"### ### ##0 €") -> 3 mois = 11 138 € | AG62: / | AH62: / | AI62: Brut de béton | AJ62: A étudier | AK62: Chaude et froide | AL62: / | AM62: Rue de quartier complétement réhabilitée avec 120 nouveaux logements et commerces | AO62: 30% du loyer facial avec un minimum de 15 000 € HT | AP62: 48.839512 | AQ62: 2.237432 | AR62: 19.6 | AS62: https://pub-843c46afc4cb41489909bce00c9b143d.r2.dev/19.1%20-%20Boulogne-Billancourt/1%20Vue%20d'ensemble.jpg; https://pub-843c46afc4cb41489909bce00c9b143d.r2.dev/19.1%20-%20Boulogne-Billancourt/2%20Plan%20de%20quartier.jpg; https://pub-843c46afc4cb41489909bce00c9b143d.r2.dev/19.1%20-%20Boulogne-Billancourt/3%20Plan%20de%20masse.jpg; https://pub-843c46afc4cb41489909bce00c9b143d.r2.dev/19.6%20-%20Boulogne-Billancourt/4%20Plan.jpg | AT62: Oui | AU62: Au BP | AV62: Altixia
A63: =VLOOKUP(Tableau1[[#This Row],[N° Département]],Feuil1!$C$6:$E$106,3) -> Ile-de-France | B63: =VLOOKUP(Tableau1[[#This Row],[N° Département]],Feuil1!$C$6:$E$106,2) -> Hauts-de-Seine | C63: =LEFT(Tableau1[[#This Row],[Code Postal]],2)*1 -> 92 | D63: Passage Châteaudun | E63: 92100 | F63: Boulogne-Billancourt | G63: =Tableau1[[#This Row],[Rue]]&CHAR(10)&Tableau1[[#This Row],[Code Postal]]&" - "&Tableau1[[#This Row],[Ville]] -> Passage Châteaudun 92100 - Boulogne-Billancourt | H63: https://maps.app.goo.gl/HLGbMrDwLnc5Q19B6 | I63: Centre Ville | J63: Pied d'immeuble | K63: / | M63: / | N63: E | O63: 45 | P63: / | Q63: / | R63: / | S63: / | T63: =Tableau1[[#This Row],[Loyer €/m²]]*Tableau1[[#This Row],[Surface GLA]] -> 24750 | U63: =IFERROR(Tableau1[[#This Row],[Loyer annuel]]/12,"") -> 2062.5 | V63: 550 | W63: / | X63: =Tableau1[[#This Row],[Charges €/m²]]*Tableau1[[#This Row],[Surface GLA]] -> 315 | Y63: =Tableau1[[#This Row],[Charges annuelles]]/12 -> 26.25 | Z63: 7 | AA63: =IFERROR(Tableau1[[#This Row],[Taxe foncière €/m²]]*Tableau1[[#This Row],[Surface GLA]],) -> 585 | AB63: 13 | AC63: =IFERROR(Tableau1[[#This Row],[Marketing €/m²]]*Tableau1[[#This Row],[Surface GLA]],) -> 0 | AD63: / | AE63: =IFERROR(Tableau1[[#This Row],[Loyer annuel]]+Tableau1[[#This Row],[Charges annuelles]]+Tableau1[[#This Row],[Taxe foncière]]+Tableau1[[#This Row],[Marketing]],"") -> 25650 | AF63: ="3 mois = "&TEXT(ROUND(3/12*T63,0),"### ### ##0 €") -> 3 mois = 6 188 € | AG63: / | AH63: / | AI63: Brut de béton | AJ63: A étudier | AK63: Chaude et froide | AL63: / | AM63: Rue de quartier complétement réhabilitée avec 120 nouveaux logements et commerces | AO63: 30% du loyer facial avec un minimum de 15 000 € HT | AP63: 48.839090 | AQ63: 2.236187 | AR63: 19.7 | AS63: https://pub-843c46afc4cb41489909bce00c9b143d.r2.dev/19.1%20-%20Boulogne-Billancourt/1%20Vue%20d'ensemble.jpg; https://pub-843c46afc4cb41489909bce00c9b143d.r2.dev/19.1%20-%20Boulogne-Billancourt/2%20Plan%20de%20quartier.jpg; https://pub-843c46afc4cb41489909bce00c9b143d.r2.dev/19.1%20-%20Boulogne-Billancourt/3%20Plan%20de%20masse.jpg; https://pub-843c46afc4cb41489909bce00c9b143d.r2.dev/19.7%20-%20Boulogne-Billancourt/4%20Plan.jpg | AT63: Oui | AU63: Au BP | AV63: Altixia
A64: =VLOOKUP(Tableau1[[#This Row],[N° Département]],Feuil1!$C$6:$E$106,3) -> Ile-de-France | B64: =VLOOKUP(Tableau1[[#This Row],[N° Département]],Feuil1!$C$6:$E$106,2) -> Hauts-de-Seine | C64: =LEFT(Tableau1[[#This Row],[Code Postal]],2)*1 -> 92 | D64: Passage Châteaudun | E64: 92100 | F64: Boulogne-Billancourt | G64: =Tableau1[[#This Row],[Rue]]&CHAR(10)&Tableau1[[#This Row],[Code Postal]]&" - "&Tableau1[[#This Row],[Ville]] -> Passage Châteaudun 92100 - Boulogne-Billancourt | H64: https://maps.app.goo.gl/HLGbMrDwLnc5Q19B6 | I64: Centre Ville | J64: Pied d'immeuble | K64: / | M64: / | N64: F | O64: 73 | P64: / | Q64: / | R64: / | S64: / | T64: =Tableau1[[#This Row],[Loyer €/m²]]*Tableau1[[#This Row],[Surface GLA]] -> 32850 | U64: =IFERROR(Tableau1[[#This Row],[Loyer annuel]]/12,"") -> 2737.5 | V64: 450 | W64: / | X64: =Tableau1[[#This Row],[Charges €/m²]]*Tableau1[[#This Row],[Surface GLA]] -> 511 | Y64: =Tableau1[[#This Row],[Charges annuelles]]/12 -> 42.583333 | Z64: 7 | AA64: =IFERROR(Tableau1[[#This Row],[Taxe foncière €/m²]]*Tableau1[[#This Row],[Surface GLA]],) -> 949 | AB64: 13 | AC64: =IFERROR(Tableau1[[#This Row],[Marketing €/m²]]*Tableau1[[#This Row],[Surface GLA]],) -> 0 | AD64: / | AE64: =IFERROR(Tableau1[[#This Row],[Loyer annuel]]+Tableau1[[#This Row],[Charges annuelles]]+Tableau1[[#This Row],[Taxe foncière]]+Tableau1[[#This Row],[Marketing]],"") -> 34310 | AF64: ="3 mois = "&TEXT(ROUND(3/12*T64,0),"### ### ##0 €") -> 3 mois = 8 213 € | AG64: / | AH64: / | AI64: Brut de béton | AJ64: A étudier | AK64: Chaude et froide | AL64: / | AM64: Rue de quartier complétement réhabilitée avec 120 nouveaux logements et commerces | AO64: 30% du loyer facial avec un minimum de 15 000 € HT | AP64: 48.839178 | AQ64: 2.236960 | AR64: 19.8 | AS64: https://pub-843c46afc4cb41489909bce00c9b143d.r2.dev/19.1%20-%20Boulogne-Billancourt/1%20Vue%20d'ensemble.jpg; https://pub-843c46afc4cb41489909bce00c9b143d.r2.dev/19.1%20-%20Boulogne-Billancourt/2%20Plan%20de%20quartier.jpg; https://pub-843c46afc4cb41489909bce00c9b143d.r2.dev/19.1%20-%20Boulogne-Billancourt/3%20Plan%20de%20masse.jpg; https://pub-843c46afc4cb41489909bce00c9b143d.r2.dev/19.8%20-%20Boulogne-Billancourt/4%20Plan.jpg | AT64: Oui | AU64: Au BP | AV64: Altixia
A65: =VLOOKUP(Tableau1[[#This Row],[N° Département]],Feuil1!$C$6:$E$106,3) -> Ile-de-France | B65: =VLOOKUP(Tableau1[[#This Row],[N° Département]],Feuil1!$C$6:$E$106,2) -> Hauts-de-Seine | C65: =LEFT(Tableau1[[#This Row],[Code Postal]],2)*1 -> 92 | D65: 143 Rue des Fauvelles | E65: 92250 | F65: La Garenne-Colombes | G65: =Tableau1[[#This Row],[Rue]]&CHAR(10)&Tableau1[[#This Row],[Code Postal]]&" - "&Tableau1[[#This Row],[Ville]] -> 143 Rue des Fauvelles 92250 - La Garenne-Colombes | H65: https://www.google.com/maps/place/143+Rue+des+Fauvelles,+92250+La+Garenne-Colombes | I65: Centre Ville | J65: Pied d'immeuble | K65: / | M65: / | N65: 1 | O65: 80 | P65: / | Q65: 190 | R65: / | S65: / | T65: =Tableau1[[#This Row],[Loyer €/m²]]*Tableau1[[#This Row],[Surface GLA]] -> 30000 | U65: =IFERROR(Tableau1[[#This Row],[Loyer annuel]]/12,"") -> 2500 | V65: 375 | W65: / | X65: =Tableau1[[#This Row],[Charges €/m²]]*Tableau1[[#This Row],[Surface GLA]] -> 320 | Y65: =Tableau1[[#This Row],[Charges annuelles]]/12 -> 26.666667 | Z65: 4 | AA65: =IFERROR(Tableau1[[#This Row],[Taxe foncière €/m²]]*Tableau1[[#This Row],[Surface GLA]],) -> 1520 | AB65: 19 | AC65: =IFERROR(Tableau1[[#This Row],[Marketing €/m²]]*Tableau1[[#This Row],[Surface GLA]],) -> 0 | AD65: / | AE65: =IFERROR(Tableau1[[#This Row],[Loyer annuel]]+Tableau1[[#This Row],[Charges annuelles]]+Tableau1[[#This Row],[Taxe foncière]]+Tableau1[[#This Row],[Marketing]],"") -> 31840 | AF65: / | AG65: / | AH65: / | AI65: Brut de béton | AJ65: Non | AK65: Froide | AL65: Logement, bureaux et restaurants | AM65: 1,2 M de flux par an, avant ouverture du nouveau siège Engie (9 000 emplois). Quartier résidentiel et de bureau | AO65: 30% du loyer facial avec un minimum de 15 000 € HT | AP65: 48.900598 | AQ65: 2.231909 | AR65: 20.1 | AS65: https://pub-843c46afc4cb41489909bce00c9b143d.r2.dev/20.1%20-%20La%20Garenne-Colombes/1%20Vue%20d'ensemble.jpg; https://pub-843c46afc4cb41489909bce00c9b143d.r2.dev/20.1%20-%20La%20Garenne-Colombes/2%20Plan.jpg | AT65: Oui | AU65: Au BP | AV65: Gecina
A66: =VLOOKUP(Tableau1[[#This Row],[N° Département]],Feuil1!$C$6:$E$106,3) -> Ile-de-France | B66: =VLOOKUP(Tableau1[[#This Row],[N° Département]],Feuil1!$C$6:$E$106,2) -> Hauts-de-Seine | C66: =LEFT(Tableau1[[#This Row],[Code Postal]],2)*1 -> 92 | D66: 143 Rue des Fauvelles | E66: 92250 | F66: La Garenne-Colombes | G66: =Tableau1[[#This Row],[Rue]]&CHAR(10)&Tableau1[[#This Row],[Code Postal]]&" - "&Tableau1[[#This Row],[Ville]] -> 143 Rue des Fauvelles 92250 - La Garenne-Colombes | H66: https://www.google.com/maps/place/143+Rue+des+Fauvelles,+92250+La+Garenne-Colombes | I66: Centre Ville | J66: Pied d'immeuble | K66: / | M66: / | N66: 2 | O66: 110 | P66: / | Q66: 190 | R66: / | S66: / | T66: =Tableau1[[#This Row],[Loyer €/m²]]*Tableau1[[#This Row],[Surface GLA]] -> 42020 | U66: =IFERROR(Tableau1[[#This Row],[Loyer annuel]]/12,"") -> 3501.6667 | V66: 382 | W66: / | X66: =Tableau1[[#This Row],[Charges €/m²]]*Tableau1[[#This Row],[Surface GLA]] -> 440 | Y66: =Tableau1[[#This Row],[Charges annuelles]]/12 -> 36.666667 | Z66: 4 | AA66: =IFERROR(Tableau1[[#This Row],[Taxe foncière €/m²]]*Tableau1[[#This Row],[Surface GLA]],) -> 2090 | AB66: 19 | AC66: =IFERROR(Tableau1[[#This Row],[Marketing €/m²]]*Tableau1[[#This Row],[Surface GLA]],) -> 0 | AD66: / | AE66: =IFERROR(Tableau1[[#This Row],[Loyer annuel]]+Tableau1[[#This Row],[Charges annuelles]]+Tableau1[[#This Row],[Taxe foncière]]+Tableau1[[#This Row],[Marketing]],"") -> 44550 | AF66: / | AG66: / | AH66: / | AI66: Brut de béton | AJ66: Oui | AK66: Chaude et froide | AL66: Logement, bureaux et restaurants | AM66: 1,2 M de flux par an, avant ouverture du nouveau siège Engie (9 000 emplois). Quartier résidentiel et de bureau | AO66: 30% du loyer facial avec un minimum de 15 000 € HT | AP66: 48.900566 | AQ66: 2.231869 | AR66: 20.2 | AS66: https://pub-843c46afc4cb41489909bce00c9b143d.r2.dev/20.1%20-%20La%20Garenne-Colombes/1%20Vue%20d'ensemble.jpg; https://pub-843c46afc4cb41489909bce00c9b143d.r2.dev/20.2%20-%20La%20Garenne-Colombes/2%20Plan.jpg | AT66: Oui | AU66: Au BP | AV66: Gecina
A67: =VLOOKUP(Tableau1[[#This Row],[N° Département]],Feuil1!$C$6:$E$106,3) -> Ile-de-France | B67: =VLOOKUP(Tableau1[[#This Row],[N° Département]],Feuil1!$C$6:$E$106,2) -> Hauts-de-Seine | C67: =LEFT(Tableau1[[#This Row],[Code Postal]],2)*1 -> 92 | D67: Cours du Commerce | E67: 92290 | F67: Châtenay-Malabry | G67: =Tableau1[[#This Row],[Rue]]&CHAR(10)&Tableau1[[#This Row],[Code Postal]]&" - "&Tableau1[[#This Row],[Ville]] -> Cours du Commerce 92290 - Châtenay-Malabry | H67: https://maps.app.goo.gl/2ebht3ajwGmy4Qai6 | I67: Centre Ville | J67: Pied d'immeuble | K67: / | M67: / | N67: G2 - A | O67: 321 | P67: / | Q67: / | R67: / | S67: / | T67: =Tableau1[[#This Row],[Loyer €/m²]]*Tableau1[[#This Row],[Surface GLA]] -> 104325 | U67: =IFERROR(Tableau1[[#This Row],[Loyer annuel]]/12,"") -> 8693.75 | V67: 325 | W67: / | X67: =Tableau1[[#This Row],[Charges €/m²]]*Tableau1[[#This Row],[Surface GLA]] -> 9630 | Y67: =Tableau1[[#This Row],[Charges annuelles]]/12 -> 802.5 | Z67: 30 | AA67: =IFERROR(Tableau1[[#This Row],[Taxe foncière €/m²]]*Tableau1[[#This Row],[Surface GLA]],) -> 0 | AB67: / | AC67: =IFERROR(Tableau1[[#This Row],[Marketing €/m²]]*Tableau1[[#This Row],[Surface GLA]],) -> 0 | AD67: / | AE67: =IFERROR(Tableau1[[#This Row],[Loyer annuel]]+Tableau1[[#This Row],[Charges annuelles]]+Tableau1[[#This Row],[Taxe foncière]]+Tableau1[[#This Row],[Marketing]],"") -> 113955 | AF67: ="3 mois = "&TEXT(ROUND(3/12*T67,0),"### ### ##0 €") -> 3 mois = 26 081 € | AG67: / | AH67: / | AI67: Brut de béton | AJ67: Oui | AK67: Chaude et froide | AL67: Basic Fit, Gifi, Lidl, Carrefour Market, Optical Center, Emjo, Perene, restaurants, coiffeur, centre de santé | AM67: Quartier neuf mixte. 40 000 m² de bureaux commercialisés. Nouveau siège de Lidl France. Les charges incluent la taxe foncière | AO67: 30% du loyer facial avec un minimum de 15 000 € HT | AP67: 48.764103 | AQ67: 2.288061 | AR67: 21.1 | AS67: https://pub-843c46afc4cb41489909bce00c9b143d.r2.dev/21.1%20-%20Ch%C3%A2tenay-Malabry/1%20Vue%20d'ensemble.jpg; https://pub-843c46afc4cb41489909bce00c9b143d.r2.dev/21.1%20-%20Ch%C3%A2tenay-Malabry/2.jpg; https://pub-843c46afc4cb41489909bce00c9b143d.r2.dev/21.1%20-%20Ch%C3%A2tenay-Malabry/3%20Plan%20de%20masse.jpg; https://pub-843c46afc4cb41489909bce00c9b143d.r2.dev/21.1%20-%20Ch%C3%A2tenay-Malabry/4.jpg | AT67: Oui | AU67: Au BP | AV67: Altixia
A68: =VLOOKUP(Tableau1[[#This Row],[N° Département]],Feuil1!$C$6:$E$106,3) -> Ile-de-France | B68: =VLOOKUP(Tableau1[[#This Row],[N° Département]],Feuil1!$C$6:$E$106,2) -> Hauts-de-Seine | C68: =LEFT(Tableau1[[#This Row],[Code Postal]],2)*1 -> 92 | D68: Cours du Commerce | E68: 92290 | F68: Châtenay-Malabry | G68: =Tableau1[[#This Row],[Rue]]&CHAR(10)&Tableau1[[#This Row],[Code Postal]]&" - "&Tableau1[[#This Row],[Ville]] -> Cours du Commerce 92290 - Châtenay-Malabry | H68: https://maps.app.goo.gl/raUgf8ugtMCj225m9 | I68: Centre Ville | J68: Pied d'immeuble | K68: / | M68: / | N68: G2 - B | O68: 159 | P68: / | Q68: / | R68: / | S68: / | T68: =Tableau1[[#This Row],[Loyer €/m²]]*Tableau1[[#This Row],[Surface GLA]] -> 51675 | U68: =IFERROR(Tableau1[[#This Row],[Loyer annuel]]/12,"") -> 4306.25 | V68: 325 | W68: / | X68: =Tableau1[[#This Row],[Charges €/m²]]*Tableau1[[#This Row],[Surface GLA]] -> 4770 | Y68: =Tableau1[[#This Row],[Charges annuelles]]/12 -> 397.5 | Z68: 30 | AA68: =IFERROR(Tableau1[[#This Row],[Taxe foncière €/m²]]*Tableau1[[#This Row],[Surface GLA]],) -> 0 | AB68: / | AC68: =IFERROR(Tableau1[[#This Row],[Marketing €/m²]]*Tableau1[[#This Row],[Surface GLA]],) -> 0 | AD68: / | AE68: =IFERROR(Tableau1[[#This Row],[Loyer annuel]]+Tableau1[[#This Row],[Charges annuelles]]+Tableau1[[#This Row],[Taxe foncière]]+Tableau1[[#This Row],[Marketing]],"") -> 56445 | AF68: ="3 mois = "&TEXT(ROUND(3/12*T68,0),"### ### ##0 €") -> 3 mois = 12 919 € | AG68: / | AH68: / | AI68: Brut de béton | AJ68: Oui | AK68: Chaude et froide | AL68: Basic Fit, Gifi, Lidl, Carrefour Market, Optical Center, Emjo, Perene, restaurants, coiffeur, centre de santé | AM68: Quartier neuf mixte. 40 000 m² de bureaux commercialisés. Nouveau siège de Lidl France. Les charges incluent la taxe foncière | AO68: 30% du loyer facial avec un minimum de 15 000 € HT | AP68: 48.764022 | AQ68: 2.288136 | AR68: 21.2 | AS68: https://pub-843c46afc4cb41489909bce00c9b143d.r2.dev/21.1%20-%20Ch%C3%A2tenay-Malabry/1%20Vue%20d'ensemble.jpg; https://pub-843c46afc4cb41489909bce00c9b143d.r2.dev/21.1%20-%20Ch%C3%A2tenay-Malabry/2.jpg; https://pub-843c46afc4cb41489909bce00c9b143d.r2.dev/21.1%20-%20Ch%C3%A2tenay-Malabry/3%20Plan%20de%20masse.jpg; https://pub-843c46afc4cb41489909bce00c9b143d.r2.dev/21.2%20-%20Ch%C3%A2tenay-Malabry/4.jpg | AT68: Oui | AU68: Au BP | AV68: Altixia
A69: =VLOOKUP(Tableau1[[#This Row],[N° Département]],Feuil1!$C$6:$E$106,3) -> Ile-de-France | B69: =VLOOKUP(Tableau1[[#This Row],[N° Département]],Feuil1!$C$6:$E$106,2) -> Hauts-de-Seine | C69: =LEFT(Tableau1[[#This Row],[Code Postal]],2)*1 -> 92 | D69: Cours du Commerce | E69: 92290 | F69: Châtenay-Malabry | G69: =Tableau1[[#This Row],[Rue]]&CHAR(10)&Tableau1[[#This Row],[Code Postal]]&" - "&Tableau1[[#This Row],[Ville]] -> Cours du Commerce 92290 - Châtenay-Malabry | H69: https://maps.app.goo.gl/B5ESPn9FHHSgMeq69 | I69: Centre Ville | J69: Pied d'immeuble | K69: / | M69: / | N69: G4 | O69: 281 | P69: / | Q69: / | R69: / | S69: / | T69: =Tableau1[[#This Row],[Loyer €/m²]]*Tableau1[[#This Row],[Surface GLA]] -> 91325 | U69: =IFERROR(Tableau1[[#This Row],[Loyer annuel]]/12,"") -> 7610.4167 | V69: 325 | W69: / | X69: =Tableau1[[#This Row],[Charges €/m²]]*Tableau1[[#This Row],[Surface GLA]] -> 8430 | Y69: =Tableau1[[#This Row],[Charges annuelles]]/12 -> 702.5 | Z69: 30 | AA69: =IFERROR(Tableau1[[#This Row],[Taxe foncière €/m²]]*Tableau1[[#This Row],[Surface GLA]],) -> 0 | AB69: / | AC69: =IFERROR(Tableau1[[#This Row],[Marketing €/m²]]*Tableau1[[#This Row],[Surface GLA]],) -> 0 | AD69: / | AE69: =IFERROR(Tableau1[[#This Row],[Loyer annuel]]+Tableau1[[#This Row],[Charges annuelles]]+Tableau1[[#This Row],[Taxe foncière]]+Tableau1[[#This Row],[Marketing]],"") -> 99755 | AF69: ="3 mois = "&TEXT(ROUND(3/12*T69,0),"### ### ##0 €") -> 3 mois = 22 831 € | AG69: / | AH69: / | AI69: Brut de béton | AJ69: Oui | AK69: Chaude et froide | AL69: Basic Fit, Gifi, Lidl, Carrefour Market, Optical Center, Emjo, Perene, restaurants, coiffeur, centre de santé | AM69: Quartier neuf mixte. 40 000 m² de bureaux commercialisés. Nouveau siège de Lidl France. Les charges incluent la taxe foncière | AO69: 30% du loyer facial avec un minimum de 15 000 € HT | AP69: 48.763691 | AQ69: 2.288439 | AR69: 21.3 | AS69: https://pub-843c46afc4cb41489909bce00c9b143d.r2.dev/21.1%20-%20Ch%C3%A2tenay-Malabry/1%20Vue%20d'ensemble.jpg; https://pub-843c46afc4cb41489909bce00c9b143d.r2.dev/21.1%20-%20Ch%C3%A2tenay-Malabry/2.jpg; https://pub-843c46afc4cb41489909bce00c9b143d.r2.dev/21.1%20-%20Ch%C3%A2tenay-Malabry/3%20Plan%20de%20masse.jpg; https://pub-843c46afc4cb41489909bce00c9b143d.r2.dev/21.3%20-%20Ch%C3%A2tenay-Malabry/4.jpg; https://pub-843c46afc4cb41489909bce00c9b143d.r2.dev/21.3%20-%20Ch%C3%A2tenay-Malabry/5.jpg | AT69: Oui | AU69: Au BP | AV69: Altixia
A70: =VLOOKUP(Tableau1[[#This Row],[N° Département]],Feuil1!$C$6:$E$106,3) -> Ile-de-France | B70: =VLOOKUP(Tableau1[[#This Row],[N° Département]],Feuil1!$C$6:$E$106,2) -> Hauts-de-Seine | C70: =LEFT(Tableau1[[#This Row],[Code Postal]],2)*1 -> 92 | D70: Cours du Commerce | E70: 92290 | F70: Châtenay-Malabry | G70: =Tableau1[[#This Row],[Rue]]&CHAR(10)&Tableau1[[#This Row],[Code Postal]]&" - "&Tableau1[[#This Row],[Ville]] -> Cours du Commerce 92290 - Châtenay-Malabry | H70: https://maps.app.goo.gl/RPqrEKJTBqHmUoWo7 | I70: Centre Ville | J70: Pied d'immeuble | K70: / | M70: / | N70: G7 | O70: 168 | P70: / | Q70: / | R70: / | S70: / | T70: =Tableau1[[#This Row],[Loyer €/m²]]*Tableau1[[#This Row],[Surface GLA]] -> 54600 | U70: =IFERROR(Tableau1[[#This Row],[Loyer annuel]]/12,"") -> 4550 | V70: 325 | W70: / | X70: =Tableau1[[#This Row],[Charges €/m²]]*Tableau1[[#This Row],[Surface GLA]] -> 5040 | Y70: =Tableau1[[#This Row],[Charges annuelles]]/12 -> 420 | Z70: 30 | AA70: =IFERROR(Tableau1[[#This Row],[Taxe foncière €/m²]]*Tableau1[[#This Row],[Surface GLA]],) -> 0 | AB70: / | AC70: =IFERROR(Tableau1[[#This Row],[Marketing €/m²]]*Tableau1[[#This Row],[Surface GLA]],) -> 0 | AD70: / | AE70: =IFERROR(Tableau1[[#This Row],[Loyer annuel]]+Tableau1[[#This Row],[Charges annuelles]]+Tableau1[[#This Row],[Taxe foncière]]+Tableau1[[#This Row],[Marketing]],"") -> 59640 | AF70: ="3 mois = "&TEXT(ROUND(3/12*T70,0),"### ### ##0 €") -> 3 mois = 13 650 € | AG70: / | AH70: / | AI70: Brut de béton | AJ70: Oui | AK70: Chaude et froide | AL70: Basic Fit, Gifi, Lidl, Carrefour Market, Optical Center, Emjo, Perene, restaurants, coiffeur, centre de santé | AM70: Quartier neuf mixte. 40 000 m² de bureaux commercialisés. Nouveau siège de Lidl France. Les charges incluent la taxe foncière | AO70: 30% du loyer facial avec un minimum de 15 000 € HT | AP70: 48.763755 | AQ70: 2.289204 | AR70: 21.4 | AS70: https://pub-843c46afc4cb41489909bce00c9b143d.r2.dev/21.1%20-%20Ch%C3%A2tenay-Malabry/1%20Vue%20d'ensemble.jpg; https://pub-843c46afc4cb41489909bce00c9b143d.r2.dev/21.1%20-%20Ch%C3%A2tenay-Malabry/2.jpg; https://pub-843c46afc4cb41489909bce00c9b143d.r2.dev/21.1%20-%20Ch%C3%A2tenay-Malabry/3%20Plan%20de%20masse.jpg; https://pub-843c46afc4cb41489909bce00c9b143d.r2.dev/21.4%20-%20Ch%C3%A2tenay-Malabry/4.jpg | AT70: Oui | AU70: Au BP | AV70: Altixia
A71: =VLOOKUP(Tableau1[[#This Row],[N° Département]],Feuil1!$C$6:$E$106,3) -> Ile-de-France | B71: =VLOOKUP(Tableau1[[#This Row],[N° Département]],Feuil1!$C$6:$E$106,2) -> Hauts-de-Seine | C71: =LEFT(Tableau1[[#This Row],[Code Postal]],2)*1 -> 92 | D71: Cours du Commerce | E71: 92290 | F71: Châtenay-Malabry | G71: =Tableau1[[#This Row],[Rue]]&CHAR(10)&Tableau1[[#This Row],[Code Postal]]&" - "&Tableau1[[#This Row],[Ville]] -> Cours du Commerce 92290 - Châtenay-Malabry | H71: https://maps.app.goo.gl/AUmyb5nmLTZPwTV36 | I71: Centre Ville | J71: Pied d'immeuble | K71: / | M71: / | N71: P2 Com.1 | O71: 228 | P71: / | Q71: / | R71: / | S71: / | T71: =Tableau1[[#This Row],[Loyer €/m²]]*Tableau1[[#This Row],[Surface GLA]] -> 74100 | U71: =IFERROR(Tableau1[[#This Row],[Loyer annuel]]/12,"") -> 6175 | V71: 325 | W71: / | X71: =Tableau1[[#This Row],[Charges €/m²]]*Tableau1[[#This Row],[Surface GLA]] -> 6840 | Y71: =Tableau1[[#This Row],[Charges annuelles]]/12 -> 570 | Z71: 30 | AA71: =IFERROR(Tableau1[[#This Row],[Taxe foncière €/m²]]*Tableau1[[#This Row],[Surface GLA]],) -> 0 | AB71: / | AC71: =IFERROR(Tableau1[[#This Row],[Marketing €/m²]]*Tableau1[[#This Row],[Surface GLA]],) -> 0 | AD71: / | AE71: =IFERROR(Tableau1[[#This Row],[Loyer annuel]]+Tableau1[[#This Row],[Charges annuelles]]+Tableau1[[#This Row],[Taxe foncière]]+Tableau1[[#This Row],[Marketing]],"") -> 80940 | AF71: ="3 mois = "&TEXT(ROUND(3/12*T71,0),"### ### ##0 €") -> 3 mois = 18 525 € | AG71: / | AH71: / | AI71: Brut de béton | AJ71: Oui | AK71: Chaude et froide | AL71: Basic Fit, Gifi, Lidl, Carrefour Market, Optical Center, Emjo, Perene, restaurants, coiffeur, centre de santé | AM71: Quartier neuf mixte. 40 000 m² de bureaux commercialisés. Nouveau siège de Lidl France. Les charges incluent la taxe foncière | AO71: 30% du loyer facial avec un minimum de 15 000 € HT | AP71: 48.762872 | AQ71: 2.287981 | AR71: 21.5 | AS71: https://pub-843c46afc4cb41489909bce00c9b143d.r2.dev/21.1%20-%20Ch%C3%A2tenay-Malabry/1%20Vue%20d'ensemble.jpg; https://pub-843c46afc4cb41489909bce00c9b143d.r2.dev/21.1%20-%20Ch%C3%A2tenay-Malabry/2.jpg; https://pub-843c46afc4cb41489909bce00c9b143d.r2.dev/21.1%20-%20Ch%C3%A2tenay-Malabry/3%20Plan%20de%20masse.jpg; https://pub-843c46afc4cb41489909bce00c9b143d.r2.dev/21.5%20-%20Ch%C3%A2tenay-Malabry/4.jpg; https://pub-843c46afc4cb41489909bce00c9b143d.r2.dev/21.5%20-%20Ch%C3%A2tenay-Malabry/5.jpg | AT71: Oui | AU71: Au BP | AV71: Altixia
A72: =VLOOKUP(Tableau1[[#This Row],[N° Département]],Feuil1!$C$6:$E$106,3) -> Ile-de-France | B72: =VLOOKUP(Tableau1[[#This Row],[N° Département]],Feuil1!$C$6:$E$106,2) -> Hauts-de-Seine | C72: =LEFT(Tableau1[[#This Row],[Code Postal]],2)*1 -> 92 | D72: Cours du Commerce | E72: 92290 | F72: Châtenay-Malabry | G72: =Tableau1[[#This Row],[Rue]]&CHAR(10)&Tableau1[[#This Row],[Code Postal]]&" - "&Tableau1[[#This Row],[Ville]] -> Cours du Commerce 92290 - Châtenay-Malabry | H72: https://maps.app.goo.gl/AUmyb5nmLTZPwTV36 | I72: Centre Ville | J72: Pied d'immeuble | K72: / | M72: / | N72: P2 Com.2 | O72: 133 | P72: / | Q72: / | R72: / | S72: / | T72: =Tableau1[[#This Row],[Loyer €/m²]]*Tableau1[[#This Row],[Surface GLA]] -> 43225 | U72: =IFERROR(Tableau1[[#This Row],[Loyer annuel]]/12,"") -> 3602.0833 | V72: 325 | W72: / | X72: =Tableau1[[#This Row],[Charges €/m²]]*Tableau1[[#This Row],[Surface GLA]] -> 3990 | Y72: =Tableau1[[#This Row],[Charges annuelles]]/12 -> 332.5 | Z72: 30 | AA72: =IFERROR(Tableau1[[#This Row],[Taxe foncière €/m²]]*Tableau1[[#This Row],[Surface GLA]],) -> 0 | AB72: / | AC72: =IFERROR(Tableau1[[#This Row],[Marketing €/m²]]*Tableau1[[#This Row],[Surface GLA]],) -> 0 | AD72: / | AE72: =IFERROR(Tableau1[[#This Row],[Loyer annuel]]+Tableau1[[#This Row],[Charges annuelles]]+Tableau1[[#This Row],[Taxe foncière]]+Tableau1[[#This Row],[Marketing]],"") -> 47215 | AF72: ="3 mois = "&TEXT(ROUND(3/12*T72,0),"### ### ##0 €") -> 3 mois = 10 806 € | AG72: / | AH72: / | AI72: Brut de béton | AJ72: Oui | AK72: Chaude et froide | AL72: Basic Fit, Gifi, Lidl, Carrefour Market, Optical Center, Emjo, Perene, restaurants, coiffeur, centre de santé | AM72: Quartier neuf mixte. 40 000 m² de bureaux commercialisés. Nouveau siège de Lidl France. Les charges incluent la taxe foncière | AO72: 30% du loyer facial avec un minimum de 15 000 € HT | AP72: 48.762731 | AQ72: 2.288117 | AR72: 21.6 | AS72: https://pub-843c46afc4cb41489909bce00c9b143d.r2.dev/21.1%20-%20Ch%C3%A2tenay-Malabry/1%20Vue%20d'ensemble.jpg; https://pub-843c46afc4cb41489909bce00c9b143d.r2.dev/21.1%20-%20Ch%C3%A2tenay-Malabry/2.jpg; https://pub-843c46afc4cb41489909bce00c9b143d.r2.dev/21.1%20-%20Ch%C3%A2tenay-Malabry/3%20Plan%20de%20masse.jpg; https://pub-843c46afc4cb41489909bce00c9b143d.r2.dev/21.6%20-%20Ch%C3%A2tenay-Malabry/4.jpg | AT72: Oui | AU72: Au BP | AV72: Altixia
A73: =VLOOKUP(Tableau1[[#This Row],[N° Département]],Feuil1!$C$6:$E$106,3) -> Ile-de-France | B73: =VLOOKUP(Tableau1[[#This Row],[N° Département]],Feuil1!$C$6:$E$106,2) -> Hauts-de-Seine | C73: =LEFT(Tableau1[[#This Row],[Code Postal]],2)*1 -> 92 | D73: Cours du Commerce | E73: 92290 | F73: Châtenay-Malabry | G73: =Tableau1[[#This Row],[Rue]]&CHAR(10)&Tableau1[[#This Row],[Code Postal]]&" - "&Tableau1[[#This Row],[Ville]] -> Cours du Commerce 92290 - Châtenay-Malabry | H73: https://maps.app.goo.gl/UFPwUo755xa7tVqYA | I73: Centre Ville | J73: Pied d'immeuble | K73: / | M73: / | N73: P3 | O73: 341 | P73: / | Q73: / | R73: / | S73: / | T73: =Tableau1[[#This Row],[Loyer €/m²]]*Tableau1[[#This Row],[Surface GLA]] -> 119350 | U73: =IFERROR(Tableau1[[#This Row],[Loyer annuel]]/12,"") -> 9945.8333 | V73: 350 | W73: / | X73: =Tableau1[[#This Row],[Charges €/m²]]*Tableau1[[#This Row],[Surface GLA]] -> 10230 | Y73: =Tableau1[[#This Row],[Charges annuelles]]/12 -> 852.5 | Z73: 30 | AA73: =IFERROR(Tableau1[[#This Row],[Taxe foncière €/m²]]*Tableau1[[#This Row],[Surface GLA]],) -> 0 | AB73: / | AC73: =IFERROR(Tableau1[[#This Row],[Marketing €/m²]]*Tableau1[[#This Row],[Surface GLA]],) -> 0 | AD73: / | AE73: =IFERROR(Tableau1[[#This Row],[Loyer annuel]]+Tableau1[[#This Row],[Charges annuelles]]+Tableau1[[#This Row],[Taxe foncière]]+Tableau1[[#This Row],[Marketing]],"") -> 129580 | AF73: ="3 mois = "&TEXT(ROUND(3/12*T73,0),"### ### ##0 €") -> 3 mois = 29 838 € | AG73: / | AH73: / | AI73: Brut de béton | AJ73: Oui | AK73: Chaude et froide | AL73: Basic Fit, Gifi, Lidl, Carrefour Market, Optical Center, Emjo, Perene, restaurants, coiffeur, centre de santé | AM73: Quartier neuf mixte. 40 000 m² de bureaux commercialisés. Nouveau siège de Lidl France. Les charges incluent la taxe foncière | AO73: 30% du loyer facial avec un minimum de 15 000 € HT | AP73: 48.762632 | AQ73: 2.288876 | AR73: 21.7 | AS73: https://pub-843c46afc4cb41489909bce00c9b143d.r2.dev/21.1%20-%20Ch%C3%A2tenay-Malabry/1%20Vue%20d'ensemble.jpg; https://pub-843c46afc4cb41489909bce00c9b143d.r2.dev/21.1%20-%20Ch%C3%A2tenay-Malabry/2.jpg; https://pub-843c46afc4cb41489909bce00c9b143d.r2.dev/21.1%20-%20Ch%C3%A2tenay-Malabry/3%20Plan%20de%20masse.jpg; https://pub-843c46afc4cb41489909bce00c9b143d.r2.dev/21.7%20-%20Ch%C3%A2tenay-Malabry/4.jpg; https://pub-843c46afc4cb41489909bce00c9b143d.r2.dev/21.7%20-%20Ch%C3%A2tenay-Malabry/5.jpg | AT73: Oui | AU73: Au BP | AV73: Altixia
A74: =VLOOKUP(Tableau1[[#This Row],[N° Département]],Feuil1!$C$6:$E$106,3) -> Ile-de-France | B74: =VLOOKUP(Tableau1[[#This Row],[N° Département]],Feuil1!$C$6:$E$106,2) -> Hauts-de-Seine | C74: =LEFT(Tableau1[[#This Row],[Code Postal]],2)*1 -> 92 | D74: Cours du Commerce | E74: 92290 | F74: Châtenay-Malabry | G74: =Tableau1[[#This Row],[Rue]]&CHAR(10)&Tableau1[[#This Row],[Code Postal]]&" - "&Tableau1[[#This Row],[Ville]] -> Cours du Commerce 92290 - Châtenay-Malabry | H74: https://maps.app.goo.gl/Uu7o9RHGMfsXKgKS9 | I74: Centre Ville | J74: Pied d'immeuble | K74: / | M74: / | N74: P4 | O74: 444 | P74: / | Q74: / | R74: / | S74: / | T74: =Tableau1[[#This Row],[Loyer €/m²]]*Tableau1[[#This Row],[Surface GLA]] -> 155400 | U74: =IFERROR(Tableau1[[#This Row],[Loyer annuel]]/12,"") -> 12950 | V74: 350 | W74: / | X74: =Tableau1[[#This Row],[Charges €/m²]]*Tableau1[[#This Row],[Surface GLA]] -> 13320 | Y74: =Tableau1[[#This Row],[Charges annuelles]]/12 -> 1110 | Z74: 30 | AA74: =IFERROR(Tableau1[[#This Row],[Taxe foncière €/m²]]*Tableau1[[#This Row],[Surface GLA]],) -> 0 | AB74: / | AC74: =IFERROR(Tableau1[[#This Row],[Marketing €/m²]]*Tableau1[[#This Row],[Surface GLA]],) -> 0 | AD74: / | AE74: =IFERROR(Tableau1[[#This Row],[Loyer annuel]]+Tableau1[[#This Row],[Charges annuelles]]+Tableau1[[#This Row],[Taxe foncière]]+Tableau1[[#This Row],[Marketing]],"") -> 168720 | AF74: ="3 mois = "&TEXT(ROUND(3/12*T74,0),"### ### ##0 €") -> 3 mois = 38 850 € | AG74: / | AH74: / | AI74: Brut de béton | AJ74: Oui | AK74: Chaude et froide | AL74: Basic Fit, Gifi, Lidl, Carrefour Market, Optical Center, Emjo, Perene, restaurants, coiffeur, centre de santé | AM74: Quartier neuf mixte. 40 000 m² de bureaux commercialisés. Nouveau siège de Lidl France. Les charges incluent la taxe foncière | AO74: 30% du loyer facial avec un minimum de 15 000 € HT | AP74: 48.762201 | AQ74: 2.289236 | AR74: 21.8 | AS74: https://pub-843c46afc4cb41489909bce00c9b143d.r2.dev/21.1%20-%20Ch%C3%A2tenay-Malabry/1%20Vue%20d'ensemble.jpg; https://pub-843c46afc4cb41489909bce00c9b143d.r2.dev/21.1%20-%20Ch%C3%A2tenay-Malabry/2.jpg; https://pub-843c46afc4cb41489909bce00c9b143d.r2.dev/21.1%20-%20Ch%C3%A2tenay-Malabry/3%20Plan%20de%20masse.jpg; https://pub-843c46afc4cb41489909bce00c9b143d.r2.dev/21.8%20-%20Ch%C3%A2tenay-Malabry/4.jpg; https://pub-843c46afc4cb41489909bce00c9b143d.r2.dev/21.8%20-%20Ch%C3%A2tenay-Malabry/5.jpg | AT74: Oui | AU74: Au BP | AV74: Altixia
A75: =VLOOKUP(Tableau1[[#This Row],[N° Département]],Feuil1!$C$6:$E$106,3) -> Ile-de-France | B75: =VLOOKUP(Tableau1[[#This Row],[N° Département]],Feuil1!$C$6:$E$106,2) -> Hauts-de-Seine | C75: =LEFT(Tableau1[[#This Row],[Code Postal]],2)*1 -> 92 | D75: Cours du Commerce | E75: 92290 | F75: Châtenay-Malabry | G75: =Tableau1[[#This Row],[Rue]]&CHAR(10)&Tableau1[[#This Row],[Code Postal]]&" - "&Tableau1[[#This Row],[Ville]] -> Cours du Commerce 92290 - Châtenay-Malabry | H75: https://maps.app.goo.gl/sQqVfKSNDubT4wGy5 | I75: Centre Ville | J75: Pied d'immeuble | K75: / | M75: / | N75: P4.5A | O75: 206 | P75: / | Q75: / | R75: / | S75: / | T75: =Tableau1[[#This Row],[Loyer €/m²]]*Tableau1[[#This Row],[Surface GLA]] -> 72100 | U75: =IFERROR(Tableau1[[#This Row],[Loyer annuel]]/12,"") -> 6008.3333 | V75: 350 | W75: / | X75: =Tableau1[[#This Row],[Charges €/m²]]*Tableau1[[#This Row],[Surface GLA]] -> 6180 | Y75: =Tableau1[[#This Row],[Charges annuelles]]/12 -> 515 | Z75: 30 | AA75: =IFERROR(Tableau1[[#This Row],[Taxe foncière €/m²]]*Tableau1[[#This Row],[Surface GLA]],) -> 0 | AB75: / | AC75: =IFERROR(Tableau1[[#This Row],[Marketing €/m²]]*Tableau1[[#This Row],[Surface GLA]],) -> 0 | AD75: / | AE75: =IFERROR(Tableau1[[#This Row],[Loyer annuel]]+Tableau1[[#This Row],[Charges annuelles]]+Tableau1[[#This Row],[Taxe foncière]]+Tableau1[[#This Row],[Marketing]],"") -> 78280 | AF75: ="3 mois = "&TEXT(ROUND(3/12*T75,0),"### ### ##0 €") -> 3 mois = 18 025 € | AG75: / | AH75: / | AI75: Brut de béton | AJ75: Oui | AK75: Chaude et froide | AL75: Basic Fit, Gifi, Lidl, Carrefour Market, Optical Center, Emjo, Perene, restaurants, coiffeur, centre de santé | AM75: Quartier neuf mixte. 40 000 m² de bureaux commercialisés. Nouveau siège de Lidl France. Les charges incluent la taxe foncière | AO75: 30% du loyer facial avec un minimum de 15 000 € HT | AP75: 48.761981 | AQ75: 2.289442 | AR75: 21.9 | AS75: https://pub-843c46afc4cb41489909bce00c9b143d.r2.dev/21.1%20-%20Ch%C3%A2tenay-Malabry/1%20Vue%20d'ensemble.jpg; https://pub-843c46afc4cb41489909bce00c9b143d.r2.dev/21.1%20-%20Ch%C3%A2tenay-Malabry/2.jpg; https://pub-843c46afc4cb41489909bce00c9b143d.r2.dev/21.1%20-%20Ch%C3%A2tenay-Malabry/3%20Plan%20de%20masse.jpg; https://pub-843c46afc4cb41489909bce00c9b143d.r2.dev/21.9%20-%20Ch%C3%A2tenay-Malabry/4.jpg | AT75: Oui | AU75: Au BP | AV75: Altixia
A76: =VLOOKUP(Tableau1[[#This Row],[N° Département]],Feuil1!$C$6:$E$106,3) -> Ile-de-France | B76: =VLOOKUP(Tableau1[[#This Row],[N° Département]],Feuil1!$C$6:$E$106,2) -> Hauts-de-Seine | C76: =LEFT(Tableau1[[#This Row],[Code Postal]],2)*1 -> 92 | D76: Cours du Commerce | E76: 92290 | F76: Châtenay-Malabry | G76: =Tableau1[[#This Row],[Rue]]&CHAR(10)&Tableau1[[#This Row],[Code Postal]]&" - "&Tableau1[[#This Row],[Ville]] -> Cours du Commerce 92290 - Châtenay-Malabry | H76: https://maps.app.goo.gl/Wgcg9ZVPkw8KPksN8 | I76: Centre Ville | J76: Pied d'immeuble | K76: / | M76: / | N76: P4 Com.6 | O76: 231 | P76: / | Q76: / | R76: / | S76: / | T76: =Tableau1[[#This Row],[Loyer €/m²]]*Tableau1[[#This Row],[Surface GLA]] -> 92400 | U76: =IFERROR(Tableau1[[#This Row],[Loyer annuel]]/12,"") -> 7700 | V76: 400 | W76: / | X76: =Tableau1[[#This Row],[Charges €/m²]]*Tableau1[[#This Row],[Surface GLA]] -> 6930 | Y76: =Tableau1[[#This Row],[Charges annuelles]]/12 -> 577.5 | Z76: 30 | AA76: =IFERROR(Tableau1[[#This Row],[Taxe foncière €/m²]]*Tableau1[[#This Row],[Surface GLA]],) -> 0 | AB76: / | AC76: =IFERROR(Tableau1[[#This Row],[Marketing €/m²]]*Tableau1[[#This Row],[Surface GLA]],) -> 0 | AD76: / | AE76: =IFERROR(Tableau1[[#This Row],[Loyer annuel]]+Tableau1[[#This Row],[Charges annuelles]]+Tableau1[[#This Row],[Taxe foncière]]+Tableau1[[#This Row],[Marketing]],"") -> 99330 | AF76: ="3 mois = "&TEXT(ROUND(3/12*T76,0),"### ### ##0 €") -> 3 mois = 23 100 € | AG76: / | AH76: / | AI76: Brut de béton | AJ76: Oui | AK76: Chaude et froide | AL76: Basic Fit, Gifi, Lidl, Carrefour Market, Optical Center, Emjo, Perene, restaurants, coiffeur, centre de santé | AM76: Quartier neuf mixte. 40 000 m² de bureaux commercialisés. Nouveau siège de Lidl France. Les charges incluent la taxe foncière | AO76: 30% du loyer facial avec un minimum de 15 000 € HT | AP76: 48.761762 | AQ76: 2.289501 | AR76: 21.10 | AS76: https://pub-843c46afc4cb41489909bce00c9b143d.r2.dev/21.1%20-%20Ch%C3%A2tenay-Malabry/1%20Vue%20d'ensemble.jpg; https://pub-843c46afc4cb41489909bce00c9b143d.r2.dev/21.1%20-%20Ch%C3%A2tenay-Malabry/2.jpg; https://pub-843c46afc4cb41489909bce00c9b143d.r2.dev/21.1%20-%20Ch%C3%A2tenay-Malabry/3%20Plan%20de%20masse.jpg; https://pub-843c46afc4cb41489909bce00c9b143d.r2.dev/21.10%20-%20Ch%C3%A2tenay-Malabry/4.jpg; https://pub-843c46afc4cb41489909bce00c9b143d.r2.dev/21.10%20-%20Ch%C3%A2tenay-Malabry/5.jpg | AT76: Oui | AU76: Au BP | AV76: Altixia
A77: =VLOOKUP(Tableau1[[#This Row],[N° Département]],Feuil1!$C$6:$E$106,3) -> Ile-de-France | B77: =VLOOKUP(Tableau1[[#This Row],[N° Département]],Feuil1!$C$6:$E$106,2) -> Hauts-de-Seine | C77: =LEFT(Tableau1[[#This Row],[Code Postal]],2)*1 -> 92 | D77: Cours du Commerce | E77: 92290 | F77: Châtenay-Malabry | G77: =Tableau1[[#This Row],[Rue]]&CHAR(10)&Tableau1[[#This Row],[Code Postal]]&" - "&Tableau1[[#This Row],[Ville]] -> Cours du Commerce 92290 - Châtenay-Malabry | H77: https://maps.app.goo.gl/BRbRB8BHCUqZw3tw6 | I77: Centre Ville | J77: Pied d'immeuble | K77: / | M77: / | N77: P4 Act.1 | O77: 235 | P77: / | Q77: / | R77: / | S77: / | T77: =Tableau1[[#This Row],[Loyer €/m²]]*Tableau1[[#This Row],[Surface GLA]] -> 82250 | U77: =IFERROR(Tableau1[[#This Row],[Loyer annuel]]/12,"") -> 6854.1667 | V77: 350 | W77: / | X77: =Tableau1[[#This Row],[Charges €/m²]]*Tableau1[[#This Row],[Surface GLA]] -> 7050 | Y77: =Tableau1[[#This Row],[Charges annuelles]]/12 -> 587.5 | Z77: 30 | AA77: =IFERROR(Tableau1[[#This Row],[Taxe foncière €/m²]]*Tableau1[[#This Row],[Surface GLA]],) -> 0 | AB77: / | AC77: =IFERROR(Tableau1[[#This Row],[Marketing €/m²]]*Tableau1[[#This Row],[Surface GLA]],) -> 0 | AD77: / | AE77: =IFERROR(Tableau1[[#This Row],[Loyer annuel]]+Tableau1[[#This Row],[Charges annuelles]]+Tableau1[[#This Row],[Taxe foncière]]+Tableau1[[#This Row],[Marketing]],"") -> 89300 | AF77: ="3 mois = "&TEXT(ROUND(3/12*T77,0),"### ### ##0 €") -> 3 mois = 20 563 € | AG77: / | AH77: / | AI77: Brut de béton | AJ77: Oui | AK77: Chaude et froide | AL77: Basic Fit, Gifi, Lidl, Carrefour Market, Optical Center, Emjo, Perene, restaurants, coiffeur, centre de santé | AM77: Quartier neuf mixte. 40 000 m² de bureaux commercialisés. Nouveau siège de Lidl France. Les charges incluent la taxe foncière | AO77: 30% du loyer facial avec un minimum de 15 000 € HT | AP77: 48.761767 | AQ77: 2.289147 | AR77: 21.11 | AS77: https://pub-843c46afc4cb41489909bce00c9b143d.r2.dev/21.1%20-%20Ch%C3%A2tenay-Malabry/1%20Vue%20d'ensemble.jpg; https://pub-843c46afc4cb41489909bce00c9b143d.r2.dev/21.1%20-%20Ch%C3%A2tenay-Malabry/2.jpg; https://pub-843c46afc4cb41489909bce00c9b143d.r2.dev/21.1%20-%20Ch%C3%A2tenay-Malabry/3%20Plan%20de%20masse.jpg; https://pub-843c46afc4cb41489909bce00c9b143d.r2.dev/21.11%20-%20Ch%C3%A2tenay-Malabry/4.jpg | AT77: Oui | AU77: Au BP | AV77: Altixia
A78: =VLOOKUP(Tableau1[[#This Row],[N° Département]],Feuil1!$C$6:$E$106,3) -> Ile-de-France | B78: =VLOOKUP(Tableau1[[#This Row],[N° Département]],Feuil1!$C$6:$E$106,2) -> Hauts-de-Seine | C78: =LEFT(Tableau1[[#This Row],[Code Postal]],2)*1 -> 92 | D78: Cours du Commerce | E78: 92290 | F78: Châtenay-Malabry | G78: =Tableau1[[#This Row],[Rue]]&CHAR(10)&Tableau1[[#This Row],[Code Postal]]&" - "&Tableau1[[#This Row],[Ville]] -> Cours du Commerce 92290 - Châtenay-Malabry | H78: https://maps.app.goo.gl/icDCmPg1Rg6epARE7 | I78: Centre Ville | J78: Pied d'immeuble | K78: / | M78: / | N78: R2 | O78: 333 | P78: / | Q78: / | R78: / | S78: / | T78: =Tableau1[[#This Row],[Loyer €/m²]]*Tableau1[[#This Row],[Surface GLA]] -> 108225 | U78: =IFERROR(Tableau1[[#This Row],[Loyer annuel]]/12,"") -> 9018.75 | V78: 325 | W78: / | X78: =Tableau1[[#This Row],[Charges €/m²]]*Tableau1[[#This Row],[Surface GLA]] -> 9990 | Y78: =Tableau1[[#This Row],[Charges annuelles]]/12 -> 832.5 | Z78: 30 | AA78: =IFERROR(Tableau1[[#This Row],[Taxe foncière €/m²]]*Tableau1[[#This Row],[Surface GLA]],) -> 0 | AB78: / | AC78: =IFERROR(Tableau1[[#This Row],[Marketing €/m²]]*Tableau1[[#This Row],[Surface GLA]],) -> 0 | AD78: / | AE78: =IFERROR(Tableau1[[#This Row],[Loyer annuel]]+Tableau1[[#This Row],[Charges annuelles]]+Tableau1[[#This Row],[Taxe foncière]]+Tableau1[[#This Row],[Marketing]],"") -> 118215 | AF78: ="3 mois = "&TEXT(ROUND(3/12*T78,0),"### ### ##0 €") -> 3 mois = 27 056 € | AG78: / | AH78: / | AI78: Brut de béton | AJ78: Oui | AK78: Chaude et froide | AL78: Basic Fit, Gifi, Lidl, Carrefour Market, Optical Center, Emjo, Perene, restaurants, coiffeur, centre de santé | AM78: Quartier neuf mixte. 40 000 m² de bureaux commercialisés. Nouveau siège de Lidl France. Les charges incluent la taxe foncière | AO78: 30% du loyer facial avec un minimum de 15 000 € HT | AP78: 48.764732 | AQ78: 2.287726 | AR78: 21.12 | AS78: https://pub-843c46afc4cb41489909bce00c9b143d.r2.dev/21.1%20-%20Ch%C3%A2tenay-Malabry/1%20Vue%20d'ensemble.jpg; https://pub-843c46afc4cb41489909bce00c9b143d.r2.dev/21.1%20-%20Ch%C3%A2tenay-Malabry/2.jpg; https://pub-843c46afc4cb41489909bce00c9b143d.r2.dev/21.1%20-%20Ch%C3%A2tenay-Malabry/3%20Plan%20de%20masse.jpg; https://pub-843c46afc4cb41489909bce00c9b143d.r2.dev/21.12%20-%20Ch%C3%A2tenay-Malabry/4.jpg | AT78: Oui | AU78: Au BP | AV78: Altixia
... A89: =VLOOKUP(Tableau1[[#This Row],[N° Département]],Feuil1!$C$6:$E$106,3) -> Ile-de-France | B89: =VLOOKUP(Tableau1[[#This Row],[N° Département]],Feuil1!$C$6:$E$106,2) -> Hauts-de-Seine | C89: =LEFT(Tableau1[[#This Row],[Code Postal]],2)*1 -> 92 | D89: Cours du Commerce | E89: 92290 | F89: Châtenay-Malabry | G89: =Tableau1[[#This Row],[Rue]]&CHAR(10)&Tableau1[[#This Row],[Code Postal]]&" - "&Tableau1[[#This Row],[Ville]] -> Cours du Commerce 92290 - Châtenay-Malabry | H89: https://maps.app.goo.gl/GbjLcfXKvoPHqUjX6 | I89: Centre Ville | J89: Pied d'immeuble | K89: / | M89: / | N89: I4 | O89: 88 | P89: / | Q89: / | R89: / | S89: / | T89: =Tableau1[[#This Row],[Loyer €/m²]]*Tableau1[[#This Row],[Surface GLA]] -> 28600 | U89: =IFERROR(Tableau1[[#This Row],[Loyer annuel]]/12,"") -> 2383.3333 | V89: 325 | W89: / | X89: =Tableau1[[#This Row],[Charges €/m²]]*Tableau1[[#This Row],[Surface GLA]] -> 2640 | Y89: =Tableau1[[#This Row],[Charges annuelles]]/12 -> 220 | Z89: 30 | AA89: =IFERROR(Tableau1[[#This Row],[Taxe foncière €/m²]]*Tableau1[[#This Row],[Surface GLA]],) -> 0 | AB89: / | AC89: =IFERROR(Tableau1[[#This Row],[Marketing €/m²]]*Tableau1[[#This Row],[Surface GLA]],) -> 0 | AD89: / | AE89: =IFERROR(Tableau1[[#This Row],[Loyer annuel]]+Tableau1[[#This Row],[Charges annuelles]]+Tableau1[[#This Row],[Taxe foncière]]+Tableau1[[#This Row],[Marketing]],"") -> 31240 | AF89: ="3 mois = "&TEXT(ROUND(3/12*T89,0),"### ### ##0 €") -> 3 mois = 7 150 € | AG89: / | AH89: / | AI89: Brut de béton | AJ89: Oui | AK89: Chaude et froide | AL89: Basic Fit, Gifi, Lidl, Carrefour Market, Optical Center, Emjo, Perene, restaurants, coiffeur, centre de santé | AM89: Quartier neuf mixte. 40 000 m² de bureaux commercialisés. Nouveau siège de Lidl France. Les charges incluent la taxe foncière | AO89: 30% du loyer facial avec un minimum de 15 000 € HT | AP89: 48.763898 | AQ89: 2.290236 | AR89: 21.23 | AS89: https://pub-843c46afc4cb41489909bce00c9b143d.r2.dev/21.1%20-%20Ch%C3%A2tenay-Malabry/1%20Vue%20d'ensemble.jpg; https://pub-843c46afc4cb41489909bce00c9b143d.r2.dev/21.1%20-%20Ch%C3%A2tenay-Malabry/2.jpg; https://pub-843c46afc4cb41489909bce00c9b143d.r2.dev/21.1%20-%20Ch%C3%A2tenay-Malabry/3%20Plan%20de%20masse.jpg; https://pub-843c46afc4cb41489909bce00c9b143d.r2.dev/21.23%20-%20Ch%C3%A2tenay-Malabry/4.jpg | AT89: Oui | AU89: Au BP | AV89: Altixia
A90: =VLOOKUP(Tableau1[[#This Row],[N° Département]],Feuil1!$C$6:$E$106,3) -> Ile-de-France | B90: =VLOOKUP(Tableau1[[#This Row],[N° Département]],Feuil1!$C$6:$E$106,2) -> Hauts-de-Seine | C90: =LEFT(Tableau1[[#This Row],[Code Postal]],2)*1 -> 92 | D90: 30 Rue de la Ronce | E90: 92410 | F90: Ville-d'Avray | G90: =Tableau1[[#This Row],[Rue]]&CHAR(10)&Tableau1[[#This Row],[Code Postal]]&" - "&Tableau1[[#This Row],[Ville]] -> 30 Rue de la Ronce 92410 - Ville-d'Avray | H90: https://www.google.com/maps/place/30+Rue+de+la+Ronce,+92410+Ville-d'Avray | I90: Centre Ville | J90: Pied d'immeuble | K90: / | M90: / | N90: 1 | O90: 372 | P90: / | Q90: 533 | R90: / | S90: / | T90: =Tableau1[[#This Row],[Loyer €/m²]]*Tableau1[[#This Row],[Surface GLA]] -> 69936 | U90: =IFERROR(Tableau1[[#This Row],[Loyer annuel]]/12,"") -> 5828 | V90: 188 | W90: / | X90: =Tableau1[[#This Row],[Charges €/m²]]*Tableau1[[#This Row],[Surface GLA]] -> 3720 | Y90: =Tableau1[[#This Row],[Charges annuelles]]/12 -> 310 | Z90: 10 | AA90: =IFERROR(Tableau1[[#This Row],[Taxe foncière €/m²]]*Tableau1[[#This Row],[Surface GLA]],) -> 5952 | AB90: 16 | AC90: =IFERROR(Tableau1[[#This Row],[Marketing €/m²]]*Tableau1[[#This Row],[Surface GLA]],) -> 0 | AD90: / | AE90: =IFERROR(Tableau1[[#This Row],[Loyer annuel]]+Tableau1[[#This Row],[Charges annuelles]]+Tableau1[[#This Row],[Taxe foncière]]+Tableau1[[#This Row],[Marketing]],"") -> 79608 | AF90: / | AG90: / | AH90: / | AI90: Brut de béton | AJ90: Oui | AK90: Chaude et froide | AL90: Boulangerie, Franprix | AM90: 250k de flux par an. 15 000 personnes dans une zone de chalandise de 15 minutes à pied. Dans un ensemble de 125 logements privés allant du T2 au T5, avec une moyenne de 3,5 personnes/foyer. 2 200 logements privés à proximité. | AO90: 30% du loyer facial avec un minimum de 15 000 € HT | AP90: 48.822274 | AQ90: 2.189029 | AR90: 22.1 | AS90: https://pub-843c46afc4cb41489909bce00c9b143d.r2.dev/22.1%20-%20Ville-d'Avray/1%20Vu%20d'ensemble.jpg; https://pub-843c46afc4cb41489909bce00c9b143d.r2.dev/22.1%20-%20Ville-d'Avray/2%20Plan%20d'ensemble.jpg; https://pub-843c46afc4cb41489909bce00c9b143d.r2.dev/22.1%20-%20Ville-d'Avray/3%20Plan%20d'ensemble%20-%20Fusion%201%2B2%2B3.jpg; https://pub-843c46afc4cb41489909bce00c9b143d.r2.dev/22.1%20-%20Ville-d'Avray/4%20.jpg; https://pub-843c46afc4cb41489909bce00c9b143d.r2.dev/22.1%20-%20Ville-d'Avray/5%20Plan.jpg | AT90: Oui | AU90: Au BP | AV90: Gecina
A91: =VLOOKUP(Tableau1[[#This Row],[N° Département]],Feuil1!$C$6:$E$106,3) -> Ile-de-France | B91: =VLOOKUP(Tableau1[[#This Row],[N° Département]],Feuil1!$C$6:$E$106,2) -> Hauts-de-Seine | C91: =LEFT(Tableau1[[#This Row],[Code Postal]],2)*1 -> 92 | D91: 30 Rue de la Ronce | E91: 92410 | F91: Ville-d'Avray | G91: =Tableau1[[#This Row],[Rue]]&CHAR(10)&Tableau1[[#This Row],[Code Postal]]&" - "&Tableau1[[#This Row],[Ville]] -> 30 Rue de la Ronce 92410 - Ville-d'Avray | H91: https://www.google.com/maps/place/30+Rue+de+la+Ronce,+92410+Ville-d'Avray | I91: Centre Ville | J91: Pied d'immeuble | K91: / | M91: / | N91: 2 | O91: 53 | P91: / | Q91: 533 | R91: / | S91: / | T91: =Tableau1[[#This Row],[Loyer €/m²]]*Tableau1[[#This Row],[Surface GLA]] -> 14840 | U91: =IFERROR(Tableau1[[#This Row],[Loyer annuel]]/12,"") -> 1236.6667 | V91: 280 | W91: / | X91: =Tableau1[[#This Row],[Charges €/m²]]*Tableau1[[#This Row],[Surface GLA]] -> 530 | Y91: =Tableau1[[#This Row],[Charges annuelles]]/12 -> 44.166667 | Z91: 10 | AA91: =IFERROR(Tableau1[[#This Row],[Taxe foncière €/m²]]*Tableau1[[#This Row],[Surface GLA]],) -> 848 | AB91: 16 | AC91: =IFERROR(Tableau1[[#This Row],[Marketing €/m²]]*Tableau1[[#This Row],[Surface GLA]],) -> 0 | AD91: / | AE91: =IFERROR(Tableau1[[#This Row],[Loyer annuel]]+Tableau1[[#This Row],[Charges annuelles]]+Tableau1[[#This Row],[Taxe foncière]]+Tableau1[[#This Row],[Marketing]],"") -> 16218 | AF91: / | AG91: / | AH91: / | AI91: Brut de béton | AJ91: Non | AK91: Froide | AL91: Boulangerie, Franprix | AM91: 250k de flux par an. 15 000 personnes dans une zone de chalandise de 15 minutes à pied. Dans un ensemble de 125 logements privés allant du T2 au T5, avec une moyenne de 3,5 personnes/foyer. 2 200 logements privés à proximité. | AO91: 30% du loyer facial avec un minimum de 15 000 € HT | AP91: 48.822302 | AQ91: 2.189139 | AR91: 22.2 | AS91: https://pub-843c46afc4cb41489909bce00c9b143d.r2.dev/22.1%20-%20Ville-d'Avray/1%20Vu%20d'ensemble.jpg; https://pub-843c46afc4cb41489909bce00c9b143d.r2.dev/22.1%20-%20Ville-d'Avray/2%20Plan%20d'ensemble.jpg; https://pub-843c46afc4cb41489909bce00c9b143d.r2.dev/22.1%20-%20Ville-d'Avray/3%20Plan%20d'ensemble%20-%20Fusion%201%2B2%2B3.jpg; https://pub-843c46afc4cb41489909bce00c9b143d.r2.dev/22.2%20-%20Ville-d'Avray/4.jpg; https://pub-843c46afc4cb41489909bce00c9b143d.r2.dev/22.2%20-%20Ville-d'Avray/5%20Plan.jpg | AT91: Oui | AU91: Au BP | AV91: Gecina
A92: =VLOOKUP(Tableau1[[#This Row],[N° Département]],Feuil1!$C$6:$E$106,3) -> Ile-de-France | B92: =VLOOKUP(Tableau1[[#This Row],[N° Département]],Feuil1!$C$6:$E$106,2) -> Hauts-de-Seine | C92: =LEFT(Tableau1[[#This Row],[Code Postal]],2)*1 -> 92 | D92: 30 Rue de la Ronce | E92: 92410 | F92: Ville-d'Avray | G92: =Tableau1[[#This Row],[Rue]]&CHAR(10)&Tableau1[[#This Row],[Code Postal]]&" - "&Tableau1[[#This Row],[Ville]] -> 30 Rue de la Ronce 92410 - Ville-d'Avray | H92: https://www.google.com/maps/place/30+Rue+de+la+Ronce,+92410+Ville-d'Avray | I92: Centre Ville | J92: Pied d'immeuble | K92: / | M92: / | N92: 3 | O92: 108 | P92: / | Q92: 533 | R92: / | S92: / | T92: =Tableau1[[#This Row],[Loyer €/m²]]*Tableau1[[#This Row],[Surface GLA]] -> 31968 | U92: =IFERROR(Tableau1[[#This Row],[Loyer annuel]]/12,"") -> 2664 | V92: 296 | W92: / | X92: =Tableau1[[#This Row],[Charges €/m²]]*Tableau1[[#This Row],[Surface GLA]] -> 1080 | Y92: =Tableau1[[#This Row],[Charges annuelles]]/12 -> 90 | Z92: 10 | AA92: =IFERROR(Tableau1[[#This Row],[Taxe foncière €/m²]]*Tableau1[[#This Row],[Surface GLA]],) -> 1728 | AB92: 16 | AC92: =IFERROR(Tableau1[[#This Row],[Marketing €/m²]]*Tableau1[[#This Row],[Surface GLA]],) -> 0 | AD92: / | AE92: =IFERROR(Tableau1[[#This Row],[Loyer annuel]]+Tableau1[[#This Row],[Charges annuelles]]+Tableau1[[#This Row],[Taxe foncière]]+Tableau1[[#This Row],[Marketing]],"") -> 34776 | AF92: / | AG92: / | AH92: / | AI92: Brut de béton | AJ92: Non | AK92: Froide | AL92: Boulangerie, Franprix | AM92: 250k de flux par an. 15 000 personnes dans une zone de chalandise de 15 minutes à pied. Dans un ensemble de 125 logements privés allant du T2 au T5, avec une moyenne de 3,5 personnes/foyer. 2 200 logements privés à proximité. | AO92: 30% du loyer facial avec un minimum de 15 000 € HT | AP92: 48.822321 | AQ92: 2.189262 | AR92: 22.3 | AS92: https://pub-843c46afc4cb41489909bce00c9b143d.r2.dev/22.1%20-%20Ville-d'Avray/1%20Vu%20d'ensemble.jpg; https://pub-843c46afc4cb41489909bce00c9b143d.r2.dev/22.1%20-%20Ville-d'Avray/2%20Plan%20d'ensemble.jpg; https://pub-843c46afc4cb41489909bce00c9b143d.r2.dev/22.1%20-%20Ville-d'Avray/3%20Plan%20d'ensemble%20-%20Fusion%201%2B2%2B3.jpg; https://pub-843c46afc4cb41489909bce00c9b143d.r2.dev/22.3%20-%20Ville-d'Avray/4.jpg; https://pub-843c46afc4cb41489909bce00c9b143d.r2.dev/22.3%20-%20Ville-d'Avray/5%20Plan.jpg | AT92: Oui | AU92: Au BP | AV92: Gecina
A93: =VLOOKUP(Tableau1[[#This Row],[N° Département]],Feuil1!$C$6:$E$106,3) -> Ile-de-France | B93: =VLOOKUP(Tableau1[[#This Row],[N° Département]],Feuil1!$C$6:$E$106,2) -> Hauts-de-Seine | C93: =LEFT(Tableau1[[#This Row],[Code Postal]],2)*1 -> 92 | D93: 30 Rue de la Ronce | E93: 92410 | F93: Ville-d'Avray | G93: =Tableau1[[#This Row],[Rue]]&CHAR(10)&Tableau1[[#This Row],[Code Postal]]&" - "&Tableau1[[#This Row],[Ville]] -> 30 Rue de la Ronce 92410 - Ville-d'Avray | H93: https://www.google.com/maps/place/30+Rue+de+la+Ronce,+92410+Ville-d'Avray | I93: Centre Ville | J93: Pied d'immeuble | K93: / | M93: / | N93: 4 | O93: 424 | P93: / | Q93: 1381 | R93: / | S93: / | T93: =Tableau1[[#This Row],[Loyer €/m²]]*Tableau1[[#This Row],[Surface GLA]] -> 86920 | U93: =IFERROR(Tableau1[[#This Row],[Loyer annuel]]/12,"") -> 7243.3333 | V93: 205 | W93: / | X93: =Tableau1[[#This Row],[Charges €/m²]]*Tableau1[[#This Row],[Surface GLA]] -> 4240 | Y93: =Tableau1[[#This Row],[Charges annuelles]]/12 -> 353.33333 | Z93: 10 | AA93: =IFERROR(Tableau1[[#This Row],[Taxe foncière €/m²]]*Tableau1[[#This Row],[Surface GLA]],) -> 6784 | AB93: 16 | AC93: =IFERROR(Tableau1[[#This Row],[Marketing €/m²]]*Tableau1[[#This Row],[Surface GLA]],) -> 0 | AD93: / | AE93: =IFERROR(Tableau1[[#This Row],[Loyer annuel]]+Tableau1[[#This Row],[Charges annuelles]]+Tableau1[[#This Row],[Taxe foncière]]+Tableau1[[#This Row],[Marketing]],"") -> 97944 | AF93: / | AG93: / | AH93: / | AI93: Brut de béton | AJ93: Non | AK93: Froide | AL93: Boulangerie, Franprix | AM93: 250k de flux par an. 15 000 personnes dans une zone de chalandise de 15 minutes à pied. Dans un ensemble de 125 logements privés allant du T2 au T5, avec une moyenne de 3,5 personnes/foyer. 2 200 logements privés à proximité. | AO93: 30% du loyer facial avec un minimum de 15 000 € HT | AP93: 48.822302 | AQ93: 2.189538 | AR93: 22.4 | AS93: https://pub-843c46afc4cb41489909bce00c9b143d.r2.dev/22.1%20-%20Ville-d'Avray/1%20Vu%20d'ensemble.jpg; https://pub-843c46afc4cb41489909bce00c9b143d.r2.dev/22.1%20-%20Ville-d'Avray/2%20Plan%20d'ensemble.jpg; https://pub-843c46afc4cb41489909bce00c9b143d.r2.dev/22.4%20-%20Ville-d'Avray/3%20Plan%20d'ensemble%20-%20Fusion%204%2B5.jpg; https://pub-843c46afc4cb41489909bce00c9b143d.r2.dev/22.4%20-%20Ville-d'Avray/4%20Plan%20d'ensemble%20-%20Fusion%204%2B5%2B10.jpg; https://pub-843c46afc4cb41489909bce00c9b143d.r2.dev/22.4%20-%20Ville-d'Avray/5%20Plan%20d'ensemble%20-%20Fusion%204%2B5%2B10%2B6.jpg; https://pub-843c46afc4cb41489909bce00c9b143d.r2.dev/22.4%20-%20Ville-d'Avray/6.jpg; https://pub-843c46afc4cb41489909bce00c9b143d.r2.dev/22.4%20-%20Ville-d'Avray/7%20Plan.jpg | AT93: Non | AU93: Au BP | AV93: Gecina
A94: =VLOOKUP(Tableau1[[#This Row],[N° Département]],Feuil1!$C$6:$E$106,3) -> Ile-de-France | B94: =VLOOKUP(Tableau1[[#This Row],[N° Département]],Feuil1!$C$6:$E$106,2) -> Hauts-de-Seine | C94: =LEFT(Tableau1[[#This Row],[Code Postal]],2)*1 -> 92 | D94: 30 Rue de la Ronce | E94: 92410 | F94: Ville-d'Avray | G94: =Tableau1[[#This Row],[Rue]]&CHAR(10)&Tableau1[[#This Row],[Code Postal]]&" - "&Tableau1[[#This Row],[Ville]] -> 30 Rue de la Ronce 92410 - Ville-d'Avray | H94: https://www.google.com/maps/place/30+Rue+de+la+Ronce,+92410+Ville-d'Avray | I94: Centre Ville | J94: Pied d'immeuble | K94: / | M94: / | N94: 5 | O94: 258 | P94: / | Q94: 1381 | R94: / | S94: / | T94: =Tableau1[[#This Row],[Loyer €/m²]]*Tableau1[[#This Row],[Surface GLA]] -> 58050 | U94: =IFERROR(Tableau1[[#This Row],[Loyer annuel]]/12,"") -> 4837.5 | V94: 225 | W94: / | X94: =Tableau1[[#This Row],[Charges €/m²]]*Tableau1[[#This Row],[Surface GLA]] -> 2580 | Y94: =Tableau1[[#This Row],[Charges annuelles]]/12 -> 215 | Z94: 10 | AA94: =IFERROR(Tableau1[[#This Row],[Taxe foncière €/m²]]*Tableau1[[#This Row],[Surface GLA]],) -> 4128 | AB94: 16 | AC94: =IFERROR(Tableau1[[#This Row],[Marketing €/m²]]*Tableau1[[#This Row],[Surface GLA]],) -> 0 | AD94: / | AE94: =IFERROR(Tableau1[[#This Row],[Loyer annuel]]+Tableau1[[#This Row],[Charges annuelles]]+Tableau1[[#This Row],[Taxe foncière]]+Tableau1[[#This Row],[Marketing]],"") -> 64758 | AF94: / | AG94: / | AH94: / | AI94: Brut de béton | AJ94: Non | AK94: Froide | AL94: Boulangerie, Franprix | AM94: 250k de flux par an. 15 000 personnes dans une zone de chalandise de 15 minutes à pied. Dans un ensemble de 125 logements privés allant du T2 au T5, avec une moyenne de 3,5 personnes/foyer. 2 200 logements privés à proximité. | AO94: 30% du loyer facial avec un minimum de 15 000 € HT | AP94: 48.822327 | AQ94: 2.189656 | AR94: 22.5 | AS94: https://pub-843c46afc4cb41489909bce00c9b143d.r2.dev/22.1%20-%20Ville-d'Avray/1%20Vu%20d'ensemble.jpg; https://pub-843c46afc4cb41489909bce00c9b143d.r2.dev/22.1%20-%20Ville-d'Avray/2%20Plan%20d'ensemble.jpg; https://pub-843c46afc4cb41489909bce00c9b143d.r2.dev/22.4%20-%20Ville-d'Avray/3%20Plan%20d'ensemble%20-%20Fusion%204%2B5.jpg; https://pub-843c46afc4cb41489909bce00c9b143d.r2.dev/22.4%20-%20Ville-d'Avray/4%20Plan%20d'ensemble%20-%20Fusion%204%2B5%2B10.jpg; https://pub-843c46afc4cb41489909bce00c9b143d.r2.dev/22.4%20-%20Ville-d'Avray/5%20Plan%20d'ensemble%20-%20Fusion%204%2B5%2B10%2B6.jpg; https://pub-843c46afc4cb41489909bce00c9b143d.r2.dev/22.5%20-%20Ville-d'Avray/6.jpg; https://pub-843c46afc4cb41489909bce00c9b143d.r2.dev/22.5%20-%20Ville-d'Avray/7%20Plan.jpg | AT94: Non | AU94: Au BP | AV94: Gecina
A95: =VLOOKUP(Tableau1[[#This Row],[N° Département]],Feuil1!$C$6:$E$106,3) -> Ile-de-France | B95: =VLOOKUP(Tableau1[[#This Row],[N° Département]],Feuil1!$C$6:$E$106,2) -> Hauts-de-Seine | C95: =LEFT(Tableau1[[#This Row],[Code Postal]],2)*1 -> 92 | D95: 30 Rue de la Ronce | E95: 92410 | F95: Ville-d'Avray | G95: =Tableau1[[#This Row],[Rue]]&CHAR(10)&Tableau1[[#This Row],[Code Postal]]&" - "&Tableau1[[#This Row],[Ville]] -> 30 Rue de la Ronce 92410 - Ville-d'Avray | H95: https://www.google.com/maps/place/30+Rue+de+la+Ronce,+92410+Ville-d'Avray | I95: Centre Ville | J95: Pied d'immeuble | K95: / | M95: / | N95: 6 | O95: 152 | P95: / | Q95: 1381 | R95: / | S95: / | T95: =Tableau1[[#This Row],[Loyer €/m²]]*Tableau1[[#This Row],[Surface GLA]] -> 36024 | U95: =IFERROR(Tableau1[[#This Row],[Loyer annuel]]/12,"") -> 3002 | V95: 237 | W95: / | X95: =Tableau1[[#This Row],[Charges €/m²]]*Tableau1[[#This Row],[Surface GLA]] -> 1520 | Y95: =Tableau1[[#This Row],[Charges annuelles]]/12 -> 126.66667 | Z95: 10 | AA95: =IFERROR(Tableau1[[#This Row],[Taxe foncière €/m²]]*Tableau1[[#This Row],[Surface GLA]],) -> 2432 | AB95: 16 | AC95: =IFERROR(Tableau1[[#This Row],[Marketing €/m²]]*Tableau1[[#This Row],[Surface GLA]],) -> 0 | AD95: / | AE95: =IFERROR(Tableau1[[#This Row],[Loyer annuel]]+Tableau1[[#This Row],[Charges annuelles]]+Tableau1[[#This Row],[Taxe foncière]]+Tableau1[[#This Row],[Marketing]],"") -> 39976 | AF95: / | AG95: / | AH95: / | AI95: Brut de béton | AJ95: Non | AK95: Froide | AL95: Boulangerie, Franprix | AM95: 250k de flux par an. 15 000 personnes dans une zone de chalandise de 15 minutes à pied. Dans un ensemble de 125 logements privés allant du T2 au T5, avec une moyenne de 3,5 personnes/foyer. 2 200 logements privés à proximité. | AO95: 30% du loyer facial avec un minimum de 15 000 € HT | AP95: 48.822357 | AQ95: 2.189809 | AR95: 22.6 | AS95: https://pub-843c46afc4cb41489909bce00c9b143d.r2.dev/22.1%20-%20Ville-d'Avray/1%20Vu%20d'ensemble.jpg; https://pub-843c46afc4cb41489909bce00c9b143d.r2.dev/22.1%20-%20Ville-d'Avray/2%20Plan%20d'ensemble.jpg; https://pub-843c46afc4cb41489909bce00c9b143d.r2.dev/22.4%20-%20Ville-d'Avray/3%20Plan%20d'ensemble%20-%20Fusion%204%2B5.jpg; https://pub-843c46afc4cb41489909bce00c9b143d.r2.dev/22.4%20-%20Ville-d'Avray/4%20Plan%20d'ensemble%20-%20Fusion%204%2B5%2B10.jpg; https://pub-843c46afc4cb41489909bce00c9b143d.r2.dev/22.4%20-%20Ville-d'Avray/5%20Plan%20d'ensemble%20-%20Fusion%204%2B5%2B10%2B6.jpg; https://pub-843c46afc4cb41489909bce00c9b143d.r2.dev/22.6%20-%20Ville-d'Avray/6.jpg; https://pub-843c46afc4cb41489909bce00c9b143d.r2.dev/22.6%20-%20Ville-d'Avray/7%20Plan.jpg | AT95: Oui | AU95: Au BP | AV95: Gecina
A96: =VLOOKUP(Tableau1[[#This Row],[N° Département]],Feuil1!$C$6:$E$106,3) -> Ile-de-France | B96: =VLOOKUP(Tableau1[[#This Row],[N° Département]],Feuil1!$C$6:$E$106,2) -> Hauts-de-Seine | C96: =LEFT(Tableau1[[#This Row],[Code Postal]],2)*1 -> 92 | D96: 30 Rue de la Ronce | E96: 92410 | F96: Ville-d'Avray | G96: =Tableau1[[#This Row],[Rue]]&CHAR(10)&Tableau1[[#This Row],[Code Postal]]&" - "&Tableau1[[#This Row],[Ville]] -> 30 Rue de la Ronce 92410 - Ville-d'Avray | H96: https://www.google.com/maps/place/30+Rue+de+la+Ronce,+92410+Ville-d'Avray | I96: Centre Ville | J96: Pied d'immeuble | K96: / | M96: / | N96: 9 | O96: 105 | P96: / | Q96: / | R96: / | S96: / | T96: =Tableau1[[#This Row],[Loyer €/m²]]*Tableau1[[#This Row],[Surface GLA]] -> 30975 | U96: =IFERROR(Tableau1[[#This Row],[Loyer annuel]]/12,"") -> 2581.25 | V96: 295 | W96: / | X96: =Tableau1[[#This Row],[Charges €/m²]]*Tableau1[[#This Row],[Surface GLA]] -> 1050 | Y96: =Tableau1[[#This Row],[Charges annuelles]]/12 -> 87.5 | Z96: 10 | AA96: =IFERROR(Tableau1[[#This Row],[Taxe foncière €/m²]]*Tableau1[[#This Row],[Surface GLA]],) -> 1680 | AB96: 16 | AC96: =IFERROR(Tableau1[[#This Row],[Marketing €/m²]]*Tableau1[[#This Row],[Surface GLA]],) -> 0 | AD96: / | AE96: =IFERROR(Tableau1[[#This Row],[Loyer annuel]]+Tableau1[[#This Row],[Charges annuelles]]+Tableau1[[#This Row],[Taxe foncière]]+Tableau1[[#This Row],[Marketing]],"") -> 33705 | AF96: / | AG96: / | AH96: / | AI96: Brut de béton | AJ96: Non | AK96: Froide | AL96: Boulangerie, Franprix | AM96: 250k de flux par an. 15 000 personnes dans une zone de chalandise de 15 minutes à pied. Dans un ensemble de 125 logements privés allant du T2 au T5, avec une moyenne de 3,5 personnes/foyer. 2 200 logements privés à proximité. | AO96: 30% du loyer facial avec un minimum de 15 000 € HT | AP96: 48.822518 | AQ96: 2.190614 | AR96: 22.7 | AS96: https://pub-843c46afc4cb41489909bce00c9b143d.r2.dev/22.1%20-%20Ville-d'Avray/1%20Vu%20d'ensemble.jpg; https://pub-843c46afc4cb41489909bce00c9b143d.r2.dev/22.1%20-%20Ville-d'Avray/2%20Plan%20d'ensemble.jpg; https://pub-843c46afc4cb41489909bce00c9b143d.r2.dev/22.4%20-%20Ville-d'Avray/3%20Plan%20d'ensemble%20-%20Fusion%204%2B5.jpg; https://pub-843c46afc4cb41489909bce00c9b143d.r2.dev/22.4%20-%20Ville-d'Avray/4%20Plan%20d'ensemble%20-%20Fusion%204%2B5%2B10.jpg; https://pub-843c46afc4cb41489909bce00c9b143d.r2.dev/22.4%20-%20Ville-d'Avray/5%20Plan%20d'ensemble%20-%20Fusion%204%2B5%2B10%2B6.jpg; https://pub-843c46afc4cb41489909bce00c9b143d.r2.dev/22.7%20-%20Ville-d'Avray/6.jpghttps://pub-843c46afc4cb41489909bce00c9b143d.r2.dev/22.7%20-%20Ville-d'Avray/7%20Plan.jpg | AT96: Oui | AU96: Au BP | AV96: Gecina
A97: =VLOOKUP(Tableau1[[#This Row],[N° Département]],Feuil1!$C$6:$E$106,3) -> Ile-de-France | B97: =VLOOKUP(Tableau1[[#This Row],[N° Département]],Feuil1!$C$6:$E$106,2) -> Hauts-de-Seine | C97: =LEFT(Tableau1[[#This Row],[Code Postal]],2)*1 -> 92 | D97: 30 Rue de la Ronce | E97: 92411 | F97: Ville-d'Avray | G97: =Tableau1[[#This Row],[Rue]]&CHAR(10)&Tableau1[[#This Row],[Code Postal]]&" - "&Tableau1[[#This Row],[Ville]] -> 30 Rue de la Ronce 92411 - Ville-d'Avray | H97: https://www.google.com/maps/place/30+Rue+de+la+Ronce,+92410+Ville-d'Avray | I97: Centre Ville | J97: Pied d'immeuble | K97: / | M97: / | N97: 10 | O97: 547 | P97: / | Q97: 1381 | R97: / | S97: / | T97: =Tableau1[[#This Row],[Loyer €/m²]]*Tableau1[[#This Row],[Surface GLA]] -> 123075 | U97: =IFERROR(Tableau1[[#This Row],[Loyer annuel]]/12,"") -> 10256.25 | V97: 225 | W97: / | X97: =Tableau1[[#This Row],[Charges €/m²]]*Tableau1[[#This Row],[Surface GLA]] -> 5470 | Y97: =Tableau1[[#This Row],[Charges annuelles]]/12 -> 455.83333 | Z97: 10 | AA97: =IFERROR(Tableau1[[#This Row],[Taxe foncière €/m²]]*Tableau1[[#This Row],[Surface GLA]],) -> 8752 | AB97: 16 | AC97: =IFERROR(Tableau1[[#This Row],[Marketing €/m²]]*Tableau1[[#This Row],[Surface GLA]],) -> 0 | AD97: / | AE97: =IFERROR(Tableau1[[#This Row],[Loyer annuel]]+Tableau1[[#This Row],[Charges annuelles]]+Tableau1[[#This Row],[Taxe foncière]]+Tableau1[[#This Row],[Marketing]],"") -> 137297 | AF97: / | AG97: / | AH97: / | AI97: Brut de béton | AJ97: Non | AK97: Froide | AL97: Boulangerie, Franprix | AM97: 250k de flux par an. 15 000 personnes dans une zone de chalandise de 15 minutes à pied. Dans un ensemble de 125 logements privés allant du T2 au T5, avec une moyenne de 3,5 personnes/foyer. 2 200 logements privés à proximité. | AO97: 30% du loyer facial avec un minimum de 15 000 € HT | AP97: 48.822412 | AQ97: 2.190252 | AR97: 22.8 | AS97: https://pub-843c46afc4cb41489909bce00c9b143d.r2.dev/22.1%20-%20Ville-d'Avray/1%20Vu%20d'ensemble.jpg; https://pub-843c46afc4cb41489909bce00c9b143d.r2.dev/22.1%20-%20Ville-d'Avray/2%20Plan%20d'ensemble.jpg; https://pub-843c46afc4cb41489909bce00c9b143d.r2.dev/22.4%20-%20Ville-d'Avray/3%20Plan%20d'ensemble%20-%20Fusion%204%2B5.jpg; https://pub-843c46afc4cb41489909bce00c9b143d.r2.dev/22.4%20-%20Ville-d'Avray/4%20Plan%20d'ensemble%20-%20Fusion%204%2B5%2B10.jpg; https://pub-843c46afc4cb41489909bce00c9b143d.r2.dev/22.4%20-%20Ville-d'Avray/5%20Plan%20d'ensemble%20-%20Fusion%204%2B5%2B10%2B6.jpg; https://pub-843c46afc4cb41489909bce00c9b143d.r2.dev/22.8%20-%20Ville-d'Avray/6.jpg | AT97: Non | AU97: 180 €/m² = 98 460 € | AV97: Gecina
A98: =VLOOKUP(Tableau1[[#This Row],[N° Département]],Feuil1!$C$6:$E$106,3) -> Ile-de-France | B98: =VLOOKUP(Tableau1[[#This Row],[N° Département]],Feuil1!$C$6:$E$106,2) -> Val-D'Oise | C98: =LEFT(Tableau1[[#This Row],[Code Postal]],2)*1 -> 95 | D98: Rue Stéphane Charbonnier | E98: 95000 | F98: Pontoise | G98: =Tableau1[[#This Row],[Rue]]&CHAR(10)&Tableau1[[#This Row],[Code Postal]]&" - "&Tableau1[[#This Row],[Ville]] -> Rue Stéphane Charbonnier 95000 - Pontoise | H98: https://maps.app.goo.gl/zkvMgjGRX8Yn5yvJ9 | I98: Centre Ville | J98: Pied d'immeuble | K98: / | M98: / | N98: A002 | O98: 286 | P98: / | Q98: / | R98: / | S98: / | T98: =Tableau1[[#This Row],[Loyer €/m²]]*Tableau1[[#This Row],[Surface GLA]] -> 92950 | U98: =IFERROR(Tableau1[[#This Row],[Loyer annuel]]/12,"") -> 7745.8333 | V98: 325 | W98: / | X98: =Tableau1[[#This Row],[Charges €/m²]]*Tableau1[[#This Row],[Surface GLA]] -> 8866 | Y98: =Tableau1[[#This Row],[Charges annuelles]]/12 -> 738.83333 | Z98: 31 | AA98: =IFERROR(Tableau1[[#This Row],[Taxe foncière €/m²]]*Tableau1[[#This Row],[Surface GLA]],) -> 0 | AB98: / | AC98: =IFERROR(Tableau1[[#This Row],[Marketing €/m²]]*Tableau1[[#This Row],[Surface GLA]],) -> 0 | AD98: / | AE98: =IFERROR(Tableau1[[#This Row],[Loyer annuel]]+Tableau1[[#This Row],[Charges annuelles]]+Tableau1[[#This Row],[Taxe foncière]]+Tableau1[[#This Row],[Marketing]],"") -> 101816 | AF98: ="3 mois = "&TEXT(ROUND(3/12*T98,0),"### ### ##0 €") -> 3 mois = 23 238 € | AG98: / | AH98: / | AI98: Brut de béton | AJ98: A étudier | AK98: Chaude et froide | AL98: Franprix, épicerie, restaurant, crèche | AM98: Quartier neuf résidentiel à côté de la gare de Pontoise | AO98: 30% du loyer facial avec un minimum de 15 000 € HT | AP98: 49.047425 | AQ98: 2.094475 | AR98: 23.1 | AS98: https://pub-843c46afc4cb41489909bce00c9b143d.r2.dev/23.1%20-%20Pontoise/1%20Vue%20d'ensemble.jpg; https://pub-843c46afc4cb41489909bce00c9b143d.r2.dev/23.1%20-%20Pontoise/2.jpg; https://pub-843c46afc4cb41489909bce00c9b143d.r2.dev/23.1%20-%20Pontoise/3.jpg; https://pub-843c46afc4cb41489909bce00c9b143d.r2.dev/23.1%20-%20Pontoise/4%20Plan.jpg | AT98: Oui | AU98: 275 €/m² | AV98: Altixia
A99: =VLOOKUP(Tableau1[[#This Row],[N° Département]],Feuil1!$C$6:$E$106,3) -> Ile-de-France | B99: =VLOOKUP(Tableau1[[#This Row],[N° Département]],Feuil1!$C$6:$E$106,2) -> Val-D'Oise | C99: =LEFT(Tableau1[[#This Row],[Code Postal]],2)*1 -> 95 | D99: Rue Stéphane Charbonnier | E99: 95000 | F99: Pontoise | G99: =Tableau1[[#This Row],[Rue]]&CHAR(10)&Tableau1[[#This Row],[Code Postal]]&" - "&Tableau1[[#This Row],[Ville]] -> Rue Stéphane Charbonnier 95000 - Pontoise | H99: https://maps.app.goo.gl/v7DEsxhAawsjJmEcA | I99: Centre Ville | J99: Pied d'immeuble | K99: / | M99: / | N99: B001 | O99: 84 | P99: / | Q99: / | R99: / | S99: / | T99: =Tableau1[[#This Row],[Loyer €/m²]]*Tableau1[[#This Row],[Surface GLA]] -> 29400 | U99: =IFERROR(Tableau1[[#This Row],[Loyer annuel]]/12,"") -> 2450 | V99: 350 | W99: / | X99: =Tableau1[[#This Row],[Charges €/m²]]*Tableau1[[#This Row],[Surface GLA]] -> 1680 | Y99: =Tableau1[[#This Row],[Charges annuelles]]/12 -> 140 | Z99: 20 | AA99: =IFERROR(Tableau1[[#This Row],[Taxe foncière €/m²]]*Tableau1[[#This Row],[Surface GLA]],) -> 0 | AB99: / | AC99: =IFERROR(Tableau1[[#This Row],[Marketing €/m²]]*Tableau1[[#This Row],[Surface GLA]],) -> 0 | AD99: / | AE99: =IFERROR(Tableau1[[#This Row],[Loyer annuel]]+Tableau1[[#This Row],[Charges annuelles]]+Tableau1[[#This Row],[Taxe foncière]]+Tableau1[[#This Row],[Marketing]],"") -> 31080 | AF99: ="3 mois = "&TEXT(ROUND(3/12*T99,0),"### ### ##0 €") -> 3 mois = 7 350 € | AG99: / | AH99: / | AI99: Brut de béton | AJ99: A étudier | AK99: Chaude et froide | AL99: Franprix, épicerie, restaurant, crèche | AM99: Quartier neuf résidentiel à côté de la gare de Pontoise | AO99: 30% du loyer facial avec un minimum de 15 000 € HT | AP99: 49.047541 | AQ99: 2.094068 | AR99: 23.2 | AS99: https://pub-843c46afc4cb41489909bce00c9b143d.r2.dev/23.1%20-%20Pontoise/1%20Vue%20d'ensemble.jpg; https://pub-843c46afc4cb41489909bce00c9b143d.r2.dev/23.2%20-%20Pontoise/2.jpg; https://pub-843c46afc4cb41489909bce00c9b143d.r2.dev/23.2%20-%20Pontoise/3.jpg; https://pub-843c46afc4cb41489909bce00c9b143d.r2.dev/23.2%20-%20Pontoise/4%20Plan.jpg | AT99: Non | AU99: 300 €/m² | AV99: Altixia
